Workbook
Name Project_Status: Lookups!$A$5:$A$9
Name Project_Phase: Lookups!$B$5:$B$15
Name Room_Type: Lookups!$C$5:$C$22
Name Room_Status: Lookups!$D$5:$D$9
Name Design_Style: Lookups!$E$5:$E$14
Name Design_Item: Lookups!$F$5:$F$17
Name Budget_Category: Lookups!$G$5:$G$14
Name Expense_Status: Lookups!$H$5:$H$8
Name Payment_Method: Lookups!$I$5:$I$10
Name Trade: Lookups!$J$5:$J$21
Name Task_Status: Lookups!$K$5:$K$10
Name Priority: Lookups!$L$5:$L$8
Name Material_Status: Lookups!$M$5:$M$13
Name Doc_Category: Lookups!$N$5:$N$18
Name Role: Lookups!$O$5:$O$13
Name Quote_Status: Lookups!$P$5:$P$10
Name Job_Status: Lookups!$Q$5:$Q$10
Name Insp_Result: Lookups!$R$5:$R$8
Name Payment_Status: Lookups!$S$5:$S$9
Name CO_Status: Lookups!$T$5:$T$9
Name Permit_Status: Lookups!$U$5:$U$10
Name Maint_Status: Lookups!$V$5:$V$9
Name Insight_Severity: Lookups!$W$5:$W$8
Name Insight_Status: Lookups!$X$5:$X$9
Name Channel: Lookups!$Y$5:$Y$11
Name Currency: Lookups!$Z$5:$Z$11
Name Language: Lookups!$AA$5:$AA$11
Name Property_Type: Lookups!$AB$5:$AB$10
Name ActiveProject: Settings!$B$9
Name HomeownerName: Settings!$B$8
Name CurSym: Settings!$B$12
Name ContingencyPct: Settings!$B$14
Name AsOfDate: Settings!$B$16
Name ContingencyFloor: Settings!$B$22
Name OverrunAlert: Settings!$B$23
Name CompanyName: Settings!$B$5
Name TaxRate: Settings!$B$18

Sheet Start Here
A1: START HERE
A2: Read this first · then open Dashboard · upload this file to Google Drive to get a Google Sheet
A4: Novality Store · Home Renovation Management System
A5: A digital twin of the home: every room, material, contractor, expense, document, task, photo, warranty and maintenance activity is connected to a place in the house. This workbook is the complete operating system for a renovation — from first idea through handover and aftercare.
A8: How to use (Excel) | F8: How to use (Google Sheets)
A9: 1. Enable editing / calculation (Formulas → Automatic). | F9: 1. Upload this .xlsx to Google Drive → Open with Google Sheets.
A10: 2. Open Settings. Set Active Project ID (PRJ-001 or PRJ-002). | F10: 2. File → Save as Google Sheets (keeps formulas, colors, charts).
A11: 3. Work in the yellow-ivory input cells. Grey-sand cells are formulas — don't type over them. | F11: 3. Extensions → Apps Script → paste google_apps_script/Code.gs.
A12: 4. Add rows above the last data row; copy the formula cells down. | F12: 4. Reload the sheet. A “Novality Store” menu appears.
A13: 5. Use column filters on every register. Status columns are color-coded. | F13: 5. Formula cells stay locked in Excel. Google Sheets: Data → Protect sheets.
A14: 6. Dashboard, Finance and Admin recalculate from the registers. | F14: 6. Share with contractors as Commenter or custom-filtered views.
A15: 7. File → Print uses tabloid landscape and branded headers. | F15: 7. Optional: File → Download to keep an Excel archive.
A18: Color system
A19: Primary #16352F Forest | C19: Secondary #E8DDCB Sand | E19: Accent #C86B4A Terracotta | G19: Background #F8F6F1 Ivory
A20: Success #719B7A Sage | C20: Warning #D99A3D Amber | E20: Danger #C75C5C Muted red | G20: Formula cells (do not type)
A22: Module index (click to jump)
A23: Sheet | B23: What it holds | F23: Sheet | G23: What it holds
A24: Dashboard | B24: Homeowner overview, KPIs, alerts, next tasks | F24: Messages | G24: Threaded communication log
A25: Projects | B25: Multi-project register with live spend | F25: Inventory | G25: Home contents for insurance
A26: Rooms | B26: Spaces, measurements, budgets, photos | F26: Maintenance | G26: Aftercare hub + reminders
A27: Design Studio | B27: Mood boards, palettes, 2D/3D, AI concepts | F27: Inspections | G27: City and independent
A28: AI Insights | B28: Assistant recommendations and savings | F28: Payments | G28: Draws and aging
A29: Budget | B29: Category + room plan vs actual | F29: Change Orders | G29: Scope / cost / schedule deltas
A30: Expenses | B30: Transaction log (Planned / Committed / Paid) | F30: Permits | G30: Authorities and expirations
A31: Finance | B31: Charts, monthly cash, smart alerts | F31: Warranties | G31: Labor and product coverage
A32: Contractors | B32: Profiles + Quality / On-time / Budget / Comms score | F32: Calendar | G32: Visits and deadlines
A33: Quotes | B33: Bid comparison and award | F33: Notifications | G33: Alert queue
A34: Jobs | B34: Assignments, milestones, balances | F34: Users | G34: Nine roles
... A40: Documents | B40: Project vault + expiry alerts | F40: Roles & Permissions | G40: Matrix of who can do what
A43: Sample story already loaded
A44: Alex Rivera is renovating 1847 Maplewood Drive, Portland (PRJ-001, $85,000, 72% complete, Construction phase). Kitchen boxes are going in this week; primary bath is on punch list after an AI-led swap from marble to porcelain (about 18% saved on that category). Contingency has dipped under 10%, so the exterior water feature is on hold. A second property — the Columbia Gorge cabin bath (PRJ-002) — is in design so you can see multi-property. Today in the file is 24 August 2026. Change Settings → Today if you reopen this later.
A49: Roles in this system
A50: Homeowner | B50: Admin | C50: Project Manager | D50: Interior Designer | E50: Contractor | F50: Subcontractor | G50: Supplier | H50: Inspector | I50: Accountant

Sheet Dashboard
A1: DASHBOARD
A2: Homeowner overview · live formulas · switch Active Project on Settings
A4: ="Good day, " & HomeownerName & " · " & TEXT(AsOfDate,"DDDD, D MMMM YYYY")
A5: ="YOUR RENOVATION · " & IFERROR(INDEX(Projects!C:C,MATCH(ActiveProject,Projects!A:A,0)),ActiveProject) & " · " & IFERROR(INDEX(Projects!F:F,MATCH(ActiveProject,Projects!A:A,0)),"")
A7: PROGRESS | E7: PHASE | H7: BUDGET | K7: SPENT
A8: =IFERROR(INDEX(Projects!P:P,MATCH(ActiveProject,Projects!A:A,0)),0) | E8: =IFERROR(INDEX(Projects!F:F,MATCH(ActiveProject,Projects!A:A,0)),"—") | H8: =IFERROR(INDEX(Projects!J:J,MATCH(ActiveProject,Projects!A:A,0)),0) | K8: =IFERROR(SUMIFS(Expenses!H:H,Expenses!C:C,ActiveProject,Expenses!J:J,"Paid"),0)
A9: =REPT("█",ROUND(A8*20,0))&REPT("░",20-ROUND(A8*20,0)) | E9: =IFERROR(INDEX(Projects!E:E,MATCH(ActiveProject,Projects!A:A,0)),"") | H9: Planned | K9: Paid to date
A11: COMMITTED | D11: REMAINING | G11: OPEN TASKS | J11: OVERDUE
A12: =IFERROR(SUMIFS(Expenses!H:H,Expenses!C:C,ActiveProject,Expenses!J:J,"Committed"),0) | D12: =H8-K8-A12 | G12: =COUNTIFS(Tasks!B:B,ActiveProject,Tasks!H:H,"<>Completed") | J12: =COUNTIFS(Tasks!B:B,ActiveProject,Tasks!H:H,"<>Completed",Tasks!K:K,"<"&AsOfDate)
A13: Not yet paid | D13: Still available | G13: Not completed | J13: Past deadline
A15: ATTENTION | H15: NEXT UP
A16: =IF((K8+A12)>H8,"⚠ Project is over the planned budget.","") | H16: When | I16: Task | J16: Room | K16: Owner | L16: Status
A17: =IF(Finance!D10<H8*ContingencyFloor,"🔴 Contingency has fallen below 10%. Freeze non-critical extras.","") | H17: =IFERROR(FILTER(Tasks!K5:K200,(Tasks!B5:B200=ActiveProject)*(Tasks!H5:H200<>"Completed")),"") | I17: =IFERROR(FILTER(Tasks!D5:D200,(Tasks!B5:B200=ActiveProject)*(Tasks!H5:H200<>"Completed")),"") | J17: =IFERROR(FILTER(Tasks!C5:C200,(Tasks!B5:B200=ActiveProject)*(Tasks!H5:H200<>"Completed")),"") | K17: =IFERROR(FILTER(Tasks!F5:F200,(Tasks!B5:B200=ActiveProject)*(Tasks!H5:H200<>"Completed")),"") | L17: =IFERROR(FILTER(Tasks!H5:H200,(Tasks!B5:B200=ActiveProject)*(Tasks!H5:H200<>"Completed")),"")
A18: =IF(COUNTIFS(Tasks!B:B,ActiveProject,Tasks!Q:Q,"Overdue")>0,"⚠ "&COUNTIFS(Tasks!B:B,ActiveProject,Tasks!Q:Q,"Overdue")&" overdue task(s).","")
A19: =IF(COUNTIFS(Materials!B:B,ActiveProject,Materials!P:P,"Backordered")>0,"⚠ Material backorder: "&COUNTIFS(Materials!B:B,ActiveProject,Materials!P:P,"Backordered")&" line(s).","")
A20: =IF(COUNTIFS(Documents!B:B,ActiveProject,Documents!N:N,"Expiring")+COUNTIFS(Documents!B:B,ActiveProject,Documents!N:N,"Expired")>0,"⚠ Document expiry needs attention.","")
A21: =IF(COUNTIFS('Change Orders'!B:B,ActiveProject,'Change Orders'!I:I,"Submitted")>0,"⚠ Change order awaiting approval.","")
A22: =IF(COUNTA(A16:A21)=0,"🟢 Nothing urgent. You're clear for the week.","")
A24: RECENT EXPENSES | H24: ROOMS
A25: Date | B25: Vendor | C25: Description | D25: Amount | E25: Status | H25: Room | I25: Status | J25: Budget | K25: Spent | L25: %
A26: =IFERROR(FILTER(Expenses!B5:B200,Expenses!C5:C200=ActiveProject),"") | B26: =IFERROR(FILTER(Expenses!F5:F200,Expenses!C5:C200=ActiveProject),"") | C26: =IFERROR(FILTER(Expenses!G5:G200,Expenses!C5:C200=ActiveProject),"") | D26: =IFERROR(FILTER(Expenses!H5:H200,Expenses!C5:C200=ActiveProject),"") | E26: =IFERROR(FILTER(Expenses!J5:J200,Expenses!C5:C200=ActiveProject),"") | H26: Kitchen | I26: =IFERROR(INDEX(Rooms!J:J,MATCH("RM-01",Rooms!A:A,0)),"") | J26: =IFERROR(INDEX(Rooms!K:K,MATCH("RM-01",Rooms!A:A,0)),0) | K26: =IFERROR(INDEX(Rooms!R:R,MATCH("RM-01",Rooms!A:A,0)),0) | L26: =IF(J26=0,"",K26/J26)
H27: Living Room | I27: =IFERROR(INDEX(Rooms!J:J,MATCH("RM-02",Rooms!A:A,0)),"") | J27: =IFERROR(INDEX(Rooms!K:K,MATCH("RM-02",Rooms!A:A,0)),0) | K27: =IFERROR(INDEX(Rooms!R:R,MATCH("RM-02",Rooms!A:A,0)),0) | L27: =IF(J27=0,"",K27/J27)
H28: Primary Bathroom | I28: =IFERROR(INDEX(Rooms!J:J,MATCH("RM-03",Rooms!A:A,0)),"") | J28: =IFERROR(INDEX(Rooms!K:K,MATCH("RM-03",Rooms!A:A,0)),0) | K28: =IFERROR(INDEX(Rooms!R:R,MATCH("RM-03",Rooms!A:A,0)),0) | L28: =IF(J28=0,"",K28/J28)
H29: Guest Bedroom | I29: =IFERROR(INDEX(Rooms!J:J,MATCH("RM-04",Rooms!A:A,0)),"") | J29: =IFERROR(INDEX(Rooms!K:K,MATCH("RM-04",Rooms!A:A,0)),0) | K29: =IFERROR(INDEX(Rooms!R:R,MATCH("RM-04",Rooms!A:A,0)),0) | L29: =IF(J29=0,"",K29/J29)
H30: Dining Room | I30: =IFERROR(INDEX(Rooms!J:J,MATCH("RM-05",Rooms!A:A,0)),"") | J30: =IFERROR(INDEX(Rooms!K:K,MATCH("RM-05",Rooms!A:A,0)),0) | K30: =IFERROR(INDEX(Rooms!R:R,MATCH("RM-05",Rooms!A:A,0)),0) | L30: =IF(J30=0,"",K30/J30)
H31: Exterior / Garden | I31: =IFERROR(INDEX(Rooms!J:J,MATCH("RM-06",Rooms!A:A,0)),"") | J31: =IFERROR(INDEX(Rooms!K:K,MATCH("RM-06",Rooms!A:A,0)),0) | K31: =IFERROR(INDEX(Rooms!R:R,MATCH("RM-06",Rooms!A:A,0)),0) | L31: =IF(J31=0,"",K31/J31)
H32: Laundry | I32: =IFERROR(INDEX(Rooms!J:J,MATCH("RM-07",Rooms!A:A,0)),"") | J32: =IFERROR(INDEX(Rooms!K:K,MATCH("RM-07",Rooms!A:A,0)),0) | K32: =IFERROR(INDEX(Rooms!R:R,MATCH("RM-07",Rooms!A:A,0)),0) | L32: =IF(J32=0,"",K32/J32)
H33: Entry / Foyer | I33: =IFERROR(INDEX(Rooms!J:J,MATCH("RM-08",Rooms!A:A,0)),"") | J33: =IFERROR(INDEX(Rooms!K:K,MATCH("RM-08",Rooms!A:A,0)),0) | K33: =IFERROR(INDEX(Rooms!R:R,MATCH("RM-08",Rooms!A:A,0)),0) | L33: =IF(J33=0,"",K33/J33)
A36: UPCOMING CONTRACTOR VISITS | H36: QUICK ACTIONS (use the Novality Store menu in Google Sheets)
A37: Date | B37: Event | C37: Owner | D37: Status | H37: + Expense
A38: =IFERROR(FILTER(Calendar!A5:A80,Calendar!A5:A80>=AsOfDate),"") | B38: =IFERROR(FILTER(Calendar!C5:C80,Calendar!A5:A80>=AsOfDate),"") | C38: =IFERROR(FILTER(Calendar!F5:F80,Calendar!A5:A80>=AsOfDate),"") | D38: =IFERROR(FILTER(Calendar!G5:G80,Calendar!A5:A80>=AsOfDate),"") | H38: + Task
H39: Upload photo note
H40: Message contractor
H41: Approve change order
H42: Generate shopping list
A45: AI INSIGHT
A46: =IFERROR(INDEX('AI Insights'!G:G,MATCH(1,('AI Insights'!C:C=ActiveProject)*(('AI Insights'!J:J="New")+('AI Insights'!J:J="In Progress")),0)),"No open AI insights.")
A49: =IFERROR("Recommendation: "&INDEX('AI Insights'!H:H,MATCH(1,('AI Insights'!C:C=ActiveProject)*(('AI Insights'!J:J="New")+('AI Insights'!J:J="In Progress")),0)),"")
A52: NAVIGATION
A53: Projects | C53: Rooms | E53: Design | G53: Budget | I53: Team | K53: Materials
A54: Tasks | C54: Messages | E54: Documents | G54: Home | I54: Maint. | K54: Admin

Sheet Projects
A1: PROJECTS
A2: All renovation projects · spent/committed roll up from Expenses
A4: Project ID | B4: Property ID | C4: Name | D4: Type | E4: Status | F4: Phase | G4: Start | H4: Target End | I4: Actual End | J4: Budget | K4: Homeowner ID | L4: PM ID | M4: Designer ID | N4: Homeowner Name | O4: Address | P4: Progress | Q4: Notes | R4: Spent | S4: Committed | T4: Remaining | U4: Health
A5: PRJ-001 | B5: PROP-001 | C5: Maplewood Whole-Home Refresh | D5: Whole Home | E5: Active | F5: Construction | G5: 46082 | H5: 46341 | J5: 85000 | K5: HO-001 | L5: PM-001 | M5: DS-001 | N5: Alex Rivera | O5: 1847 Maplewood Drive, Portland, OR | P5: 0.72 | Q5: Kitchen, primary bath, living, guest bedroom, exterior paint, garden path. | R5: =IF($A5="","",SUMIFS(Expenses!$H:$H,Expenses!$C:$C,$A5,Expenses!$J:$J,"Paid")) | S5: =IF($A5="","",SUMIFS(Expenses!$H:$H,Expenses!$C:$C,$A5,Expenses!$J:$J,"Committed")) | T5: =IF($A5="","",$J5-$R5-$S5) | U5: =IF($A5="","",IF($R5+$S5>$J5*(1+OverrunAlert),"Over",IF($R5+$S5>$J5,"Watch","On Track")))
A6: PRJ-002 | B6: PROP-002 | C6: Gorge Cabin Bath Refresh | D6: Bathroom | E6: Planning | F6: Design | G6: 46296 | H6: 46371 | J6: 18500 | K6: HO-001 | L6: PM-001 | M6: DS-001 | N6: Alex Rivera | O6: 88 Ridge Trail, Hood River, OR | P6: 0.12 | Q6: Single bath + vanity lighting. Starts after Maplewood handover. | R6: =IF($A6="","",SUMIFS(Expenses!$H:$H,Expenses!$C:$C,$A6,Expenses!$J:$J,"Paid")) | S6: =IF($A6="","",SUMIFS(Expenses!$H:$H,Expenses!$C:$C,$A6,Expenses!$J:$J,"Committed")) | T6: =IF($A6="","",$J6-$R6-$S6) | U6: =IF($A6="","",IF($R6+$S6>$J6*(1+OverrunAlert),"Over",IF($R6+$S6>$J6,"Watch","On Track")))

Sheet Rooms
A1: ROOMS
A2: Every space is a node in the digital twin
A4: Room ID | B4: Project ID | C4: Room Name | D4: Type | E4: Floor | F4: Length (ft) | G4: Width (ft) | H4: Height (ft) | I4: Condition | J4: Status | K4: Budget | L4: Contractor ID | M4: Design Style | N4: Before Photos | O4: After Photos | P4: Notes | Q4: Area (sf) | R4: Spent | S4: Committed | T4: Remaining | U4: Budget used
A5: RM-01 | B5: PRJ-001 | C5: Kitchen | D5: Kitchen | E5: 1 | F5: 16 | G5: 12.5 | H5: 9 | I5: Fair | J5: In Progress | K5: 32000 | L5: CTR-001 | M5: Modern | N5: drive/photos/kitchen-before | O5: drive/photos/kitchen-wip | P5: Load-bearing wall stays. Island added. | Q5: =IF($A5="","",ROUND($F5*$G5,1)) | R5: =IF($A5="","",SUMIFS(Expenses!$H:$H,Expenses!$D:$D,$A5,Expenses!$J:$J,"Paid")) | S5: =IF($A5="","",SUMIFS(Expenses!$H:$H,Expenses!$D:$D,$A5,Expenses!$J:$J,"Committed")) | T5: =IF($A5="","",$K5-$R5-$S5) | U5: =IF(OR($A5="",$K5=0),"",($R5+$S5)/$K5)
A6: RM-02 | B6: PRJ-001 | C6: Living Room | D6: Living Room | E6: 1 | F6: 20 | G6: 15 | H6: 9.5 | I6: Good | J6: In Progress | K6: 12500 | L6: CTR-006 | M6: Scandinavian | N6: drive/photos/living-before | P6: White oak floors continue from kitchen. | Q6: =IF($A6="","",ROUND($F6*$G6,1)) | R6: =IF($A6="","",SUMIFS(Expenses!$H:$H,Expenses!$D:$D,$A6,Expenses!$J:$J,"Paid")) | S6: =IF($A6="","",SUMIFS(Expenses!$H:$H,Expenses!$D:$D,$A6,Expenses!$J:$J,"Committed")) | T6: =IF($A6="","",$K6-$R6-$S6) | U6: =IF(OR($A6="",$K6=0),"",($R6+$S6)/$K6)
A7: RM-03 | B7: PRJ-001 | C7: Primary Bathroom | D7: Primary Bathroom | E7: 2 | F7: 10 | G7: 8 | H7: 8.5 | I7: Poor | J7: Punch List | K7: 18500 | L7: CTR-004 | M7: Luxury | N7: drive/photos/bath-before | O7: drive/photos/bath-after-draft | P7: Heated floor. Porcelain in lieu of marble. | Q7: =IF($A7="","",ROUND($F7*$G7,1)) | R7: =IF($A7="","",SUMIFS(Expenses!$H:$H,Expenses!$D:$D,$A7,Expenses!$J:$J,"Paid")) | S7: =IF($A7="","",SUMIFS(Expenses!$H:$H,Expenses!$D:$D,$A7,Expenses!$J:$J,"Committed")) | T7: =IF($A7="","",$K7-$R7-$S7) | U7: =IF(OR($A7="",$K7=0),"",($R7+$S7)/$K7)
A8: RM-04 | B8: PRJ-001 | C8: Guest Bedroom | D8: Bedroom | E8: 2 | F8: 12 | G8: 11 | H8: 8.5 | I8: Fair | J8: Design | K8: 6200 | L8: CTR-005 | M8: Minimal | N8: drive/photos/guest-before | P8: Paint, lighting, built-in wardrobe. | Q8: =IF($A8="","",ROUND($F8*$G8,1)) | R8: =IF($A8="","",SUMIFS(Expenses!$H:$H,Expenses!$D:$D,$A8,Expenses!$J:$J,"Paid")) | S8: =IF($A8="","",SUMIFS(Expenses!$H:$H,Expenses!$D:$D,$A8,Expenses!$J:$J,"Committed")) | T8: =IF($A8="","",$K8-$R8-$S8) | U8: =IF(OR($A8="",$K8=0),"",($R8+$S8)/$K8)
A9: RM-05 | B9: PRJ-001 | C9: Dining Room | D9: Dining Room | E9: 1 | F9: 13 | G9: 11 | H9: 9.5 | I9: Good | J9: In Progress | K9: 4800 | L9: CTR-005 | M9: Transitional | N9: drive/photos/dining-before | P9: Sconce pair + plaster repair. | Q9: =IF($A9="","",ROUND($F9*$G9,1)) | R9: =IF($A9="","",SUMIFS(Expenses!$H:$H,Expenses!$D:$D,$A9,Expenses!$J:$J,"Paid")) | S9: =IF($A9="","",SUMIFS(Expenses!$H:$H,Expenses!$D:$D,$A9,Expenses!$J:$J,"Committed")) | T9: =IF($A9="","",$K9-$R9-$S9) | U9: =IF(OR($A9="",$K9=0),"",($R9+$S9)/$K9)
A10: RM-06 | B10: PRJ-001 | C10: Exterior / Garden | D10: Exterior | E10: 0 | F10: 40 | G10: 22 | H10: 0 | I10: Fair | J10: Not Started | K10: 7400 | L10: CTR-010 | M10: Traditional | N10: drive/photos/exterior-before | P10: Front path, porch stain, lighting. | Q10: =IF($A10="","",ROUND($F10*$G10,1)) | R10: =IF($A10="","",SUMIFS(Expenses!$H:$H,Expenses!$D:$D,$A10,Expenses!$J:$J,"Paid")) | S10: =IF($A10="","",SUMIFS(Expenses!$H:$H,Expenses!$D:$D,$A10,Expenses!$J:$J,"Committed")) | T10: =IF($A10="","",$K10-$R10-$S10) | U10: =IF(OR($A10="",$K10=0),"",($R10+$S10)/$K10)
A11: RM-07 | B11: PRJ-001 | C11: Laundry | D11: Laundry | E11: 1 | F11: 8 | G11: 6 | H11: 8.5 | I11: Fair | J11: Complete | K11: 2100 | L11: CTR-003 | M11: Minimal | N11: drive/photos/laundry-before | O11: drive/photos/laundry-after | P11: Utility sink and tile splash. | Q11: =IF($A11="","",ROUND($F11*$G11,1)) | R11: =IF($A11="","",SUMIFS(Expenses!$H:$H,Expenses!$D:$D,$A11,Expenses!$J:$J,"Paid")) | S11: =IF($A11="","",SUMIFS(Expenses!$H:$H,Expenses!$D:$D,$A11,Expenses!$J:$J,"Committed")) | T11: =IF($A11="","",$K11-$R11-$S11) | U11: =IF(OR($A11="",$K11=0),"",($R11+$S11)/$K11)
A12: RM-08 | B12: PRJ-001 | C12: Entry / Foyer | D12: Entry / Foyer | E12: 1 | F12: 8 | G12: 7 | H12: 9.5 | I12: Good | J12: In Progress | K12: 1500 | L12: CTR-005 | M12: Transitional | N12: drive/photos/entry-before | P12: Bench, hook rail, paint. | Q12: =IF($A12="","",ROUND($F12*$G12,1)) | R12: =IF($A12="","",SUMIFS(Expenses!$H:$H,Expenses!$D:$D,$A12,Expenses!$J:$J,"Paid")) | S12: =IF($A12="","",SUMIFS(Expenses!$H:$H,Expenses!$D:$D,$A12,Expenses!$J:$J,"Committed")) | T12: =IF($A12="","",$K12-$R12-$S12) | U12: =IF(OR($A12="",$K12=0),"",($R12+$S12)/$K12)
A13: RM-09 | B13: PRJ-002 | C13: Cabin Bathroom | D13: Bathroom | E13: 1 | F13: 8 | G13: 6.5 | H13: 8 | I13: Poor | J13: Design | K13: 18500 | L13: CTR-004 | M13: Scandinavian | N13: drive/photos/cabin-bath-before | P13: Full gut. Starts October. | Q13: =IF($A13="","",ROUND($F13*$G13,1)) | R13: =IF($A13="","",SUMIFS(Expenses!$H:$H,Expenses!$D:$D,$A13,Expenses!$J:$J,"Paid")) | S13: =IF($A13="","",SUMIFS(Expenses!$H:$H,Expenses!$D:$D,$A13,Expenses!$J:$J,"Committed")) | T13: =IF($A13="","",$K13-$R13-$S13) | U13: =IF(OR($A13="",$K13=0),"",($R13+$S13)/$K13)

Sheet Design Studio
A1: DESIGN STUDIO
A2: Mood boards, palettes, materials, 2D/3D, AI concepts · style presets included
A4: Design ID | B4: Project ID | C4: Room ID | D4: Item Type | E4: Name | F4: Style | G4: Brand | H4: Color Hex | I4: Link / File | J4: Status | K4: Cost Est. | L4: AI Suggested | M4: Notes
A5: DSN-001 | B5: PRJ-001 | C5: RM-01 | D5: Mood Board | E5: Kitchen — warm modern | F5: Modern | H5: #16352F | I5: drive/mood/kitchen-01 | J5: Approved | K5: 0 | L5: No | M5: Forest + sand + terracotta. Brass hardware.
A6: DSN-002 | B6: PRJ-001 | C6: RM-01 | D6: Color Palette | E6: Kitchen palette v3 | F6: Modern | G6: Farrow & Ball | H6: #E8DDCB | I6: drive/palette/kitchen | J6: Approved | K6: 0 | L6: Yes | M6: AI suggested dropping cool gray for sand.
A7: DSN-003 | B7: PRJ-001 | C7: RM-01 | D7: Cabinetry | E7: Shaker, painted sage | F7: Modern | G7: Cascade | H7: #719B7A | I7: drive/cabs/shaker-sage | J7: Approved | K7: 14800 | L7: No | M7: Inset doors, walnut island.
A8: DSN-004 | B8: PRJ-001 | C8: RM-01 | D8: Flooring | E8: White oak 7in | F8: Scandinavian | G8: Timberline | H8: #D4C6AE | I8: drive/floor/oak | J8: Installed | K8: 4200 | L8: No | M8: Continues into living + dining.
A9: DSN-005 | B9: PRJ-001 | C9: RM-01 | D9: Lighting | E9: Aged brass pendants x3 | F9: Luxury | G9: BrightPath | H9: #C86B4A | I9: drive/light/island | J9: Ordered | K9: 890 | L9: No | M9: Dimmer on island circuit.
A10: DSN-006 | B10: PRJ-001 | C10: RM-03 | D10: Material Board | E10: Bath — porcelain in lieu of marble | F10: Luxury | G10: Heritage | H10: #F8F6F1 | I10: drive/bath/materials | J10: Approved | K10: 0 | L10: Yes | M10: AI: porcelain saves ~18% vs marble.
A11: DSN-007 | B11: PRJ-001 | C11: RM-03 | D11: AI Concept | E11: Primary bath — spa luxury | F11: Luxury | I11: drive/ai/bath-luxury | J11: Accepted | K11: 0 | L11: Yes | M11: Before/after concept set.
A12: DSN-008 | B12: PRJ-001 | C12: RM-02 | D12: Mood Board | E12: Living — Scandinavian calm | F12: Scandinavian | H12: #E8DDCB | I12: drive/mood/living | J12: Approved | K12: 0 | L12: No | M12: Linen, oak, charcoal textiles.
A13: DSN-009 | B13: PRJ-001 | C13: RM-02 | D13: Furniture | E13: Modular sofa + oak table | F13: Scandinavian | G13: Article | H13: #202522 | I13: drive/furn/living | J13: Quoted | K13: 3400 | L13: No | M13: Lead time 6 weeks — order by Sep 1.
A14: DSN-010 | B14: PRJ-001 | C14: RM-04 | D14: Color Palette | E14: Guest — clay + linen | F14: Minimal | G14: Benjamin Moore | H14: #C86B4A | I14: drive/palette/guest | J14: In Review | K14: 0 | L14: Yes | M14: Two accent options pending Alex.
A15: DSN-011 | B15: PRJ-001 | C15: RM-01 | D15: 2D Floor Plan | E15: Kitchen layout v4 | F15: Modern | G15: Luna | I15: drive/plans/kitchen-v4 | J15: Approved | K15: 0 | L15: No | M15: Island 8ft. Fridge wall flipped.
A16: DSN-012 | B16: PRJ-001 | C16: RM-01 | D16: 3D Visualization | E16: Kitchen dusk render | F16: Modern | G16: Luna | I16: drive/3d/kitchen-dusk | J16: Approved | K16: 0 | L16: Yes | M16: AI lighting study included.
A17: DSN-013 | B17: PRJ-002 | C17: RM-09 | D17: Mood Board | E17: Cabin bath — Japandi | F17: Japandi | H17: #16352F | I17: drive/mood/cabin | J17: Draft | K17: 0 | L17: Yes | M17: Cedar, plaster, black fixtures.

Sheet AI Insights
A1: AI INSIGHTS
A2: Renovation assistant · budget, materials, schedule, contractor comparison, photo analysis
A4: Insight ID | B4: Date | C4: Project ID | D4: Room ID | E4: Category | F4: Severity | G4: Insight | H4: Recommendation | I4: Est. Impact $ | J4: Status | K4: Action Taken
A5: AI-001 | B5: 46254 | C5: PRJ-001 | D5: RM-01 | E5: Budget | F5: Warning | G5: Kitchen renovation is currently 12% over the planned budget. | H5: Switch remaining stone from marble to porcelain slab on the island only; keep quartz on perimeter. | I5: 2100 | J5: Accepted | K5: Quote requested from Heritage Tile
A6: AI-002 | B6: 46252 | C6: PRJ-001 | D6: RM-03 | E6: Materials | F6: Opportunity | G6: Porcelain tile alternative identified for primary bath floor. | H6: Heritage porcelain (SKU HT-8841) matches the approved palette and saves ~18% versus marble. | I6: 1640 | J6: Resolved | K6: Material swapped. Installed.
A7: AI-003 | B7: 46256 | C7: PRJ-001 | D7: RM-01 | E7: Schedule | F7: Warning | G7: Cabinet installation is on the critical path and hardware is still in transit. | H7: Confirm hardware ETA. If later than Aug 27, install doors without pulls and return for hardware day. | I7: 0 | J7: In Progress | K7: Maya tracking shipment
A8: AI-004 | B8: 46249 | C8: PRJ-001 | E8: Contractor | F8: Info | G8: Three lighting bids received. Spread is 22%. | H8: BrightPath is mid-price with the highest communication score. Accept unless value-engineering fixtures. | I8: 340 | J8: Accepted | K8: BrightPath awarded
A9: AI-005 | B9: 46257 | C9: PRJ-001 | D9: RM-06 | E9: Risk | F9: Critical | G9: Project contingency has fallen to 9.4%, below the 10% threshold. | H9: Freeze non-critical exterior extras (water feature) until kitchen close-out. | I9: 1800 | J9: New
A10: AI-006 | B10: 46244 | C10: PRJ-001 | D10: RM-02 | E10: Design | F10: Opportunity | G10: Room photo analysis: north-facing living room reads cool and dim after 4pm. | H10: Specify 2700K lamps, add floor lamp at north corner, keep walls in Warm Sand not cool gray. | I10: 0 | J10: Resolved | K10: Palette updated
A11: AI-007 | B11: 46255 | C11: PRJ-001 | E11: Procurement | F11: Warning | G11: White oak stair nosing is backordered 11 days. | H11: Use matching leftover plank with site-cut nosing, or delay living-room furniture delivery. | I11: 0 | J11: Accepted | K11: Site-cut nosing approved
A12: AI-008 | B12: 46258 | C12: PRJ-001 | E12: Prediction | F12: Info | G12: Likely completion date given current float: 12 Nov 2026 (3 days ahead of target). | H12: Protect flooring cure time. Do not accelerate furniture move-in before Oct 20. | I12: 0 | J12: New

Sheet Budget
A1: BUDGET
A2: Category + room budgets · spent/committed live from Expenses
A4: Line ID | B4: Project ID | C4: Room ID | D4: Category | E4: Subcategory | F4: Planned | G4: Spent (Paid) | H4: Committed | I4: Remaining | J4: Variance | K4: Variance % | L4: Alert
A5: BL-001 | B5: PRJ-001 | C5: RM-01 | D5: Materials | E5: Cabinetry & hardware | F5: 14800 | G5: =IF($A5="","",IF($C5="",SUMIFS(Expenses!$H:$H,Expenses!$C:$C,$B5,Expenses!$E:$E,$D5,Expenses!$J:$J,"Paid"),SUMIFS(Expenses!$H:$H,Expenses!$C:$C,$B5,Expenses!$D:$D,$C5,Expenses!$E:$E,$D5,Expenses!$J:$J,"Paid"))) | H5: =IF($A5="","",IF($C5="",SUMIFS(Expenses!$H:$H,Expenses!$C:$C,$B5,Expenses!$E:$E,$D5,Expenses!$J:$J,"Committed"),SUMIFS(Expenses!$H:$H,Expenses!$C:$C,$B5,Expenses!$D:$D,$C5,Expenses!$E:$E,$D5,Expenses!$J:$J,"Committed"))) | I5: =IF($A5="","",$F5-$G5-$H5) | J5: =IF($A5="","",$F5-($G5+$H5)) | K5: =IF(OR($A5="",$F5=0),"",($G5+$H5-$F5)/$F5) | L5: =IF($A5="","",IF($F5=0,"",IF(($G5+$H5)>$F5*(1+OverrunAlert),"Over",IF(($G5+$H5)>$F5,"Watch",IF(($G5+$H5)<$F5*0.85,"Under","On Track")))))
A6: BL-002 | B6: PRJ-001 | C6: RM-01 | D6: Materials | E6: Counters & backsplash | F6: 6200 | G6: =IF($A6="","",IF($C6="",SUMIFS(Expenses!$H:$H,Expenses!$C:$C,$B6,Expenses!$E:$E,$D6,Expenses!$J:$J,"Paid"),SUMIFS(Expenses!$H:$H,Expenses!$C:$C,$B6,Expenses!$D:$D,$C6,Expenses!$E:$E,$D6,Expenses!$J:$J,"Paid"))) | H6: =IF($A6="","",IF($C6="",SUMIFS(Expenses!$H:$H,Expenses!$C:$C,$B6,Expenses!$E:$E,$D6,Expenses!$J:$J,"Committed"),SUMIFS(Expenses!$H:$H,Expenses!$C:$C,$B6,Expenses!$D:$D,$C6,Expenses!$E:$E,$D6,Expenses!$J:$J,"Committed"))) | I6: =IF($A6="","",$F6-$G6-$H6) | J6: =IF($A6="","",$F6-($G6+$H6)) | K6: =IF(OR($A6="",$F6=0),"",($G6+$H6-$F6)/$F6) | L6: =IF($A6="","",IF($F6=0,"",IF(($G6+$H6)>$F6*(1+OverrunAlert),"Over",IF(($G6+$H6)>$F6,"Watch",IF(($G6+$H6)<$F6*0.85,"Under","On Track")))))
A7: BL-003 | B7: PRJ-001 | C7: RM-01 | D7: Materials | E7: Appliances | F7: 5400 | G7: =IF($A7="","",IF($C7="",SUMIFS(Expenses!$H:$H,Expenses!$C:$C,$B7,Expenses!$E:$E,$D7,Expenses!$J:$J,"Paid"),SUMIFS(Expenses!$H:$H,Expenses!$C:$C,$B7,Expenses!$D:$D,$C7,Expenses!$E:$E,$D7,Expenses!$J:$J,"Paid"))) | H7: =IF($A7="","",IF($C7="",SUMIFS(Expenses!$H:$H,Expenses!$C:$C,$B7,Expenses!$E:$E,$D7,Expenses!$J:$J,"Committed"),SUMIFS(Expenses!$H:$H,Expenses!$C:$C,$B7,Expenses!$D:$D,$C7,Expenses!$E:$E,$D7,Expenses!$J:$J,"Committed"))) | I7: =IF($A7="","",$F7-$G7-$H7) | J7: =IF($A7="","",$F7-($G7+$H7)) | K7: =IF(OR($A7="",$F7=0),"",($G7+$H7-$F7)/$F7) | L7: =IF($A7="","",IF($F7=0,"",IF(($G7+$H7)>$F7*(1+OverrunAlert),"Over",IF(($G7+$H7)>$F7,"Watch",IF(($G7+$H7)<$F7*0.85,"Under","On Track")))))
A8: BL-004 | B8: PRJ-001 | C8: RM-01 | D8: Labor | E8: Cabinet install + finish carpentry | F8: 3600 | G8: =IF($A8="","",IF($C8="",SUMIFS(Expenses!$H:$H,Expenses!$C:$C,$B8,Expenses!$E:$E,$D8,Expenses!$J:$J,"Paid"),SUMIFS(Expenses!$H:$H,Expenses!$C:$C,$B8,Expenses!$D:$D,$C8,Expenses!$E:$E,$D8,Expenses!$J:$J,"Paid"))) | H8: =IF($A8="","",IF($C8="",SUMIFS(Expenses!$H:$H,Expenses!$C:$C,$B8,Expenses!$E:$E,$D8,Expenses!$J:$J,"Committed"),SUMIFS(Expenses!$H:$H,Expenses!$C:$C,$B8,Expenses!$D:$D,$C8,Expenses!$E:$E,$D8,Expenses!$J:$J,"Committed"))) | I8: =IF($A8="","",$F8-$G8-$H8) | J8: =IF($A8="","",$F8-($G8+$H8)) | K8: =IF(OR($A8="",$F8=0),"",($G8+$H8-$F8)/$F8) | L8: =IF($A8="","",IF($F8=0,"",IF(($G8+$H8)>$F8*(1+OverrunAlert),"Over",IF(($G8+$H8)>$F8,"Watch",IF(($G8+$H8)<$F8*0.85,"Under","On Track")))))
A9: BL-005 | B9: PRJ-001 | C9: RM-01 | D9: Labor | E9: Plumbing relocate | F9: 1400 | G9: =IF($A9="","",IF($C9="",SUMIFS(Expenses!$H:$H,Expenses!$C:$C,$B9,Expenses!$E:$E,$D9,Expenses!$J:$J,"Paid"),SUMIFS(Expenses!$H:$H,Expenses!$C:$C,$B9,Expenses!$D:$D,$C9,Expenses!$E:$E,$D9,Expenses!$J:$J,"Paid"))) | H9: =IF($A9="","",IF($C9="",SUMIFS(Expenses!$H:$H,Expenses!$C:$C,$B9,Expenses!$E:$E,$D9,Expenses!$J:$J,"Committed"),SUMIFS(Expenses!$H:$H,Expenses!$C:$C,$B9,Expenses!$D:$D,$C9,Expenses!$E:$E,$D9,Expenses!$J:$J,"Committed"))) | I9: =IF($A9="","",$F9-$G9-$H9) | J9: =IF($A9="","",$F9-($G9+$H9)) | K9: =IF(OR($A9="",$F9=0),"",($G9+$H9-$F9)/$F9) | L9: =IF($A9="","",IF($F9=0,"",IF(($G9+$H9)>$F9*(1+OverrunAlert),"Over",IF(($G9+$H9)>$F9,"Watch",IF(($G9+$H9)<$F9*0.85,"Under","On Track")))))
A10: BL-006 | B10: PRJ-001 | C10: RM-01 | D10: Labor | E10: Electrical / lighting | F10: 600 | G10: =IF($A10="","",IF($C10="",SUMIFS(Expenses!$H:$H,Expenses!$C:$C,$B10,Expenses!$E:$E,$D10,Expenses!$J:$J,"Paid"),SUMIFS(Expenses!$H:$H,Expenses!$C:$C,$B10,Expenses!$D:$D,$C10,Expenses!$E:$E,$D10,Expenses!$J:$J,"Paid"))) | H10: =IF($A10="","",IF($C10="",SUMIFS(Expenses!$H:$H,Expenses!$C:$C,$B10,Expenses!$E:$E,$D10,Expenses!$J:$J,"Committed"),SUMIFS(Expenses!$H:$H,Expenses!$C:$C,$B10,Expenses!$D:$D,$C10,Expenses!$E:$E,$D10,Expenses!$J:$J,"Committed"))) | I10: =IF($A10="","",$F10-$G10-$H10) | J10: =IF($A10="","",$F10-($G10+$H10)) | K10: =IF(OR($A10="",$F10=0),"",($G10+$H10-$F10)/$F10) | L10: =IF($A10="","",IF($F10=0,"",IF(($G10+$H10)>$F10*(1+OverrunAlert),"Over",IF(($G10+$H10)>$F10,"Watch",IF(($G10+$H10)<$F10*0.85,"Under","On Track")))))
A11: BL-007 | B11: PRJ-001 | C11: RM-02 | D11: Materials | E11: White oak flooring (share) | F11: 2800 | G11: =IF($A11="","",IF($C11="",SUMIFS(Expenses!$H:$H,Expenses!$C:$C,$B11,Expenses!$E:$E,$D11,Expenses!$J:$J,"Paid"),SUMIFS(Expenses!$H:$H,Expenses!$C:$C,$B11,Expenses!$D:$D,$C11,Expenses!$E:$E,$D11,Expenses!$J:$J,"Paid"))) | H11: =IF($A11="","",IF($C11="",SUMIFS(Expenses!$H:$H,Expenses!$C:$C,$B11,Expenses!$E:$E,$D11,Expenses!$J:$J,"Committed"),SUMIFS(Expenses!$H:$H,Expenses!$C:$C,$B11,Expenses!$D:$D,$C11,Expenses!$E:$E,$D11,Expenses!$J:$J,"Committed"))) | I11: =IF($A11="","",$F11-$G11-$H11) | J11: =IF($A11="","",$F11-($G11+$H11)) | K11: =IF(OR($A11="",$F11=0),"",($G11+$H11-$F11)/$F11) | L11: =IF($A11="","",IF($F11=0,"",IF(($G11+$H11)>$F11*(1+OverrunAlert),"Over",IF(($G11+$H11)>$F11,"Watch",IF(($G11+$H11)<$F11*0.85,"Under","On Track")))))
A12: BL-008 | B12: PRJ-001 | C12: RM-02 | D12: Labor | E12: Floor install + finish | F12: 2200 | G12: =IF($A12="","",IF($C12="",SUMIFS(Expenses!$H:$H,Expenses!$C:$C,$B12,Expenses!$E:$E,$D12,Expenses!$J:$J,"Paid"),SUMIFS(Expenses!$H:$H,Expenses!$C:$C,$B12,Expenses!$D:$D,$C12,Expenses!$E:$E,$D12,Expenses!$J:$J,"Paid"))) | H12: =IF($A12="","",IF($C12="",SUMIFS(Expenses!$H:$H,Expenses!$C:$C,$B12,Expenses!$E:$E,$D12,Expenses!$J:$J,"Committed"),SUMIFS(Expenses!$H:$H,Expenses!$C:$C,$B12,Expenses!$D:$D,$C12,Expenses!$E:$E,$D12,Expenses!$J:$J,"Committed"))) | I12: =IF($A12="","",$F12-$G12-$H12) | J12: =IF($A12="","",$F12-($G12+$H12)) | K12: =IF(OR($A12="",$F12=0),"",($G12+$H12-$F12)/$F12) | L12: =IF($A12="","",IF($F12=0,"",IF(($G12+$H12)>$F12*(1+OverrunAlert),"Over",IF(($G12+$H12)>$F12,"Watch",IF(($G12+$H12)<$F12*0.85,"Under","On Track")))))
A13: BL-009 | B13: PRJ-001 | C13: RM-02 | D13: Furniture | E13: Sofa, table, lighting | F13: 4200 | G13: =IF($A13="","",IF($C13="",SUMIFS(Expenses!$H:$H,Expenses!$C:$C,$B13,Expenses!$E:$E,$D13,Expenses!$J:$J,"Paid"),SUMIFS(Expenses!$H:$H,Expenses!$C:$C,$B13,Expenses!$D:$D,$C13,Expenses!$E:$E,$D13,Expenses!$J:$J,"Paid"))) | H13: =IF($A13="","",IF($C13="",SUMIFS(Expenses!$H:$H,Expenses!$C:$C,$B13,Expenses!$E:$E,$D13,Expenses!$J:$J,"Committed"),SUMIFS(Expenses!$H:$H,Expenses!$C:$C,$B13,Expenses!$D:$D,$C13,Expenses!$E:$E,$D13,Expenses!$J:$J,"Committed"))) | I13: =IF($A13="","",$F13-$G13-$H13) | J13: =IF($A13="","",$F13-($G13+$H13)) | K13: =IF(OR($A13="",$F13=0),"",($G13+$H13-$F13)/$F13) | L13: =IF($A13="","",IF($F13=0,"",IF(($G13+$H13)>$F13*(1+OverrunAlert),"Over",IF(($G13+$H13)>$F13,"Watch",IF(($G13+$H13)<$F13*0.85,"Under","On Track")))))
A14: BL-010 | B14: PRJ-001 | C14: RM-02 | D14: Materials | E14: Paint & plaster | F14: 900 | G14: =IF($A14="","",IF($C14="",SUMIFS(Expenses!$H:$H,Expenses!$C:$C,$B14,Expenses!$E:$E,$D14,Expenses!$J:$J,"Paid"),SUMIFS(Expenses!$H:$H,Expenses!$C:$C,$B14,Expenses!$D:$D,$C14,Expenses!$E:$E,$D14,Expenses!$J:$J,"Paid"))) | H14: =IF($A14="","",IF($C14="",SUMIFS(Expenses!$H:$H,Expenses!$C:$C,$B14,Expenses!$E:$E,$D14,Expenses!$J:$J,"Committed"),SUMIFS(Expenses!$H:$H,Expenses!$C:$C,$B14,Expenses!$D:$D,$C14,Expenses!$E:$E,$D14,Expenses!$J:$J,"Committed"))) | I14: =IF($A14="","",$F14-$G14-$H14) | J14: =IF($A14="","",$F14-($G14+$H14)) | K14: =IF(OR($A14="",$F14=0),"",($G14+$H14-$F14)/$F14) | L14: =IF($A14="","",IF($F14=0,"",IF(($G14+$H14)>$F14*(1+OverrunAlert),"Over",IF(($G14+$H14)>$F14,"Watch",IF(($G14+$H14)<$F14*0.85,"Under","On Track")))))
A15: BL-011 | B15: PRJ-001 | C15: RM-02 | D15: Labor | E15: Paint labor | F15: 1400 | G15: =IF($A15="","",IF($C15="",SUMIFS(Expenses!$H:$H,Expenses!$C:$C,$B15,Expenses!$E:$E,$D15,Expenses!$J:$J,"Paid"),SUMIFS(Expenses!$H:$H,Expenses!$C:$C,$B15,Expenses!$D:$D,$C15,Expenses!$E:$E,$D15,Expenses!$J:$J,"Paid"))) | H15: =IF($A15="","",IF($C15="",SUMIFS(Expenses!$H:$H,Expenses!$C:$C,$B15,Expenses!$E:$E,$D15,Expenses!$J:$J,"Committed"),SUMIFS(Expenses!$H:$H,Expenses!$C:$C,$B15,Expenses!$D:$D,$C15,Expenses!$E:$E,$D15,Expenses!$J:$J,"Committed"))) | I15: =IF($A15="","",$F15-$G15-$H15) | J15: =IF($A15="","",$F15-($G15+$H15)) | K15: =IF(OR($A15="",$F15=0),"",($G15+$H15-$F15)/$F15) | L15: =IF($A15="","",IF($F15=0,"",IF(($G15+$H15)>$F15*(1+OverrunAlert),"Over",IF(($G15+$H15)>$F15,"Watch",IF(($G15+$H15)<$F15*0.85,"Under","On Track")))))
A16: BL-012 | B16: PRJ-001 | C16: RM-03 | D16: Materials | E16: Tile, fixtures, vanity | F16: 9200 | G16: =IF($A16="","",IF($C16="",SUMIFS(Expenses!$H:$H,Expenses!$C:$C,$B16,Expenses!$E:$E,$D16,Expenses!$J:$J,"Paid"),SUMIFS(Expenses!$H:$H,Expenses!$C:$C,$B16,Expenses!$D:$D,$C16,Expenses!$E:$E,$D16,Expenses!$J:$J,"Paid"))) | H16: =IF($A16="","",IF($C16="",SUMIFS(Expenses!$H:$H,Expenses!$C:$C,$B16,Expenses!$E:$E,$D16,Expenses!$J:$J,"Committed"),SUMIFS(Expenses!$H:$H,Expenses!$C:$C,$B16,Expenses!$D:$D,$C16,Expenses!$E:$E,$D16,Expenses!$J:$J,"Committed"))) | I16: =IF($A16="","",$F16-$G16-$H16) | J16: =IF($A16="","",$F16-($G16+$H16)) | K16: =IF(OR($A16="",$F16=0),"",($G16+$H16-$F16)/$F16) | L16: =IF($A16="","",IF($F16=0,"",IF(($G16+$H16)>$F16*(1+OverrunAlert),"Over",IF(($G16+$H16)>$F16,"Watch",IF(($G16+$H16)<$F16*0.85,"Under","On Track")))))
... A30: BL-026 | B30: PRJ-001 | C30: RM-08 | D30: Labor | E30: Carpentry + paint | F30: 800 | G30: =IF($A30="","",IF($C30="",SUMIFS(Expenses!$H:$H,Expenses!$C:$C,$B30,Expenses!$E:$E,$D30,Expenses!$J:$J,"Paid"),SUMIFS(Expenses!$H:$H,Expenses!$C:$C,$B30,Expenses!$D:$D,$C30,Expenses!$E:$E,$D30,Expenses!$J:$J,"Paid"))) | H30: =IF($A30="","",IF($C30="",SUMIFS(Expenses!$H:$H,Expenses!$C:$C,$B30,Expenses!$E:$E,$D30,Expenses!$J:$J,"Committed"),SUMIFS(Expenses!$H:$H,Expenses!$C:$C,$B30,Expenses!$D:$D,$C30,Expenses!$E:$E,$D30,Expenses!$J:$J,"Committed"))) | I30: =IF($A30="","",$F30-$G30-$H30) | J30: =IF($A30="","",$F30-($G30+$H30)) | K30: =IF(OR($A30="",$F30=0),"",($G30+$H30-$F30)/$F30) | L30: =IF($A30="","",IF($F30=0,"",IF(($G30+$H30)>$F30*(1+OverrunAlert),"Over",IF(($G30+$H30)>$F30,"Watch",IF(($G30+$H30)<$F30*0.85,"Under","On Track")))))
A31: BL-027 | B31: PRJ-001 | D31: Design | E31: Luna Interiors retainer + hours | F31: 4800 | G31: =IF($A31="","",IF($C31="",SUMIFS(Expenses!$H:$H,Expenses!$C:$C,$B31,Expenses!$E:$E,$D31,Expenses!$J:$J,"Paid"),SUMIFS(Expenses!$H:$H,Expenses!$C:$C,$B31,Expenses!$D:$D,$C31,Expenses!$E:$E,$D31,Expenses!$J:$J,"Paid"))) | H31: =IF($A31="","",IF($C31="",SUMIFS(Expenses!$H:$H,Expenses!$C:$C,$B31,Expenses!$E:$E,$D31,Expenses!$J:$J,"Committed"),SUMIFS(Expenses!$H:$H,Expenses!$C:$C,$B31,Expenses!$D:$D,$C31,Expenses!$E:$E,$D31,Expenses!$J:$J,"Committed"))) | I31: =IF($A31="","",$F31-$G31-$H31) | J31: =IF($A31="","",$F31-($G31+$H31)) | K31: =IF(OR($A31="",$F31=0),"",($G31+$H31-$F31)/$F31) | L31: =IF($A31="","",IF($F31=0,"",IF(($G31+$H31)>$F31*(1+OverrunAlert),"Over",IF(($G31+$H31)>$F31,"Watch",IF(($G31+$H31)<$F31*0.85,"Under","On Track")))))
A32: BL-028 | B32: PRJ-001 | D32: Permits | E32: Building, electrical, plumbing | F32: 1850 | G32: =IF($A32="","",IF($C32="",SUMIFS(Expenses!$H:$H,Expenses!$C:$C,$B32,Expenses!$E:$E,$D32,Expenses!$J:$J,"Paid"),SUMIFS(Expenses!$H:$H,Expenses!$C:$C,$B32,Expenses!$D:$D,$C32,Expenses!$E:$E,$D32,Expenses!$J:$J,"Paid"))) | H32: =IF($A32="","",IF($C32="",SUMIFS(Expenses!$H:$H,Expenses!$C:$C,$B32,Expenses!$E:$E,$D32,Expenses!$J:$J,"Committed"),SUMIFS(Expenses!$H:$H,Expenses!$C:$C,$B32,Expenses!$D:$D,$C32,Expenses!$E:$E,$D32,Expenses!$J:$J,"Committed"))) | I32: =IF($A32="","",$F32-$G32-$H32) | J32: =IF($A32="","",$F32-($G32+$H32)) | K32: =IF(OR($A32="",$F32=0),"",($G32+$H32-$F32)/$F32) | L32: =IF($A32="","",IF($F32=0,"",IF(($G32+$H32)>$F32*(1+OverrunAlert),"Over",IF(($G32+$H32)>$F32,"Watch",IF(($G32+$H32)<$F32*0.85,"Under","On Track")))))
A33: BL-029 | B33: PRJ-001 | D33: Delivery | E33: Freight & white-glove | F33: 900 | G33: =IF($A33="","",IF($C33="",SUMIFS(Expenses!$H:$H,Expenses!$C:$C,$B33,Expenses!$E:$E,$D33,Expenses!$J:$J,"Paid"),SUMIFS(Expenses!$H:$H,Expenses!$C:$C,$B33,Expenses!$D:$D,$C33,Expenses!$E:$E,$D33,Expenses!$J:$J,"Paid"))) | H33: =IF($A33="","",IF($C33="",SUMIFS(Expenses!$H:$H,Expenses!$C:$C,$B33,Expenses!$E:$E,$D33,Expenses!$J:$J,"Committed"),SUMIFS(Expenses!$H:$H,Expenses!$C:$C,$B33,Expenses!$D:$D,$C33,Expenses!$E:$E,$D33,Expenses!$J:$J,"Committed"))) | I33: =IF($A33="","",$F33-$G33-$H33) | J33: =IF($A33="","",$F33-($G33+$H33)) | K33: =IF(OR($A33="",$F33=0),"",($G33+$H33-$F33)/$F33) | L33: =IF($A33="","",IF($F33=0,"",IF(($G33+$H33)>$F33*(1+OverrunAlert),"Over",IF(($G33+$H33)>$F33,"Watch",IF(($G33+$H33)<$F33*0.85,"Under","On Track")))))
A34: BL-030 | B34: PRJ-001 | D34: Inspections | E34: City + independent | F34: 650 | G34: =IF($A34="","",IF($C34="",SUMIFS(Expenses!$H:$H,Expenses!$C:$C,$B34,Expenses!$E:$E,$D34,Expenses!$J:$J,"Paid"),SUMIFS(Expenses!$H:$H,Expenses!$C:$C,$B34,Expenses!$D:$D,$C34,Expenses!$E:$E,$D34,Expenses!$J:$J,"Paid"))) | H34: =IF($A34="","",IF($C34="",SUMIFS(Expenses!$H:$H,Expenses!$C:$C,$B34,Expenses!$E:$E,$D34,Expenses!$J:$J,"Committed"),SUMIFS(Expenses!$H:$H,Expenses!$C:$C,$B34,Expenses!$D:$D,$C34,Expenses!$E:$E,$D34,Expenses!$J:$J,"Committed"))) | I34: =IF($A34="","",$F34-$G34-$H34) | J34: =IF($A34="","",$F34-($G34+$H34)) | K34: =IF(OR($A34="",$F34=0),"",($G34+$H34-$F34)/$F34) | L34: =IF($A34="","",IF($F34=0,"",IF(($G34+$H34)>$F34*(1+OverrunAlert),"Over",IF(($G34+$H34)>$F34,"Watch",IF(($G34+$H34)<$F34*0.85,"Under","On Track")))))
A35: BL-031 | B35: PRJ-001 | D35: Contingency | E35: 10% project reserve | F35: 8500 | G35: =IF($A35="","",IF($C35="",SUMIFS(Expenses!$H:$H,Expenses!$C:$C,$B35,Expenses!$E:$E,$D35,Expenses!$J:$J,"Paid"),SUMIFS(Expenses!$H:$H,Expenses!$C:$C,$B35,Expenses!$D:$D,$C35,Expenses!$E:$E,$D35,Expenses!$J:$J,"Paid"))) | H35: =IF($A35="","",IF($C35="",SUMIFS(Expenses!$H:$H,Expenses!$C:$C,$B35,Expenses!$E:$E,$D35,Expenses!$J:$J,"Committed"),SUMIFS(Expenses!$H:$H,Expenses!$C:$C,$B35,Expenses!$D:$D,$C35,Expenses!$E:$E,$D35,Expenses!$J:$J,"Committed"))) | I35: =IF($A35="","",$F35-$G35-$H35) | J35: =IF($A35="","",$F35-($G35+$H35)) | K35: =IF(OR($A35="",$F35=0),"",($G35+$H35-$F35)/$F35) | L35: =IF($A35="","",IF($F35=0,"",IF(($G35+$H35)>$F35*(1+OverrunAlert),"Over",IF(($G35+$H35)>$F35,"Watch",IF(($G35+$H35)<$F35*0.85,"Under","On Track")))))
A36: BL-032 | B36: PRJ-001 | C36: RM-01 | D36: Labor | E36: Demolition (kitchen share) | F36: 0 | G36: =IF($A36="","",IF($C36="",SUMIFS(Expenses!$H:$H,Expenses!$C:$C,$B36,Expenses!$E:$E,$D36,Expenses!$J:$J,"Paid"),SUMIFS(Expenses!$H:$H,Expenses!$C:$C,$B36,Expenses!$D:$D,$C36,Expenses!$E:$E,$D36,Expenses!$J:$J,"Paid"))) | H36: =IF($A36="","",IF($C36="",SUMIFS(Expenses!$H:$H,Expenses!$C:$C,$B36,Expenses!$E:$E,$D36,Expenses!$J:$J,"Committed"),SUMIFS(Expenses!$H:$H,Expenses!$C:$C,$B36,Expenses!$D:$D,$C36,Expenses!$E:$E,$D36,Expenses!$J:$J,"Committed"))) | I36: =IF($A36="","",$F36-$G36-$H36) | J36: =IF($A36="","",$F36-($G36+$H36)) | K36: =IF(OR($A36="",$F36=0),"",($G36+$H36-$F36)/$F36) | L36: =IF($A36="","",IF($F36=0,"",IF(($G36+$H36)>$F36*(1+OverrunAlert),"Over",IF(($G36+$H36)>$F36,"Watch",IF(($G36+$H36)<$F36*0.85,"Under","On Track")))))
A37: BL-033 | B37: PRJ-001 | D37: Labor | E37: General contractor / PM | F37: 6200 | G37: =IF($A37="","",IF($C37="",SUMIFS(Expenses!$H:$H,Expenses!$C:$C,$B37,Expenses!$E:$E,$D37,Expenses!$J:$J,"Paid"),SUMIFS(Expenses!$H:$H,Expenses!$C:$C,$B37,Expenses!$D:$D,$C37,Expenses!$E:$E,$D37,Expenses!$J:$J,"Paid"))) | H37: =IF($A37="","",IF($C37="",SUMIFS(Expenses!$H:$H,Expenses!$C:$C,$B37,Expenses!$E:$E,$D37,Expenses!$J:$J,"Committed"),SUMIFS(Expenses!$H:$H,Expenses!$C:$C,$B37,Expenses!$D:$D,$C37,Expenses!$E:$E,$D37,Expenses!$J:$J,"Committed"))) | I37: =IF($A37="","",$F37-$G37-$H37) | J37: =IF($A37="","",$F37-($G37+$H37)) | K37: =IF(OR($A37="",$F37=0),"",($G37+$H37-$F37)/$F37) | L37: =IF($A37="","",IF($F37=0,"",IF(($G37+$H37)>$F37*(1+OverrunAlert),"Over",IF(($G37+$H37)>$F37,"Watch",IF(($G37+$H37)<$F37*0.85,"Under","On Track")))))
A38: BL-034 | B38: PRJ-002 | C38: RM-09 | D38: Materials | E38: Cabin bath package | F38: 9200 | G38: =IF($A38="","",IF($C38="",SUMIFS(Expenses!$H:$H,Expenses!$C:$C,$B38,Expenses!$E:$E,$D38,Expenses!$J:$J,"Paid"),SUMIFS(Expenses!$H:$H,Expenses!$C:$C,$B38,Expenses!$D:$D,$C38,Expenses!$E:$E,$D38,Expenses!$J:$J,"Paid"))) | H38: =IF($A38="","",IF($C38="",SUMIFS(Expenses!$H:$H,Expenses!$C:$C,$B38,Expenses!$E:$E,$D38,Expenses!$J:$J,"Committed"),SUMIFS(Expenses!$H:$H,Expenses!$C:$C,$B38,Expenses!$D:$D,$C38,Expenses!$E:$E,$D38,Expenses!$J:$J,"Committed"))) | I38: =IF($A38="","",$F38-$G38-$H38) | J38: =IF($A38="","",$F38-($G38+$H38)) | K38: =IF(OR($A38="",$F38=0),"",($G38+$H38-$F38)/$F38) | L38: =IF($A38="","",IF($F38=0,"",IF(($G38+$H38)>$F38*(1+OverrunAlert),"Over",IF(($G38+$H38)>$F38,"Watch",IF(($G38+$H38)<$F38*0.85,"Under","On Track")))))
A39: BL-035 | B39: PRJ-002 | C39: RM-09 | D39: Labor | E39: Gut and reset | F39: 6800 | G39: =IF($A39="","",IF($C39="",SUMIFS(Expenses!$H:$H,Expenses!$C:$C,$B39,Expenses!$E:$E,$D39,Expenses!$J:$J,"Paid"),SUMIFS(Expenses!$H:$H,Expenses!$C:$C,$B39,Expenses!$D:$D,$C39,Expenses!$E:$E,$D39,Expenses!$J:$J,"Paid"))) | H39: =IF($A39="","",IF($C39="",SUMIFS(Expenses!$H:$H,Expenses!$C:$C,$B39,Expenses!$E:$E,$D39,Expenses!$J:$J,"Committed"),SUMIFS(Expenses!$H:$H,Expenses!$C:$C,$B39,Expenses!$D:$D,$C39,Expenses!$E:$E,$D39,Expenses!$J:$J,"Committed"))) | I39: =IF($A39="","",$F39-$G39-$H39) | J39: =IF($A39="","",$F39-($G39+$H39)) | K39: =IF(OR($A39="",$F39=0),"",($G39+$H39-$F39)/$F39) | L39: =IF($A39="","",IF($F39=0,"",IF(($G39+$H39)>$F39*(1+OverrunAlert),"Over",IF(($G39+$H39)>$F39,"Watch",IF(($G39+$H39)<$F39*0.85,"Under","On Track")))))
A40: BL-036 | B40: PRJ-002 | D40: Design | E40: Concept + drawings | F40: 1200 | G40: =IF($A40="","",IF($C40="",SUMIFS(Expenses!$H:$H,Expenses!$C:$C,$B40,Expenses!$E:$E,$D40,Expenses!$J:$J,"Paid"),SUMIFS(Expenses!$H:$H,Expenses!$C:$C,$B40,Expenses!$D:$D,$C40,Expenses!$E:$E,$D40,Expenses!$J:$J,"Paid"))) | H40: =IF($A40="","",IF($C40="",SUMIFS(Expenses!$H:$H,Expenses!$C:$C,$B40,Expenses!$E:$E,$D40,Expenses!$J:$J,"Committed"),SUMIFS(Expenses!$H:$H,Expenses!$C:$C,$B40,Expenses!$D:$D,$C40,Expenses!$E:$E,$D40,Expenses!$J:$J,"Committed"))) | I40: =IF($A40="","",$F40-$G40-$H40) | J40: =IF($A40="","",$F40-($G40+$H40)) | K40: =IF(OR($A40="",$F40=0),"",($G40+$H40-$F40)/$F40) | L40: =IF($A40="","",IF($F40=0,"",IF(($G40+$H40)>$F40*(1+OverrunAlert),"Over",IF(($G40+$H40)>$F40,"Watch",IF(($G40+$H40)<$F40*0.85,"Under","On Track")))))
A41: BL-037 | B41: PRJ-002 | D41: Contingency | E41: 10% reserve | F41: 1300 | G41: =IF($A41="","",IF($C41="",SUMIFS(Expenses!$H:$H,Expenses!$C:$C,$B41,Expenses!$E:$E,$D41,Expenses!$J:$J,"Paid"),SUMIFS(Expenses!$H:$H,Expenses!$C:$C,$B41,Expenses!$D:$D,$C41,Expenses!$E:$E,$D41,Expenses!$J:$J,"Paid"))) | H41: =IF($A41="","",IF($C41="",SUMIFS(Expenses!$H:$H,Expenses!$C:$C,$B41,Expenses!$E:$E,$D41,Expenses!$J:$J,"Committed"),SUMIFS(Expenses!$H:$H,Expenses!$C:$C,$B41,Expenses!$D:$D,$C41,Expenses!$E:$E,$D41,Expenses!$J:$J,"Committed"))) | I41: =IF($A41="","",$F41-$G41-$H41) | J41: =IF($A41="","",$F41-($G41+$H41)) | K41: =IF(OR($A41="",$F41=0),"",($G41+$H41-$F41)/$F41) | L41: =IF($A41="","",IF($F41=0,"",IF(($G41+$H41)>$F41*(1+OverrunAlert),"Over",IF(($G41+$H41)>$F41,"Watch",IF(($G41+$H41)<$F41*0.85,"Under","On Track")))))
E43: TOTAL (all lines) | F43: =SUM(F5:F41) | G43: =SUM(G5:G41) | H43: =SUM(H5:H41) | I43: =SUM(I5:I41) | J43: =F43-G43-H43

Sheet Expenses
A1: EXPENSES
A2: Every dollar · Planned / Committed / Paid · add rows below, keep Status valid
A4: Expense ID | B4: Date | C4: Project ID | D4: Room ID | E4: Category | F4: Vendor | G4: Description | H4: Amount | I4: Method | J4: Status | K4: Receipt / Invoice | L4: Approved By
A5: EXP-001 | B5: 46089 | C5: PRJ-001 | E5: Design | F5: Luna Interiors | G5: Design retainer | H5: 2400 | I5: ACH | J5: Paid | K5: INV-LUNA-110 | L5: Alex Rivera
A6: EXP-002 | B6: 46114 | C6: PRJ-001 | E6: Permits | F6: City of Portland | G6: Building permit | H6: 840 | I6: Credit Card | J6: Paid | K6: PMT-2026-441 | L6: Marcus Webb
A7: EXP-003 | B7: 46130 | C7: PRJ-001 | E7: Permits | F7: City of Portland | G7: Electrical + plumbing permits | H7: 610 | I7: Credit Card | J7: Paid | K7: PMT-2026-478 | L7: Marcus Webb
A8: EXP-004 | B8: 46146 | C8: PRJ-001 | E8: Design | F8: Luna Interiors | G8: Drawings + 3D package | H8: 1800 | I8: ACH | J8: Paid | K8: INV-LUNA-126 | L8: Alex Rivera
A9: EXP-005 | B9: 46164 | C9: PRJ-001 | E9: Labor | F9: Ironwood Construction | G9: Demolition + dumpsters | H9: 2800 | I9: Check | J9: Paid | K9: INV-IW-204 | L9: Alex Rivera
A10: EXP-006 | B10: 46179 | C10: PRJ-001 | D10: RM-01 | E10: Labor | F10: Northwest Electric | G10: Kitchen / bath rough-in | H10: 1900 | I10: ACH | J10: Paid | K10: INV-NWE-88 | L10: Marcus Webb
A11: EXP-007 | B11: 46185 | C11: PRJ-001 | D11: RM-03 | E11: Labor | F11: Pacific Plumbing | G11: Bath / laundry rough-in | H11: 2400 | I11: ACH | J11: Paid | K11: INV-PP-301 | L11: Marcus Webb
A12: EXP-008 | B12: 46193 | C12: PRJ-001 | D12: RM-03 | E12: Materials | F12: Tile & Timber Co. | G12: Porcelain floor + wall tile | H12: 3180 | I12: Credit Card | J12: Paid | K12: PO-114 | L12: Sofia Alvarez
A13: EXP-009 | B13: 46201 | C13: PRJ-001 | D13: RM-03 | E13: Materials | F13: Ferguson | G13: Bath fixtures package | H13: 2140 | I13: Credit Card | J13: Paid | K13: FERG-9921 | L13: Sofia Alvarez
A14: EXP-010 | B14: 46205 | C14: PRJ-001 | D14: RM-03 | E14: Materials | F14: WarmFloor Co. | G14: Heated floor kit | H14: 1680 | I14: Credit Card | J14: Paid | K14: WF-441 | L14: Marcus Webb
A15: EXP-011 | B15: 46211 | C15: PRJ-001 | D15: RM-01 | E15: Labor | F15: Pacific Plumbing | G15: Kitchen sink relocate | H15: 1280 | I15: ACH | J15: Paid | K15: INV-PP-318 | L15: Marcus Webb
A16: EXP-012 | B16: 46218 | C16: PRJ-001 | D16: RM-03 | E16: Labor | F16: Heritage Tile & Stone | G16: Primary bath tile labor (50%) | H16: 2100 | I16: ACH | J16: Paid | K16: INV-HT-77 | L16: Marcus Webb
A17: EXP-013 | B17: 46221 | C17: PRJ-001 | D17: RM-07 | E17: Materials | F17: Tile & Timber Co. | G17: Laundry tile + sink | H17: 860 | I17: Credit Card | J17: Paid | K17: PO-129 | L17: Sofia Alvarez
A18: EXP-014 | B18: 46225 | C18: PRJ-001 | D18: RM-07 | E18: Labor | F18: Pacific Plumbing | G18: Laundry install | H18: 980 | I18: ACH | J18: Paid | K18: INV-PP-330 | L18: Marcus Webb
A19: EXP-015 | B19: 46231 | C19: PRJ-001 | D19: RM-01 | E19: Materials | F19: Timberline Floors | G19: White oak 7in — kitchen/living/dining | H19: 6400 | I19: ACH | J19: Paid | K19: PO-140 | L19: Sofia Alvarez
A20: EXP-016 | B20: 46236 | C20: PRJ-001 | D20: RM-01 | E20: Materials | F20: Cascade Cabinets | G20: Cabinet deposit 50% | H20: 7400 | I20: Wire | J20: Paid | K20: INV-CC-501 | L20: Alex Rivera
A21: EXP-017 | B21: 46239 | C21: PRJ-001 | D21: RM-02 | E21: Labor | F21: Timberline Floors | G21: Floor install progress | H21: 1800 | I21: ACH | J21: Paid | K21: INV-TF-19 | L21: Marcus Webb
... A23: EXP-019 | B23: 46244 | C23: PRJ-001 | D23: RM-03 | E23: Labor | F23: Pacific Plumbing | G23: Bath trim-out | H23: 1460 | I23: ACH | J23: Paid | K23: INV-PP-341 | L23: Marcus Webb
A24: EXP-020 | B24: 46246 | C24: PRJ-001 | E24: Inspections | F24: City of Portland | G24: Plumbing + electrical inspection | H24: 240 | I24: Credit Card | J24: Paid | K24: INSP-0812 | L24: Marcus Webb
A25: EXP-021 | B25: 46248 | C25: PRJ-001 | D25: RM-01 | E25: Materials | F25: Sub-Zero / Wolf dealer | G25: Range + fridge deposit | H25: 2700 | I25: Credit Card | J25: Paid | K25: APPL-01 | L25: Alex Rivera
A26: EXP-022 | B26: 46250 | C26: PRJ-001 | D26: RM-01 | E26: Materials | F26: Caesarstone | G26: Perimeter quartz | H26: 2480 | I26: Credit Card | J26: Paid | K26: CS-882 | L26: Sofia Alvarez
A27: EXP-023 | B27: 46252 | C27: PRJ-001 | E27: Labor | F27: Ironwood Construction | G27: August PM / supervision | H27: 1550 | I27: ACH | J27: Paid | K27: INV-IW-228 | L27: Alex Rivera
A28: EXP-024 | B28: 46254 | C28: PRJ-001 | D28: RM-01 | E28: Delivery | F28: Cascade Cabinets | G28: Cabinet freight | H28: 420 | I28: Credit Card | J28: Paid | K28: FRT-88 | L28: Maya Chen
A29: EXP-025 | B29: 46256 | C29: PRJ-001 | D29: RM-05 | E29: Materials | F29: BrightPath Lighting | G29: Dining sconces | H29: 380 | I29: Credit Card | J29: Paid | K29: BP-204 | L29: Sofia Alvarez
A30: EXP-026 | B30: 46259 | C30: PRJ-001 | D30: RM-01 | E30: Materials | F30: Cascade Cabinets | G30: Cabinet balance | H30: 7400 | I30: Wire | J30: Committed | K30: INV-CC-502 | L30: Alex Rivera
A31: EXP-027 | B31: 46262 | C31: PRJ-001 | D31: RM-01 | E31: Labor | F31: Cascade Cabinets | G31: Install labor | H31: 3600 | I31: ACH | J31: Committed | K31: INV-CC-510 | L31: Marcus Webb
A32: EXP-028 | B32: 46269 | C32: PRJ-001 | D32: RM-01 | E32: Materials | F32: Heritage Tile & Stone | G32: Island porcelain slab | H32: 1860 | I32: Credit Card | J32: Committed | K32: PO-155 | L32: Sofia Alvarez
A33: EXP-029 | B33: 46273 | C33: PRJ-001 | D33: RM-01 | E33: Materials | F33: BrightPath Lighting | G33: Island pendants | H33: 890 | I33: Credit Card | J33: Planned | K33: BP-220 | L33: Sofia Alvarez
A34: EXP-030 | B34: 46277 | C34: PRJ-001 | D34: RM-04 | E34: Materials | F34: Sherwin-Williams | G34: Guest bedroom paint | H34: 240 | I34: Credit Card | J34: Planned
A35: EXP-031 | B35: 46283 | C35: PRJ-001 | D35: RM-02 | E35: Furniture | F35: Article | G35: Sofa + coffee table | H35: 3400 | I35: Credit Card | J35: Planned | L35: Sofia Alvarez
A36: EXP-032 | B36: 46297 | C36: PRJ-001 | D36: RM-06 | E36: Materials | F36: Garden & Gate | G36: Path stone deposit | H36: 1200 | I36: Check | J36: Planned
A37: EXP-033 | B37: 46235 | C37: PRJ-002 | E37: Design | F37: Luna Interiors | G37: Cabin bath concept | H37: 600 | I37: ACH | J37: Paid | K37: INV-LUNA-140 | L37: Alex Rivera
A38: EXP-034 | B38: 46233 | C38: PRJ-001 | D38: RM-01 | E38: Labor | F38: Northwest Electric | G38: Finish electrical progress | H38: 720 | I38: ACH | J38: Paid | K38: INV-NWE-97 | L38: Marcus Webb
A39: EXP-035 | B39: 46253 | C39: PRJ-001 | D39: RM-08 | E39: Materials | F39: Rejuvenation | G39: Hook rail + hooks | H39: 186 | I39: Credit Card | J39: Paid | K39: REJ-33 | L39: Alex Rivera

Sheet Finance
A1: FINANCE
A2: Financial dashboard · planned vs actual, by room, by category, by month
A5: BUDGET (active project) | D5: SPENT | G5: COMMITTED | J5: REMAINING
A6: =IFERROR(SUMIF(Projects!A:A,ActiveProject,Projects!J:J),0) | D6: =IFERROR(SUMIFS(Expenses!H:H,Expenses!C:C,ActiveProject,Expenses!J:J,"Paid"),0) | G6: =IFERROR(SUMIFS(Expenses!H:H,Expenses!C:C,ActiveProject,Expenses!J:J,"Committed"),0) | J6: =A6-D6-G6
A7: Total planned | D7: Paid to date | G7: Approved, not yet paid | J7: Budget − spent − committed
A9: % USED | D9: CONTINGENCY LEFT | G9: THIS MONTH SPENT | J9: HEALTH
A10: =IFERROR((D6+G6)/A6,0) | D10: =IFERROR(SUMIFS(Budget!I:I,Budget!B:B,ActiveProject,Budget!D:D,"Contingency"),0) | G10: =SUMIFS(Expenses!H:H,Expenses!C:C,ActiveProject,Expenses!J:J,"Paid",Expenses!B:B,">="&DATE(YEAR(AsOfDate),MONTH(AsOfDate),1),Expenses!B:B,"<"&DATE(YEAR(AsOfDate),MONTH(AsOfDate)+1,1)) | J10: =IF((D6+G6)>A6*(1+OverrunAlert),"OVER",IF((D6+G6)>A6,"WATCH","ON TRACK"))
A11: Spent + committed | D11: Watch the 10% floor | G11: Paid in current month | J11: Vs overrun threshold
A13: Cost by category | H13: Cost by room (active project)
A14: Category | B14: Planned | C14: Spent | D14: Committed | E14: Remaining | F14: % Used | H14: Room | I14: Budget | J14: Spent | K14: Committed | L14: Remaining | M14: % Used
A15: Labor | B15: =SUMIFS(Budget!F:F,Budget!B:B,ActiveProject,Budget!D:D,A15) | C15: =SUMIFS(Expenses!H:H,Expenses!C:C,ActiveProject,Expenses!E:E,A15,Expenses!J:J,"Paid") | D15: =SUMIFS(Expenses!H:H,Expenses!C:C,ActiveProject,Expenses!E:E,A15,Expenses!J:J,"Committed") | E15: =B15-C15-D15 | F15: =IF(B15=0,"",(C15+D15)/B15) | H15: Kitchen | I15: =SUMIF(Rooms!A:A,"RM-01",Rooms!K:K) | J15: =SUMIFS(Expenses!H:H,Expenses!D:D,"RM-01",Expenses!J:J,"Paid") | K15: =SUMIFS(Expenses!H:H,Expenses!D:D,"RM-01",Expenses!J:J,"Committed") | L15: =I15-J15-K15 | M15: =IF(I15=0,"",(J15+K15)/I15)
A16: Materials | B16: =SUMIFS(Budget!F:F,Budget!B:B,ActiveProject,Budget!D:D,A16) | C16: =SUMIFS(Expenses!H:H,Expenses!C:C,ActiveProject,Expenses!E:E,A16,Expenses!J:J,"Paid") | D16: =SUMIFS(Expenses!H:H,Expenses!C:C,ActiveProject,Expenses!E:E,A16,Expenses!J:J,"Committed") | E16: =B16-C16-D16 | F16: =IF(B16=0,"",(C16+D16)/B16) | H16: Living Room | I16: =SUMIF(Rooms!A:A,"RM-02",Rooms!K:K) | J16: =SUMIFS(Expenses!H:H,Expenses!D:D,"RM-02",Expenses!J:J,"Paid") | K16: =SUMIFS(Expenses!H:H,Expenses!D:D,"RM-02",Expenses!J:J,"Committed") | L16: =I16-J16-K16 | M16: =IF(I16=0,"",(J16+K16)/I16)
A17: Design | B17: =SUMIFS(Budget!F:F,Budget!B:B,ActiveProject,Budget!D:D,A17) | C17: =SUMIFS(Expenses!H:H,Expenses!C:C,ActiveProject,Expenses!E:E,A17,Expenses!J:J,"Paid") | D17: =SUMIFS(Expenses!H:H,Expenses!C:C,ActiveProject,Expenses!E:E,A17,Expenses!J:J,"Committed") | E17: =B17-C17-D17 | F17: =IF(B17=0,"",(C17+D17)/B17) | H17: Primary Bathroom | I17: =SUMIF(Rooms!A:A,"RM-03",Rooms!K:K) | J17: =SUMIFS(Expenses!H:H,Expenses!D:D,"RM-03",Expenses!J:J,"Paid") | K17: =SUMIFS(Expenses!H:H,Expenses!D:D,"RM-03",Expenses!J:J,"Committed") | L17: =I17-J17-K17 | M17: =IF(I17=0,"",(J17+K17)/I17)
A18: Permits | B18: =SUMIFS(Budget!F:F,Budget!B:B,ActiveProject,Budget!D:D,A18) | C18: =SUMIFS(Expenses!H:H,Expenses!C:C,ActiveProject,Expenses!E:E,A18,Expenses!J:J,"Paid") | D18: =SUMIFS(Expenses!H:H,Expenses!C:C,ActiveProject,Expenses!E:E,A18,Expenses!J:J,"Committed") | E18: =B18-C18-D18 | F18: =IF(B18=0,"",(C18+D18)/B18) | H18: Guest Bedroom | I18: =SUMIF(Rooms!A:A,"RM-04",Rooms!K:K) | J18: =SUMIFS(Expenses!H:H,Expenses!D:D,"RM-04",Expenses!J:J,"Paid") | K18: =SUMIFS(Expenses!H:H,Expenses!D:D,"RM-04",Expenses!J:J,"Committed") | L18: =I18-J18-K18 | M18: =IF(I18=0,"",(J18+K18)/I18)
A19: Delivery | B19: =SUMIFS(Budget!F:F,Budget!B:B,ActiveProject,Budget!D:D,A19) | C19: =SUMIFS(Expenses!H:H,Expenses!C:C,ActiveProject,Expenses!E:E,A19,Expenses!J:J,"Paid") | D19: =SUMIFS(Expenses!H:H,Expenses!C:C,ActiveProject,Expenses!E:E,A19,Expenses!J:J,"Committed") | E19: =B19-C19-D19 | F19: =IF(B19=0,"",(C19+D19)/B19) | H19: Dining Room | I19: =SUMIF(Rooms!A:A,"RM-05",Rooms!K:K) | J19: =SUMIFS(Expenses!H:H,Expenses!D:D,"RM-05",Expenses!J:J,"Paid") | K19: =SUMIFS(Expenses!H:H,Expenses!D:D,"RM-05",Expenses!J:J,"Committed") | L19: =I19-J19-K19 | M19: =IF(I19=0,"",(J19+K19)/I19)
A20: Contingency | B20: =SUMIFS(Budget!F:F,Budget!B:B,ActiveProject,Budget!D:D,A20) | C20: =SUMIFS(Expenses!H:H,Expenses!C:C,ActiveProject,Expenses!E:E,A20,Expenses!J:J,"Paid") | D20: =SUMIFS(Expenses!H:H,Expenses!C:C,ActiveProject,Expenses!E:E,A20,Expenses!J:J,"Committed") | E20: =B20-C20-D20 | F20: =IF(B20=0,"",(C20+D20)/B20) | H20: Exterior / Garden | I20: =SUMIF(Rooms!A:A,"RM-06",Rooms!K:K) | J20: =SUMIFS(Expenses!H:H,Expenses!D:D,"RM-06",Expenses!J:J,"Paid") | K20: =SUMIFS(Expenses!H:H,Expenses!D:D,"RM-06",Expenses!J:J,"Committed") | L20: =I20-J20-K20 | M20: =IF(I20=0,"",(J20+K20)/I20)
A21: Appliances | B21: =SUMIFS(Budget!F:F,Budget!B:B,ActiveProject,Budget!D:D,A21) | C21: =SUMIFS(Expenses!H:H,Expenses!C:C,ActiveProject,Expenses!E:E,A21,Expenses!J:J,"Paid") | D21: =SUMIFS(Expenses!H:H,Expenses!C:C,ActiveProject,Expenses!E:E,A21,Expenses!J:J,"Committed") | E21: =B21-C21-D21 | F21: =IF(B21=0,"",(C21+D21)/B21) | H21: Laundry | I21: =SUMIF(Rooms!A:A,"RM-07",Rooms!K:K) | J21: =SUMIFS(Expenses!H:H,Expenses!D:D,"RM-07",Expenses!J:J,"Paid") | K21: =SUMIFS(Expenses!H:H,Expenses!D:D,"RM-07",Expenses!J:J,"Committed") | L21: =I21-J21-K21 | M21: =IF(I21=0,"",(J21+K21)/I21)
A22: Furniture | B22: =SUMIFS(Budget!F:F,Budget!B:B,ActiveProject,Budget!D:D,A22) | C22: =SUMIFS(Expenses!H:H,Expenses!C:C,ActiveProject,Expenses!E:E,A22,Expenses!J:J,"Paid") | D22: =SUMIFS(Expenses!H:H,Expenses!C:C,ActiveProject,Expenses!E:E,A22,Expenses!J:J,"Committed") | E22: =B22-C22-D22 | F22: =IF(B22=0,"",(C22+D22)/B22) | H22: Entry / Foyer | I22: =SUMIF(Rooms!A:A,"RM-08",Rooms!K:K) | J22: =SUMIFS(Expenses!H:H,Expenses!D:D,"RM-08",Expenses!J:J,"Paid") | K22: =SUMIFS(Expenses!H:H,Expenses!D:D,"RM-08",Expenses!J:J,"Committed") | L22: =I22-J22-K22 | M22: =IF(I22=0,"",(J22+K22)/I22)
A23: Inspections | B23: =SUMIFS(Budget!F:F,Budget!B:B,ActiveProject,Budget!D:D,A23) | C23: =SUMIFS(Expenses!H:H,Expenses!C:C,ActiveProject,Expenses!E:E,A23,Expenses!J:J,"Paid") | D23: =SUMIFS(Expenses!H:H,Expenses!C:C,ActiveProject,Expenses!E:E,A23,Expenses!J:J,"Committed") | E23: =B23-C23-D23 | F23: =IF(B23=0,"",(C23+D23)/B23) | H23: =IFERROR(INDEX(Rooms!$C:$C,SMALL(IF(Rooms!$B$5:$B$80=ActiveProject,ROW(Rooms!$B$5:$B$80)),9)),"")
A24: Other | B24: =SUMIFS(Budget!F:F,Budget!B:B,ActiveProject,Budget!D:D,A24) | C24: =SUMIFS(Expenses!H:H,Expenses!C:C,ActiveProject,Expenses!E:E,A24,Expenses!J:J,"Paid") | D24: =SUMIFS(Expenses!H:H,Expenses!C:C,ActiveProject,Expenses!E:E,A24,Expenses!J:J,"Committed") | E24: =B24-C24-D24 | F24: =IF(B24=0,"",(C24+D24)/B24) | H24: =IFERROR(INDEX(Rooms!$C:$C,SMALL(IF(Rooms!$B$5:$B$80=ActiveProject,ROW(Rooms!$B$5:$B$80)),10)),"")
H25: =IFERROR(INDEX(Rooms!$C:$C,SMALL(IF(Rooms!$B$5:$B$80=ActiveProject,ROW(Rooms!$B$5:$B$80)),11)),"")
H26: =IFERROR(INDEX(Rooms!$C:$C,SMALL(IF(Rooms!$B$5:$B$80=ActiveProject,ROW(Rooms!$B$5:$B$80)),12)),"")
A27: Monthly spending (paid)
A28: Month | B28: Spent | C28: Committed dated | H28: Smart alerts
A29: Mar 2026 | B29: =SUMIFS(Expenses!H:H,Expenses!C:C,ActiveProject,Expenses!J:J,"Paid",Expenses!B:B,">="&DATE(2026,3,1),Expenses!B:B,"<"&DATE(2026,4,1)) | C29: =SUMIFS(Expenses!H:H,Expenses!C:C,ActiveProject,Expenses!J:J,"Committed",Expenses!B:B,">="&DATE(2026,3,1),Expenses!B:B,"<"&DATE(2026,4,1)) | H29: =IF((D6+G6)>A6,"🔴 Project is over planned budget","🟢 Project within planned budget")
A30: Apr 2026 | B30: =SUMIFS(Expenses!H:H,Expenses!C:C,ActiveProject,Expenses!J:J,"Paid",Expenses!B:B,">="&DATE(2026,4,1),Expenses!B:B,"<"&DATE(2026,5,1)) | C30: =SUMIFS(Expenses!H:H,Expenses!C:C,ActiveProject,Expenses!J:J,"Committed",Expenses!B:B,">="&DATE(2026,4,1),Expenses!B:B,"<"&DATE(2026,5,1)) | H30: =IF(D10<A6*ContingencyFloor,"🔴 Contingency has fallen below the threshold","🟢 Contingency healthy")
A31: May 2026 | B31: =SUMIFS(Expenses!H:H,Expenses!C:C,ActiveProject,Expenses!J:J,"Paid",Expenses!B:B,">="&DATE(2026,5,1),Expenses!B:B,"<"&DATE(2026,6,1)) | C31: =SUMIFS(Expenses!H:H,Expenses!C:C,ActiveProject,Expenses!J:J,"Committed",Expenses!B:B,">="&DATE(2026,5,1),Expenses!B:B,"<"&DATE(2026,6,1)) | H31: =IFERROR(IF(SUMIFS(Rooms!R:R,Rooms!B:B,ActiveProject,Rooms!C:C,"Kitchen")+SUMIFS(Rooms!S:S,Rooms!B:B,ActiveProject,Rooms!C:C,"Kitchen")>SUMIFS(Rooms!K:K,Rooms!B:B,ActiveProject,Rooms!C:C,"Kitchen"),"⚠️ Kitchen is over its room budget","🟢 Kitchen within room budget"),"")
A32: Jun 2026 | B32: =SUMIFS(Expenses!H:H,Expenses!C:C,ActiveProject,Expenses!J:J,"Paid",Expenses!B:B,">="&DATE(2026,6,1),Expenses!B:B,"<"&DATE(2026,7,1)) | C32: =SUMIFS(Expenses!H:H,Expenses!C:C,ActiveProject,Expenses!J:J,"Committed",Expenses!B:B,">="&DATE(2026,6,1),Expenses!B:B,"<"&DATE(2026,7,1)) | H32: =IFERROR(IF(SUMIFS(Rooms!R:R,Rooms!B:B,ActiveProject,Rooms!C:C,"Primary Bathroom")+SUMIFS(Rooms!S:S,Rooms!B:B,ActiveProject,Rooms!C:C,"Primary Bathroom")<SUMIFS(Rooms!K:K,Rooms!B:B,ActiveProject,Rooms!C:C,"Primary Bathroom"),"🟢 Primary bathroom is under budget","⚠️ Primary bathroom at or over budget"),"")
A33: Jul 2026 | B33: =SUMIFS(Expenses!H:H,Expenses!C:C,ActiveProject,Expenses!J:J,"Paid",Expenses!B:B,">="&DATE(2026,7,1),Expenses!B:B,"<"&DATE(2026,8,1)) | C33: =SUMIFS(Expenses!H:H,Expenses!C:C,ActiveProject,Expenses!J:J,"Committed",Expenses!B:B,">="&DATE(2026,7,1),Expenses!B:B,"<"&DATE(2026,8,1)) | H33: ="As of "&TEXT(AsOfDate,"YYYY-MM-DD")&" · Active project "&ActiveProject
A34: Aug 2026 | B34: =SUMIFS(Expenses!H:H,Expenses!C:C,ActiveProject,Expenses!J:J,"Paid",Expenses!B:B,">="&DATE(2026,8,1),Expenses!B:B,"<"&DATE(2026,9,1)) | C34: =SUMIFS(Expenses!H:H,Expenses!C:C,ActiveProject,Expenses!J:J,"Committed",Expenses!B:B,">="&DATE(2026,8,1),Expenses!B:B,"<"&DATE(2026,9,1))
A35: Sep 2026 | B35: =SUMIFS(Expenses!H:H,Expenses!C:C,ActiveProject,Expenses!J:J,"Paid",Expenses!B:B,">="&DATE(2026,9,1),Expenses!B:B,"<"&DATE(2026,10,1)) | C35: =SUMIFS(Expenses!H:H,Expenses!C:C,ActiveProject,Expenses!J:J,"Committed",Expenses!B:B,">="&DATE(2026,9,1),Expenses!B:B,"<"&DATE(2026,10,1))
A36: Oct 2026 | B36: =SUMIFS(Expenses!H:H,Expenses!C:C,ActiveProject,Expenses!J:J,"Paid",Expenses!B:B,">="&DATE(2026,10,1),Expenses!B:B,"<"&DATE(2026,11,1)) | C36: =SUMIFS(Expenses!H:H,Expenses!C:C,ActiveProject,Expenses!J:J,"Committed",Expenses!B:B,">="&DATE(2026,10,1),Expenses!B:B,"<"&DATE(2026,11,1))
A37: Nov 2026 | B37: =SUMIFS(Expenses!H:H,Expenses!C:C,ActiveProject,Expenses!J:J,"Paid",Expenses!B:B,">="&DATE(2026,11,1),Expenses!B:B,"<"&DATE(2026,12,1)) | C37: =SUMIFS(Expenses!H:H,Expenses!C:C,ActiveProject,Expenses!J:J,"Committed",Expenses!B:B,">="&DATE(2026,11,1),Expenses!B:B,"<"&DATE(2026,12,1))

Sheet Contractors
A1: CONTRACTORS
A2: Profiles, insurance, licenses · Score = average of Quality / On-time / Budget / Communication
A4: Contractor ID | B4: Company | C4: Contact | D4: Trade | E4: Skills | F4: Phone | G4: Email | H4: Rating | I4: Quality | J4: On-Time | K4: Budget | L4: Communication | M4: Score | N4: Insurance Exp | O4: License | P4: Availability | Q4: Rate ($/hr) | R4: Status | S4: Portfolio
A5: CTR-001 | B5: Cascade Cabinets | C5: Maya Chen | D5: Cabinetry | E5: Custom millwork, inset doors | F5: +1-503-555-0111 | G5: maya@cascadecabinets.example | H5: 4.8 | I5: 0.92 | J5: 0.87 | K5: 0.95 | L5: 0.9 | M5: =IF($A5="","",AVERAGE(I5:L5)) | N5: 46447 | O5: CCB-210998 | P5: Aug 20–Sep 15 | Q5: 85 | R5: Active | S5: drive/portfolio/cascade
A6: CTR-002 | B6: Northwest Electric | C6: Jordan Hale | D6: Electrical | E6: Residential remodel, lighting | F6: +1-503-555-0133 | G6: jordan@nw-electric.example | H6: 4.7 | I6: 0.94 | J6: 0.91 | K6: 0.88 | L6: 0.86 | M6: =IF($A6="","",AVERAGE(I6:L6)) | N6: 46371 | O6: EL-44821 | P6: On call | Q6: 110 | R6: Active | S6: drive/portfolio/nwe
A7: CTR-003 | B7: Pacific Plumbing | C7: Sam Ortiz | D7: Plumbing | E7: Repipe, fixtures, radiant | F7: +1-503-555-0140 | G7: sam@pacificplumbing.example | H7: 4.6 | I7: 0.9 | J7: 0.84 | K7: 0.93 | L7: 0.88 | M7: =IF($A7="","",AVERAGE(I7:L7)) | N7: 46407 | O7: PL-77310 | P7: Wrap this week | Q7: 120 | R7: Active | S7: drive/portfolio/pp
A8: CTR-004 | B8: Heritage Tile & Stone | C8: Priya Shah | D8: Tile & Stone | E8: Porcelain, slab, steam | F8: +1-503-555-0155 | G8: priya@heritagetile.example | H8: 4.9 | I8: 0.96 | J8: 0.89 | K8: 0.91 | L8: 0.93 | M8: =IF($A8="","",AVERAGE(I8:L8)) | N8: 46539 | O8: CCB-188442 | P8: Punch list | Q8: 95 | R8: Active | S8: drive/portfolio/heritage
A9: CTR-005 | B9: Greenfield Painting | C9: Leo Park | D9: Painting | E9: Plaster, limewash, cabinets | F9: +1-503-555-0122 | G9: leo@greenfieldpaint.example | H9: 4.5 | I9: 0.88 | J9: 0.9 | K9: 0.86 | L9: 0.91 | M9: =IF($A9="","",AVERAGE(I9:L9)) | N9: 46356 | O9: CCB-201774 | P9: Sep 10–28 | Q9: 65 | R9: Active | S9: drive/portfolio/greenfield
A10: CTR-006 | B10: Timberline Floors | C10: Elena Voss | D10: Flooring | E10: White oak, site finish | F10: +1-503-555-0166 | G10: elena@timberlinefloors.example | H10: 4.7 | I10: 0.91 | J10: 0.83 | K10: 0.9 | L10: 0.87 | M10: =IF($A10="","",AVERAGE(I10:L10)) | N10: 46432 | O10: CCB-176330 | P10: Through Aug 28 | Q10: 8 | R10: Active | S10: drive/portfolio/timberline
A11: CTR-007 | B11: Luna Interiors | C11: Sofia Alvarez | D11: Interior Designer | E11: Residential, kitchen, bath | F11: +1-503-555-0194 | G11: sofia@lunainteriors.example | H11: 4.9 | I11: 0.95 | J11: 0.94 | K11: 0.89 | L11: 0.97 | M11: =IF($A11="","",AVERAGE(I11:L11)) | N11: 46296 | O11: ASID-4491 | P11: Ongoing | Q11: 145 | R11: Active | S11: drive/portfolio/luna
A12: CTR-008 | B12: Ironwood Construction | C12: Marcus Webb | D12: General Contractor | E12: Remodel GC, historic homes | F12: +1-503-555-0172 | G12: marcus@ironwood.build | H12: 4.8 | I12: 0.93 | J12: 0.88 | K12: 0.92 | L12: 0.94 | M12: =IF($A12="","",AVERAGE(I12:L12)) | N12: 46507 | O12: CCB-154009 | P12: Full project | Q12: 0 | R12: Active | S12: drive/portfolio/ironwood
A13: CTR-009 | B13: BrightPath Lighting | C13: Nina Cho | D13: Lighting | E13: Specification + supply | F13: +1-503-555-0180 | G13: nina@brightpath.example | H13: 4.6 | I13: 0.9 | J13: 0.92 | K13: 0.94 | L13: 0.89 | M13: =IF($A13="","",AVERAGE(I13:L13)) | N13: 46295 | O13: SUP-8891 | P13: Lead time 3 wks | Q13: 0 | R13: Active | S13: drive/portfolio/brightpath
A14: CTR-010 | B14: Garden & Gate | C14: Theo Brooks | D14: Landscaping | E14: Paths, planting, irrigation | F14: +1-503-555-0199 | G14: theo@gardengate.example | H14: 4.4 | I14: 0.86 | J14: 0.8 | K14: 0.88 | L14: 0.85 | M14: =IF($A14="","",AVERAGE(I14:L14)) | N14: 46508 | O14: LCB-3320 | P14: Oct window | Q14: 70 | R14: Active | S14: drive/portfolio/gg
A15: CTR-011 | B15: Alder Inspection Group | C15: Riley Grant | D15: Inspection | E15: Independent punch | F15: +1-503-555-0188 | G15: riley@alderinspect.example | H15: 4.8 | I15: 0.97 | J15: 0.95 | K15: 1 | L15: 0.9 | M15: =IF($A15="","",AVERAGE(I15:L15)) | N15: 46387 | O15: OR-INSP-220 | P15: On call | Q15: 175 | R15: Active

Sheet Quotes
A1: QUOTES
A2: Request → receive → compare → award
A4: Quote ID | B4: Project ID | C4: Room ID | D4: Contractor ID | E4: Trade | F4: Scope | G4: Amount | H4: Timeline (days) | I4: Valid Until | J4: Status | K4: Notes
A5: Q-001 | B5: PRJ-001 | C5: RM-01 | D5: CTR-001 | E5: Cabinetry | F5: Full kitchen millwork — sage shaker + walnut island | G5: 14800 | H5: 18 | I5: 46172 | J5: Accepted | K5: Awarded. Deposit paid.
A6: Q-002 | B6: PRJ-001 | C6: RM-01 | D6: CTR-001 | E6: Cabinetry | F6: Alternate: all walnut | G6: 18600 | H6: 22 | I6: 46172 | J6: Rejected | K6: Over palette and budget.
A7: Q-003 | B7: PRJ-001 | C7: RM-03 | D7: CTR-004 | E7: Tile & Stone | F7: Marble floor + shower | G7: 9100 | H7: 14 | I7: 46162 | J7: Rejected | K7: AI flagged 18% save with porcelain.
A8: Q-004 | B8: PRJ-001 | C8: RM-03 | D8: CTR-004 | E8: Tile & Stone | F8: Porcelain floor + shower + slab niche | G8: 7460 | H8: 12 | I8: 46162 | J8: Accepted | K8: Selected.
A9: Q-005 | B9: PRJ-001 | D9: CTR-009 | E9: Lighting | F9: Whole-home spec package | G9: 4120 | H9: 21 | I9: 46188 | J9: Accepted | K9: Best communication score.
A10: Q-006 | B10: PRJ-001 | D10: CTR-009 | E10: Lighting | F10: Competitor A package | G10: 3680 | H10: 28 | I10: 46188 | J10: Compared | K10: Cheaper, slower, weaker spec.
A11: Q-007 | B11: PRJ-001 | D11: CTR-009 | E11: Lighting | F11: Competitor B package | G11: 4490 | H11: 18 | I11: 46188 | J11: Compared | K11: Premium, not needed.
A12: Q-008 | B12: PRJ-001 | C12: RM-02 | D12: CTR-006 | E12: Flooring | F12: White oak supply + install | G12: 8600 | H12: 16 | I12: 46174 | J12: Accepted | K12: Shared across 3 rooms.
A13: Q-009 | B13: PRJ-001 | C13: RM-06 | D13: CTR-010 | E13: Landscaping | F13: Path + planting + lighting | G13: 7400 | H13: 12 | I13: 46280 | J13: Received | K13: Hold extras until contingency recovers.
A14: Q-010 | B14: PRJ-002 | C14: RM-09 | D14: CTR-004 | E14: Tile & Stone | F14: Cabin bath tile package | G14: 5400 | H14: 10 | I14: 46325 | J14: Requested

Sheet Jobs
A1: JOBS
A2: Assigned work, milestones, balances
A4: Job ID | B4: Project ID | C4: Room ID | D4: Contractor ID | E4: Quote ID | F4: Scope | G4: Start | H4: End | I4: Milestone | J4: Status | K4: Amount | L4: Paid | M4: Balance | N4: % Paid
A5: JOB-001 | B5: PRJ-001 | D5: CTR-008 | E5: Q-000 | F5: GC / project management | G5: 46082 | H5: 46341 | I5: Monthly supervision | J5: In Progress | K5: 6200 | L5: 4350 | M5: =IF($A5="","",$K5-$L5) | N5: =IF(OR($A5="",$K5=0),"",$L5/$K5)
A6: JOB-002 | B6: PRJ-001 | C6: RM-01 | D6: CTR-001 | E6: Q-001 | F6: Kitchen cabinetry fabricate + install | G6: 46254 | H6: 46280 | I6: Boxes set; doors next | J6: In Progress | K6: 18400 | L6: 7400 | M6: =IF($A6="","",$K6-$L6) | N6: =IF(OR($A6="",$K6=0),"",$L6/$K6)
A7: JOB-003 | B7: PRJ-001 | C7: RM-03 | D7: CTR-004 | E7: Q-004 | F7: Primary bath tile | G7: 46211 | H7: 46246 | I7: Complete — punch remaining | J7: Milestone Review | K7: 7460 | L7: 7460 | M7: =IF($A7="","",$K7-$L7) | N7: =IF(OR($A7="",$K7=0),"",$L7/$K7)
A8: JOB-004 | B8: PRJ-001 | C8: RM-01 | D8: CTR-002 | E8: Q-000 | F8: Electrical rough + finish | G8: 46174 | H8: 46285 | I8: Finish pending cabinets | J8: In Progress | K8: 2620 | L8: 2620 | M8: =IF($A8="","",$K8-$L8) | N8: =IF(OR($A8="",$K8=0),"",$L8/$K8)
A9: JOB-005 | B9: PRJ-001 | C9: RM-03 | D9: CTR-003 | E9: Q-000 | F9: Plumbing rough + trim | G9: 46181 | H9: 46248 | I9: Trim complete | J9: Complete | K9: 5140 | L9: 5140 | M9: =IF($A9="","",$K9-$L9) | N9: =IF(OR($A9="",$K9=0),"",$L9/$K9)
A10: JOB-006 | B10: PRJ-001 | C10: RM-02 | D10: CTR-006 | E10: Q-008 | F10: Flooring install | G10: 46239 | H10: 46262 | I10: Sand/finish this week | J10: In Progress | K10: 8600 | L10: 8200 | M10: =IF($A10="","",$K10-$L10) | N10: =IF(OR($A10="",$K10=0),"",$L10/$K10)
A11: JOB-007 | B11: PRJ-001 | D11: CTR-007 | E11: Q-000 | F11: Interior design services | G11: 46082 | H11: 46327 | I11: FF&E procurement | J11: In Progress | K11: 4800 | L11: 4200 | M11: =IF($A11="","",$K11-$L11) | N11: =IF(OR($A11="",$K11=0),"",$L11/$K11)
A12: JOB-008 | B12: PRJ-001 | C12: RM-04 | D12: CTR-005 | E12: Q-000 | F12: Paint guest + dining + entry | G12: 46275 | H12: 46293 | I12: Scheduled | J12: Scheduled | K12: 3600 | L12: 0 | M12: =IF($A12="","",$K12-$L12) | N12: =IF(OR($A12="",$K12=0),"",$L12/$K12)
A13: JOB-009 | B13: PRJ-001 | C13: RM-06 | D13: CTR-010 | E13: Q-009 | F13: Exterior path + porch | G13: 46301 | H13: 46319 | I13: Not released | J13: Assigned | K13: 7400 | L13: 0 | M13: =IF($A13="","",$K13-$L13) | N13: =IF(OR($A13="",$K13=0),"",$L13/$K13)
A14: JOB-010 | B14: PRJ-001 | D14: CTR-009 | E14: Q-005 | F14: Lighting supply | G14: 46204 | H14: 46285 | I14: Pendants in transit | J14: In Progress | K14: 4120 | L14: 380 | M14: =IF($A14="","",$K14-$L14) | N14: =IF(OR($A14="",$K14=0),"",$L14/$K14)

Sheet Tasks
A1: TASKS
A2: Kanban fields · To Do → Scheduled → In Progress → Inspection → Completed
A4: Task ID | B4: Project ID | C4: Room ID | D4: Title | E4: Description | F4: Assignee | G4: Role | H4: Status | I4: Priority | J4: Start | K4: Deadline | L4: Cost | M4: Depends On | N4: % Complete | O4: Attachments / Comments | P4: Days Left | Q4: Health
A5: TSK-001 | B5: PRJ-001 | D5: Kickoff + scope lock | E5: Confirm rooms, budget, style. | F5: Marcus Webb | G5: Project Manager | H5: Completed | I5: High | J5: 46082 | K5: 46089 | L5: 0 | N5: 1 | O5: drive/notes/kickoff | P5: =IF(OR($A5="",$K5=""),"", $K5-AsOfDate) | Q5: =IF($A5="","",IF($H5="Completed","Done",IF($K5<AsOfDate,"Overdue",IF($K5<=AsOfDate+7,"Due Soon","On Track"))))
A6: TSK-002 | B6: PRJ-001 | C6: RM-01 | D6: Kitchen measured drawings | E6: Field measure + as-builts. | F6: Sofia Alvarez | G6: Interior Designer | H6: Completed | I6: High | J6: 46091 | K6: 46101 | L6: 0 | N6: 1 | P6: =IF(OR($A6="",$K6=""),"", $K6-AsOfDate) | Q6: =IF($A6="","",IF($H6="Completed","Done",IF($K6<AsOfDate,"Overdue",IF($K6<=AsOfDate+7,"Due Soon","On Track"))))
A7: TSK-003 | B7: PRJ-001 | D7: Submit building permit | E7: Packet to City of Portland. | F7: Marcus Webb | G7: Project Manager | H7: Completed | I7: Critical | J7: 46113 | K7: 46122 | L7: 840 | N7: 1 | P7: =IF(OR($A7="",$K7=""),"", $K7-AsOfDate) | Q7: =IF($A7="","",IF($H7="Completed","Done",IF($K7<AsOfDate,"Overdue",IF($K7<=AsOfDate+7,"Due Soon","On Track"))))
A8: TSK-004 | B8: PRJ-001 | C8: RM-01 | D8: Kitchen demolition | E8: Cabinets, floor, plaster. | F8: Marcus Webb | G8: Project Manager | H8: Completed | I8: High | J8: 46163 | K8: 46178 | L8: 2800 | M8: TSK-003 | N8: 1 | O8: drive/photos/demo | P8: =IF(OR($A8="",$K8=""),"", $K8-AsOfDate) | Q8: =IF($A8="","",IF($H8="Completed","Done",IF($K8<AsOfDate,"Overdue",IF($K8<=AsOfDate+7,"Due Soon","On Track"))))
A9: TSK-005 | B9: PRJ-001 | C9: RM-01 | D9: Electrical rough-in | E9: New circuits, island, lighting. | F9: Jordan Hale | G9: Subcontractor | H9: Completed | I9: High | J9: 46174 | K9: 46193 | L9: 1900 | M9: TSK-004 | N9: 1 | P9: =IF(OR($A9="",$K9=""),"", $K9-AsOfDate) | Q9: =IF($A9="","",IF($H9="Completed","Done",IF($K9<AsOfDate,"Overdue",IF($K9<=AsOfDate+7,"Due Soon","On Track"))))
A10: TSK-006 | B10: PRJ-001 | C10: RM-03 | D10: Plumbing rough-in | E10: Bath + laundry + kitchen stub. | F10: Sam Ortiz | G10: Contractor | H10: Completed | I10: High | J10: 46181 | K10: 46201 | L10: 2400 | M10: TSK-004 | N10: 1 | P10: =IF(OR($A10="",$K10=""),"", $K10-AsOfDate) | Q10: =IF($A10="","",IF($H10="Completed","Done",IF($K10<AsOfDate,"Overdue",IF($K10<=AsOfDate+7,"Due Soon","On Track"))))
A11: TSK-007 | B11: PRJ-001 | C11: RM-03 | D11: Heated floor install | E11: WarmFloor mat + thermostat. | F11: Sam Ortiz | G11: Contractor | H11: Completed | I11: Medium | J11: 46205 | K11: 46209 | L11: 1680 | M11: TSK-006 | N11: 1 | P11: =IF(OR($A11="",$K11=""),"", $K11-AsOfDate) | Q11: =IF($A11="","",IF($H11="Completed","Done",IF($K11<AsOfDate,"Overdue",IF($K11<=AsOfDate+7,"Due Soon","On Track"))))
A12: TSK-008 | B12: PRJ-001 | C12: RM-03 | D12: Tile primary bath | E12: Floor, shower, niche. | F12: Priya Shah | G12: Contractor | H12: Completed | I12: High | J12: 46211 | K12: 46242 | L12: 4200 | M12: TSK-007 | N12: 1 | P12: =IF(OR($A12="",$K12=""),"", $K12-AsOfDate) | Q12: =IF($A12="","",IF($H12="Completed","Done",IF($K12<AsOfDate,"Overdue",IF($K12<=AsOfDate+7,"Due Soon","On Track"))))
A13: TSK-009 | B13: PRJ-001 | C13: RM-03 | D13: Bath fixture trim | E13: Valve trims, vanity, toilet, glass. | F13: Sam Ortiz | G13: Contractor | H13: Completed | I13: High | J13: 46243 | K13: 46248 | L13: 1460 | M13: TSK-008 | N13: 1 | P13: =IF(OR($A13="",$K13=""),"", $K13-AsOfDate) | Q13: =IF($A13="","",IF($H13="Completed","Done",IF($K13<AsOfDate,"Overdue",IF($K13<=AsOfDate+7,"Due Soon","On Track"))))
A14: TSK-010 | B14: PRJ-001 | C14: RM-03 | D14: Primary bath punch | E14: Silicone, grout haze, door align. | F14: Priya Shah | G14: Contractor | H14: Inspection | I14: Medium | J14: 46252 | K14: 46260 | L14: 0 | M14: TSK-009 | N14: 0.8 | P14: =IF(OR($A14="",$K14=""),"", $K14-AsOfDate) | Q14: =IF($A14="","",IF($H14="Completed","Done",IF($K14<AsOfDate,"Overdue",IF($K14<=AsOfDate+7,"Due Soon","On Track"))))
A15: TSK-011 | B15: PRJ-001 | C15: RM-07 | D15: Laundry complete | E15: Tile splash + utility sink. | F15: Sam Ortiz | G15: Contractor | H15: Completed | I15: Low | J15: 46221 | K15: 46227 | L15: 1840 | N15: 1 | P15: =IF(OR($A15="",$K15=""),"", $K15-AsOfDate) | Q15: =IF($A15="","",IF($H15="Completed","Done",IF($K15<AsOfDate,"Overdue",IF($K15<=AsOfDate+7,"Due Soon","On Track"))))
A16: TSK-012 | B16: PRJ-001 | C16: RM-01 | D16: White oak flooring | E16: Install kitchen/living/dining. | F16: Elena Voss | G16: Contractor | H16: In Progress | I16: Critical | J16: 46239 | K16: 46262 | L16: 8200 | M16: TSK-005 | N16: 0.75 | P16: =IF(OR($A16="",$K16=""),"", $K16-AsOfDate) | Q16: =IF($A16="","",IF($H16="Completed","Done",IF($K16<AsOfDate,"Overdue",IF($K16<=AsOfDate+7,"Due Soon","On Track"))))
A17: TSK-013 | B17: PRJ-001 | C17: RM-01 | D17: Cabinet box set | E17: Set boxes, scribe, level island. | F17: Maya Chen | G17: Contractor | H17: In Progress | I17: Critical | J17: 46254 | K17: 46261 | L17: 0 | M17: TSK-012 | N17: 0.55 | P17: =IF(OR($A17="",$K17=""),"", $K17-AsOfDate) | Q17: =IF($A17="","",IF($H17="Completed","Done",IF($K17<AsOfDate,"Overdue",IF($K17<=AsOfDate+7,"Due Soon","On Track"))))
A18: TSK-014 | B18: PRJ-001 | C18: RM-01 | D18: Cabinet doors + hardware | E18: Hang doors, install pulls. | F18: Maya Chen | G18: Contractor | H18: Scheduled | I18: Critical | J18: 46262 | K18: 46270 | L18: 0 | M18: TSK-013 | N18: 0 | O18: Hardware in transit | P18: =IF(OR($A18="",$K18=""),"", $K18-AsOfDate) | Q18: =IF($A18="","",IF($H18="Completed","Done",IF($K18<AsOfDate,"Overdue",IF($K18<=AsOfDate+7,"Due Soon","On Track"))))
A19: TSK-015 | B19: PRJ-001 | C19: RM-01 | D19: Counter template | E19: Quartz + island porcelain. | F19: Heritage Tile | G19: Contractor | H19: Scheduled | I19: High | J19: 46269 | K19: 46269 | L19: 0 | M19: TSK-014 | N19: 0 | P19: =IF(OR($A19="",$K19=""),"", $K19-AsOfDate) | Q19: =IF($A19="","",IF($H19="Completed","Done",IF($K19<AsOfDate,"Overdue",IF($K19<=AsOfDate+7,"Due Soon","On Track"))))
A20: TSK-016 | B20: PRJ-001 | C20: RM-01 | D20: Counter install | E20: Set, seam, sink. | F20: Heritage Tile | G20: Contractor | H20: To Do | I20: High | J20: 46275 | K20: 46276 | L20: 1860 | M20: TSK-015 | N20: 0 | P20: =IF(OR($A20="",$K20=""),"", $K20-AsOfDate) | Q20: =IF($A20="","",IF($H20="Completed","Done",IF($K20<AsOfDate,"Overdue",IF($K20<=AsOfDate+7,"Due Soon","On Track"))))
A21: TSK-017 | B21: PRJ-001 | C21: RM-01 | D21: Appliance delivery | E21: Range, fridge, DW. | F21: Alex Rivera | G21: Homeowner | H21: Scheduled | I21: High | J21: 46277 | K21: 46277 | L21: 2700 | M21: TSK-016 | N21: 0 | P21: =IF(OR($A21="",$K21=""),"", $K21-AsOfDate) | Q21: =IF($A21="","",IF($H21="Completed","Done",IF($K21<AsOfDate,"Overdue",IF($K21<=AsOfDate+7,"Due Soon","On Track"))))
A22: TSK-018 | B22: PRJ-001 | C22: RM-01 | D22: Island pendant hang | E22: Three aged-brass pendants. | F22: Nina Cho | G22: Supplier | H22: To Do | I22: Medium | J22: 46281 | K22: 46281 | L22: 890 | M22: TSK-017 | N22: 0 | P22: =IF(OR($A22="",$K22=""),"", $K22-AsOfDate) | Q22: =IF($A22="","",IF($H22="Completed","Done",IF($K22<AsOfDate,"Overdue",IF($K22<=AsOfDate+7,"Due Soon","On Track"))))
A23: TSK-019 | B23: PRJ-001 | C23: RM-04 | D23: Guest bedroom paint | E23: Clay + linen palette. | F23: Leo Park | G23: Contractor | H23: Scheduled | I23: Medium | J23: 46275 | K23: 46281 | L23: 240 | N23: 0 | O23: Awaiting palette lock | P23: =IF(OR($A23="",$K23=""),"", $K23-AsOfDate) | Q23: =IF($A23="","",IF($H23="Completed","Done",IF($K23<AsOfDate,"Overdue",IF($K23<=AsOfDate+7,"Due Soon","On Track"))))
A24: TSK-020 | B24: PRJ-001 | C24: RM-05 | D24: Dining plaster + paint | E24: Repair north wall, paint. | F24: Leo Park | G24: Contractor | H24: Scheduled | I24: Medium | J24: 46282 | K24: 46287 | L24: 0 | N24: 0 | P24: =IF(OR($A24="",$K24=""),"", $K24-AsOfDate) | Q24: =IF($A24="","",IF($H24="Completed","Done",IF($K24<AsOfDate,"Overdue",IF($K24<=AsOfDate+7,"Due Soon","On Track"))))
A25: TSK-021 | B25: PRJ-001 | C25: RM-08 | D25: Entry bench + rail | E25: White oak bench, brass hooks. | F25: Marcus Webb | G25: Project Manager | H25: In Progress | I25: Low | J25: 46252 | K25: 46263 | L25: 186 | N25: 0.4 | P25: =IF(OR($A25="",$K25=""),"", $K25-AsOfDate) | Q25: =IF($A25="","",IF($H25="Completed","Done",IF($K25<AsOfDate,"Overdue",IF($K25<=AsOfDate+7,"Due Soon","On Track"))))
A26: TSK-022 | B26: PRJ-001 | C26: RM-02 | D26: Living furniture order | E26: Sofa + table. 6-week lead. | F26: Sofia Alvarez | G26: Interior Designer | H26: To Do | I26: High | J26: 46266 | K26: 46266 | L26: 3400 | N26: 0 | O26: Order by Sep 1 | P26: =IF(OR($A26="",$K26=""),"", $K26-AsOfDate) | Q26: =IF($A26="","",IF($H26="Completed","Done",IF($K26<AsOfDate,"Overdue",IF($K26<=AsOfDate+7,"Due Soon","On Track"))))
A27: TSK-023 | B27: PRJ-001 | C27: RM-06 | D27: Exterior path layout | E27: Stake path, confirm stone. | F27: Theo Brooks | G27: Contractor | H27: To Do | I27: Low | J27: 46301 | K27: 46303 | L27: 0 | N27: 0 | O27: Hold extras | P27: =IF(OR($A27="",$K27=""),"", $K27-AsOfDate) | Q27: =IF($A27="","",IF($H27="Completed","Done",IF($K27<AsOfDate,"Overdue",IF($K27<=AsOfDate+7,"Due Soon","On Track"))))
A28: TSK-024 | B28: PRJ-001 | D28: Final city inspection | E28: Building final. | F28: Riley Grant | G28: Inspector | H28: To Do | I28: Critical | J28: 46320 | K28: 46331 | L28: 175 | M28: TSK-018 | N28: 0 | P28: =IF(OR($A28="",$K28=""),"", $K28-AsOfDate) | Q28: =IF($A28="","",IF($H28="Completed","Done",IF($K28<AsOfDate,"Overdue",IF($K28<=AsOfDate+7,"Due Soon","On Track"))))
A29: TSK-025 | B29: PRJ-001 | D29: Homeowner walkthrough | E29: Punch list + handover packet. | F29: Marcus Webb | G29: Project Manager | H29: To Do | I29: High | J29: 46336 | K29: 46341 | L29: 0 | M29: TSK-024 | N29: 0 | P29: =IF(OR($A29="",$K29=""),"", $K29-AsOfDate) | Q29: =IF($A29="","",IF($H29="Completed","Done",IF($K29<AsOfDate,"Overdue",IF($K29<=AsOfDate+7,"Due Soon","On Track"))))
A30: TSK-026 | B30: PRJ-001 | C30: RM-01 | D30: Approve island slab | E30: Confirm porcelain vs leftover quartz. | F30: Alex Rivera | G30: Homeowner | H30: In Progress | I30: High | J30: 46256 | K30: 46259 | L30: 0 | M30: AI-001 | N30: 0.5 | O30: Pending approval | P30: =IF(OR($A30="",$K30=""),"", $K30-AsOfDate) | Q30: =IF($A30="","",IF($H30="Completed","Done",IF($K30<AsOfDate,"Overdue",IF($K30<=AsOfDate+7,"Due Soon","On Track"))))
A31: TSK-027 | B31: PRJ-001 | D31: Weekly site meeting | E31: GC + designer + homeowner. | F31: Marcus Webb | G31: Project Manager | H31: Scheduled | I31: Medium | J31: 46259 | K31: 46259 | L31: 0 | N31: 0 | O31: Tue 9:00 | P31: =IF(OR($A31="",$K31=""),"", $K31-AsOfDate) | Q31: =IF($A31="","",IF($H31="Completed","Done",IF($K31<AsOfDate,"Overdue",IF($K31<=AsOfDate+7,"Due Soon","On Track"))))
A32: TSK-028 | B32: PRJ-002 | C32: RM-09 | D32: Cabin bath concept | E32: Japandi mood board lock. | F32: Sofia Alvarez | G32: Interior Designer | H32: In Progress | I32: Low | J32: 46235 | K32: 46280 | L32: 600 | N32: 0.4 | P32: =IF(OR($A32="",$K32=""),"", $K32-AsOfDate) | Q32: =IF($A32="","",IF($H32="Completed","Done",IF($K32<AsOfDate,"Overdue",IF($K32<=AsOfDate+7,"Due Soon","On Track"))))
A33: TSK-029 | B33: PRJ-001 | C33: RM-01 | D33: Backsplash layout | E33: Zellige sample on site. | F33: Sofia Alvarez | G33: Interior Designer | H33: Scheduled | I33: Medium | J33: 46273 | K33: 46274 | L33: 0 | M33: TSK-016 | N33: 0 | P33: =IF(OR($A33="",$K33=""),"", $K33-AsOfDate) | Q33: =IF($A33="","",IF($H33="Completed","Done",IF($K33<AsOfDate,"Overdue",IF($K33<=AsOfDate+7,"Due Soon","On Track"))))
A34: TSK-030 | B34: PRJ-001 | D34: Update insurance inventory | E34: Photograph new fixtures. | F34: Alex Rivera | G34: Homeowner | H34: To Do | I34: Medium | J34: 46338 | K34: 46340 | L34: 0 | M34: TSK-025 | N34: 0 | P34: =IF(OR($A34="",$K34=""),"", $K34-AsOfDate) | Q34: =IF($A34="","",IF($H34="Completed","Done",IF($K34<AsOfDate,"Overdue",IF($K34<=AsOfDate+7,"Due Soon","On Track"))))

Sheet Timeline
A1: TIMELINE
A2: Phase schedule · Gantt to the right · each block is one week from 1 Mar 2026
K3: WEEKLY GANTT · filled cell = phase is active that week · gold column = this week
A4: Phase ID | B4: Project ID | C4: Phase | D4: Start | E4: End | F4: Duration (days) | G4: Status | H4: Depends On | I4: % Elapsed | K4: 46082 | L4: 46089 | M4: 46096 | N4: 46103 | O4: 46110 | P4: 46117 | Q4: 46124 | R4: 46131 | S4: 46138 | T4: 46145 | U4: 46152 | V4: 46159 | W4: 46166 | X4: 46173 | Y4: 46180 | Z4: 46187 | AA4: 46194 | AB4: 46201 | AC4: 46208 | AD4: 46215 | AE4: 46222 | AF4: 46229 | AG4: 46236 | AH4: 46243 | AI4: 46250 | AJ4: 46257 | AK4: 46264 | AL4: 46271 | AM4: 46278 | AN4: 46285 | AO4: 46292 | AP4: 46299 | AQ4: 46306 | AR4: 46313 | AS4: 46320 | AT4: 46327 | AU4: 46334 | AV4: 46341 | AW4: 46348 | AX4: 46355
A5: PH-01 | B5: PRJ-001 | C5: Planning | D5: 46082 | E5: 46112 | F5: =IF($A5="","",$E5-$D5+1) | G5: Completed | I5: =IF($A5="","",MAX(0,MIN(1,(AsOfDate-$D5+1)/MAX(1,$E5-$D5+1)))) | K5: =IF(OR($D5="",$E5=""),"",IF(AND(K$4<=$E5,K$4+6>=$D5),IF($G5="Completed","D",IF($G5="In Progress","N","P")),"")) | L5: =IF(OR($D5="",$E5=""),"",IF(AND(L$4<=$E5,L$4+6>=$D5),IF($G5="Completed","D",IF($G5="In Progress","N","P")),"")) | M5: =IF(OR($D5="",$E5=""),"",IF(AND(M$4<=$E5,M$4+6>=$D5),IF($G5="Completed","D",IF($G5="In Progress","N","P")),"")) | N5: =IF(OR($D5="",$E5=""),"",IF(AND(N$4<=$E5,N$4+6>=$D5),IF($G5="Completed","D",IF($G5="In Progress","N","P")),"")) | O5: =IF(OR($D5="",$E5=""),"",IF(AND(O$4<=$E5,O$4+6>=$D5),IF($G5="Completed","D",IF($G5="In Progress","N","P")),"")) | P5: =IF(OR($D5="",$E5=""),"",IF(AND(P$4<=$E5,P$4+6>=$D5),IF($G5="Completed","D",IF($G5="In Progress","N","P")),"")) | Q5: =IF(OR($D5="",$E5=""),"",IF(AND(Q$4<=$E5,Q$4+6>=$D5),IF($G5="Completed","D",IF($G5="In Progress","N","P")),"")) | R5: =IF(OR($D5="",$E5=""),"",IF(AND(R$4<=$E5,R$4+6>=$D5),IF($G5="Completed","D",IF($G5="In Progress","N","P")),"")) | ... AX5: =IF(OR($D5="",$E5=""),"",IF(AND(AX$4<=$E5,AX$4+6>=$D5),IF($G5="Completed","D",IF($G5="In Progress","N","P")),""))
A6: PH-02 | B6: PRJ-001 | C6: Design | D6: 46096 | E6: 46157 | F6: =IF($A6="","",$E6-$D6+1) | G6: Completed | H6: PH-01 | I6: =IF($A6="","",MAX(0,MIN(1,(AsOfDate-$D6+1)/MAX(1,$E6-$D6+1)))) | K6: =IF(OR($D6="",$E6=""),"",IF(AND(K$4<=$E6,K$4+6>=$D6),IF($G6="Completed","D",IF($G6="In Progress","N","P")),"")) | L6: =IF(OR($D6="",$E6=""),"",IF(AND(L$4<=$E6,L$4+6>=$D6),IF($G6="Completed","D",IF($G6="In Progress","N","P")),"")) | M6: =IF(OR($D6="",$E6=""),"",IF(AND(M$4<=$E6,M$4+6>=$D6),IF($G6="Completed","D",IF($G6="In Progress","N","P")),"")) | N6: =IF(OR($D6="",$E6=""),"",IF(AND(N$4<=$E6,N$4+6>=$D6),IF($G6="Completed","D",IF($G6="In Progress","N","P")),"")) | O6: =IF(OR($D6="",$E6=""),"",IF(AND(O$4<=$E6,O$4+6>=$D6),IF($G6="Completed","D",IF($G6="In Progress","N","P")),"")) | P6: =IF(OR($D6="",$E6=""),"",IF(AND(P$4<=$E6,P$4+6>=$D6),IF($G6="Completed","D",IF($G6="In Progress","N","P")),"")) | Q6: =IF(OR($D6="",$E6=""),"",IF(AND(Q$4<=$E6,Q$4+6>=$D6),IF($G6="Completed","D",IF($G6="In Progress","N","P")),"")) | R6: =IF(OR($D6="",$E6=""),"",IF(AND(R$4<=$E6,R$4+6>=$D6),IF($G6="Completed","D",IF($G6="In Progress","N","P")),"")) | ... AX6: =IF(OR($D6="",$E6=""),"",IF(AND(AX$4<=$E6,AX$4+6>=$D6),IF($G6="Completed","D",IF($G6="In Progress","N","P")),""))
A7: PH-03 | B7: PRJ-001 | C7: Permits | D7: 46113 | E7: 46162 | F7: =IF($A7="","",$E7-$D7+1) | G7: Completed | H7: PH-01 | I7: =IF($A7="","",MAX(0,MIN(1,(AsOfDate-$D7+1)/MAX(1,$E7-$D7+1)))) | K7: =IF(OR($D7="",$E7=""),"",IF(AND(K$4<=$E7,K$4+6>=$D7),IF($G7="Completed","D",IF($G7="In Progress","N","P")),"")) | L7: =IF(OR($D7="",$E7=""),"",IF(AND(L$4<=$E7,L$4+6>=$D7),IF($G7="Completed","D",IF($G7="In Progress","N","P")),"")) | M7: =IF(OR($D7="",$E7=""),"",IF(AND(M$4<=$E7,M$4+6>=$D7),IF($G7="Completed","D",IF($G7="In Progress","N","P")),"")) | N7: =IF(OR($D7="",$E7=""),"",IF(AND(N$4<=$E7,N$4+6>=$D7),IF($G7="Completed","D",IF($G7="In Progress","N","P")),"")) | O7: =IF(OR($D7="",$E7=""),"",IF(AND(O$4<=$E7,O$4+6>=$D7),IF($G7="Completed","D",IF($G7="In Progress","N","P")),"")) | P7: =IF(OR($D7="",$E7=""),"",IF(AND(P$4<=$E7,P$4+6>=$D7),IF($G7="Completed","D",IF($G7="In Progress","N","P")),"")) | Q7: =IF(OR($D7="",$E7=""),"",IF(AND(Q$4<=$E7,Q$4+6>=$D7),IF($G7="Completed","D",IF($G7="In Progress","N","P")),"")) | R7: =IF(OR($D7="",$E7=""),"",IF(AND(R$4<=$E7,R$4+6>=$D7),IF($G7="Completed","D",IF($G7="In Progress","N","P")),"")) | ... AX7: =IF(OR($D7="",$E7=""),"",IF(AND(AX$4<=$E7,AX$4+6>=$D7),IF($G7="Completed","D",IF($G7="In Progress","N","P")),""))
A8: PH-04 | B8: PRJ-001 | C8: Demolition | D8: 46163 | E8: 46178 | F8: =IF($A8="","",$E8-$D8+1) | G8: Completed | H8: PH-03 | I8: =IF($A8="","",MAX(0,MIN(1,(AsOfDate-$D8+1)/MAX(1,$E8-$D8+1)))) | K8: =IF(OR($D8="",$E8=""),"",IF(AND(K$4<=$E8,K$4+6>=$D8),IF($G8="Completed","D",IF($G8="In Progress","N","P")),"")) | L8: =IF(OR($D8="",$E8=""),"",IF(AND(L$4<=$E8,L$4+6>=$D8),IF($G8="Completed","D",IF($G8="In Progress","N","P")),"")) | M8: =IF(OR($D8="",$E8=""),"",IF(AND(M$4<=$E8,M$4+6>=$D8),IF($G8="Completed","D",IF($G8="In Progress","N","P")),"")) | N8: =IF(OR($D8="",$E8=""),"",IF(AND(N$4<=$E8,N$4+6>=$D8),IF($G8="Completed","D",IF($G8="In Progress","N","P")),"")) | O8: =IF(OR($D8="",$E8=""),"",IF(AND(O$4<=$E8,O$4+6>=$D8),IF($G8="Completed","D",IF($G8="In Progress","N","P")),"")) | P8: =IF(OR($D8="",$E8=""),"",IF(AND(P$4<=$E8,P$4+6>=$D8),IF($G8="Completed","D",IF($G8="In Progress","N","P")),"")) | Q8: =IF(OR($D8="",$E8=""),"",IF(AND(Q$4<=$E8,Q$4+6>=$D8),IF($G8="Completed","D",IF($G8="In Progress","N","P")),"")) | R8: =IF(OR($D8="",$E8=""),"",IF(AND(R$4<=$E8,R$4+6>=$D8),IF($G8="Completed","D",IF($G8="In Progress","N","P")),"")) | ... AX8: =IF(OR($D8="",$E8=""),"",IF(AND(AX$4<=$E8,AX$4+6>=$D8),IF($G8="Completed","D",IF($G8="In Progress","N","P")),""))
A9: PH-05 | B9: PRJ-001 | C9: Electrical | D9: 46174 | E9: 46213 | F9: =IF($A9="","",$E9-$D9+1) | G9: Completed | H9: PH-04 | I9: =IF($A9="","",MAX(0,MIN(1,(AsOfDate-$D9+1)/MAX(1,$E9-$D9+1)))) | K9: =IF(OR($D9="",$E9=""),"",IF(AND(K$4<=$E9,K$4+6>=$D9),IF($G9="Completed","D",IF($G9="In Progress","N","P")),"")) | L9: =IF(OR($D9="",$E9=""),"",IF(AND(L$4<=$E9,L$4+6>=$D9),IF($G9="Completed","D",IF($G9="In Progress","N","P")),"")) | M9: =IF(OR($D9="",$E9=""),"",IF(AND(M$4<=$E9,M$4+6>=$D9),IF($G9="Completed","D",IF($G9="In Progress","N","P")),"")) | N9: =IF(OR($D9="",$E9=""),"",IF(AND(N$4<=$E9,N$4+6>=$D9),IF($G9="Completed","D",IF($G9="In Progress","N","P")),"")) | O9: =IF(OR($D9="",$E9=""),"",IF(AND(O$4<=$E9,O$4+6>=$D9),IF($G9="Completed","D",IF($G9="In Progress","N","P")),"")) | P9: =IF(OR($D9="",$E9=""),"",IF(AND(P$4<=$E9,P$4+6>=$D9),IF($G9="Completed","D",IF($G9="In Progress","N","P")),"")) | Q9: =IF(OR($D9="",$E9=""),"",IF(AND(Q$4<=$E9,Q$4+6>=$D9),IF($G9="Completed","D",IF($G9="In Progress","N","P")),"")) | R9: =IF(OR($D9="",$E9=""),"",IF(AND(R$4<=$E9,R$4+6>=$D9),IF($G9="Completed","D",IF($G9="In Progress","N","P")),"")) | ... AX9: =IF(OR($D9="",$E9=""),"",IF(AND(AX$4<=$E9,AX$4+6>=$D9),IF($G9="Completed","D",IF($G9="In Progress","N","P")),""))
A10: PH-06 | B10: PRJ-001 | C10: Plumbing | D10: 46181 | E10: 46223 | F10: =IF($A10="","",$E10-$D10+1) | G10: Completed | H10: PH-04 | I10: =IF($A10="","",MAX(0,MIN(1,(AsOfDate-$D10+1)/MAX(1,$E10-$D10+1)))) | K10: =IF(OR($D10="",$E10=""),"",IF(AND(K$4<=$E10,K$4+6>=$D10),IF($G10="Completed","D",IF($G10="In Progress","N","P")),"")) | L10: =IF(OR($D10="",$E10=""),"",IF(AND(L$4<=$E10,L$4+6>=$D10),IF($G10="Completed","D",IF($G10="In Progress","N","P")),"")) | M10: =IF(OR($D10="",$E10=""),"",IF(AND(M$4<=$E10,M$4+6>=$D10),IF($G10="Completed","D",IF($G10="In Progress","N","P")),"")) | N10: =IF(OR($D10="",$E10=""),"",IF(AND(N$4<=$E10,N$4+6>=$D10),IF($G10="Completed","D",IF($G10="In Progress","N","P")),"")) | O10: =IF(OR($D10="",$E10=""),"",IF(AND(O$4<=$E10,O$4+6>=$D10),IF($G10="Completed","D",IF($G10="In Progress","N","P")),"")) | P10: =IF(OR($D10="",$E10=""),"",IF(AND(P$4<=$E10,P$4+6>=$D10),IF($G10="Completed","D",IF($G10="In Progress","N","P")),"")) | Q10: =IF(OR($D10="",$E10=""),"",IF(AND(Q$4<=$E10,Q$4+6>=$D10),IF($G10="Completed","D",IF($G10="In Progress","N","P")),"")) | R10: =IF(OR($D10="",$E10=""),"",IF(AND(R$4<=$E10,R$4+6>=$D10),IF($G10="Completed","D",IF($G10="In Progress","N","P")),"")) | ... AX10: =IF(OR($D10="",$E10=""),"",IF(AND(AX$4<=$E10,AX$4+6>=$D10),IF($G10="Completed","D",IF($G10="In Progress","N","P")),""))
A11: PH-07 | B11: PRJ-001 | C11: Walls / plaster | D11: 46218 | E11: 46244 | F11: =IF($A11="","",$E11-$D11+1) | G11: Completed | H11: PH-05 | I11: =IF($A11="","",MAX(0,MIN(1,(AsOfDate-$D11+1)/MAX(1,$E11-$D11+1)))) | K11: =IF(OR($D11="",$E11=""),"",IF(AND(K$4<=$E11,K$4+6>=$D11),IF($G11="Completed","D",IF($G11="In Progress","N","P")),"")) | L11: =IF(OR($D11="",$E11=""),"",IF(AND(L$4<=$E11,L$4+6>=$D11),IF($G11="Completed","D",IF($G11="In Progress","N","P")),"")) | M11: =IF(OR($D11="",$E11=""),"",IF(AND(M$4<=$E11,M$4+6>=$D11),IF($G11="Completed","D",IF($G11="In Progress","N","P")),"")) | N11: =IF(OR($D11="",$E11=""),"",IF(AND(N$4<=$E11,N$4+6>=$D11),IF($G11="Completed","D",IF($G11="In Progress","N","P")),"")) | O11: =IF(OR($D11="",$E11=""),"",IF(AND(O$4<=$E11,O$4+6>=$D11),IF($G11="Completed","D",IF($G11="In Progress","N","P")),"")) | P11: =IF(OR($D11="",$E11=""),"",IF(AND(P$4<=$E11,P$4+6>=$D11),IF($G11="Completed","D",IF($G11="In Progress","N","P")),"")) | Q11: =IF(OR($D11="",$E11=""),"",IF(AND(Q$4<=$E11,Q$4+6>=$D11),IF($G11="Completed","D",IF($G11="In Progress","N","P")),"")) | R11: =IF(OR($D11="",$E11=""),"",IF(AND(R$4<=$E11,R$4+6>=$D11),IF($G11="Completed","D",IF($G11="In Progress","N","P")),"")) | ... AX11: =IF(OR($D11="",$E11=""),"",IF(AND(AX$4<=$E11,AX$4+6>=$D11),IF($G11="Completed","D",IF($G11="In Progress","N","P")),""))
A12: PH-08 | B12: PRJ-001 | C12: Flooring | D12: 46239 | E12: 46262 | F12: =IF($A12="","",$E12-$D12+1) | G12: In Progress | H12: PH-07 | I12: =IF($A12="","",MAX(0,MIN(1,(AsOfDate-$D12+1)/MAX(1,$E12-$D12+1)))) | K12: =IF(OR($D12="",$E12=""),"",IF(AND(K$4<=$E12,K$4+6>=$D12),IF($G12="Completed","D",IF($G12="In Progress","N","P")),"")) | L12: =IF(OR($D12="",$E12=""),"",IF(AND(L$4<=$E12,L$4+6>=$D12),IF($G12="Completed","D",IF($G12="In Progress","N","P")),"")) | M12: =IF(OR($D12="",$E12=""),"",IF(AND(M$4<=$E12,M$4+6>=$D12),IF($G12="Completed","D",IF($G12="In Progress","N","P")),"")) | N12: =IF(OR($D12="",$E12=""),"",IF(AND(N$4<=$E12,N$4+6>=$D12),IF($G12="Completed","D",IF($G12="In Progress","N","P")),"")) | O12: =IF(OR($D12="",$E12=""),"",IF(AND(O$4<=$E12,O$4+6>=$D12),IF($G12="Completed","D",IF($G12="In Progress","N","P")),"")) | P12: =IF(OR($D12="",$E12=""),"",IF(AND(P$4<=$E12,P$4+6>=$D12),IF($G12="Completed","D",IF($G12="In Progress","N","P")),"")) | Q12: =IF(OR($D12="",$E12=""),"",IF(AND(Q$4<=$E12,Q$4+6>=$D12),IF($G12="Completed","D",IF($G12="In Progress","N","P")),"")) | R12: =IF(OR($D12="",$E12=""),"",IF(AND(R$4<=$E12,R$4+6>=$D12),IF($G12="Completed","D",IF($G12="In Progress","N","P")),"")) | ... AX12: =IF(OR($D12="",$E12=""),"",IF(AND(AX$4<=$E12,AX$4+6>=$D12),IF($G12="Completed","D",IF($G12="In Progress","N","P")),""))
A13: PH-09 | B13: PRJ-001 | C13: Cabinetry | D13: 46254 | E13: 46280 | F13: =IF($A13="","",$E13-$D13+1) | G13: In Progress | H13: PH-08 | I13: =IF($A13="","",MAX(0,MIN(1,(AsOfDate-$D13+1)/MAX(1,$E13-$D13+1)))) | K13: =IF(OR($D13="",$E13=""),"",IF(AND(K$4<=$E13,K$4+6>=$D13),IF($G13="Completed","D",IF($G13="In Progress","N","P")),"")) | L13: =IF(OR($D13="",$E13=""),"",IF(AND(L$4<=$E13,L$4+6>=$D13),IF($G13="Completed","D",IF($G13="In Progress","N","P")),"")) | M13: =IF(OR($D13="",$E13=""),"",IF(AND(M$4<=$E13,M$4+6>=$D13),IF($G13="Completed","D",IF($G13="In Progress","N","P")),"")) | N13: =IF(OR($D13="",$E13=""),"",IF(AND(N$4<=$E13,N$4+6>=$D13),IF($G13="Completed","D",IF($G13="In Progress","N","P")),"")) | O13: =IF(OR($D13="",$E13=""),"",IF(AND(O$4<=$E13,O$4+6>=$D13),IF($G13="Completed","D",IF($G13="In Progress","N","P")),"")) | P13: =IF(OR($D13="",$E13=""),"",IF(AND(P$4<=$E13,P$4+6>=$D13),IF($G13="Completed","D",IF($G13="In Progress","N","P")),"")) | Q13: =IF(OR($D13="",$E13=""),"",IF(AND(Q$4<=$E13,Q$4+6>=$D13),IF($G13="Completed","D",IF($G13="In Progress","N","P")),"")) | R13: =IF(OR($D13="",$E13=""),"",IF(AND(R$4<=$E13,R$4+6>=$D13),IF($G13="Completed","D",IF($G13="In Progress","N","P")),"")) | ... AX13: =IF(OR($D13="",$E13=""),"",IF(AND(AX$4<=$E13,AX$4+6>=$D13),IF($G13="Completed","D",IF($G13="In Progress","N","P")),""))
A14: PH-10 | B14: PRJ-001 | C14: Counters / appliances | D14: 46275 | E14: 46283 | F14: =IF($A14="","",$E14-$D14+1) | G14: Scheduled | H14: PH-09 | I14: =IF($A14="","",MAX(0,MIN(1,(AsOfDate-$D14+1)/MAX(1,$E14-$D14+1)))) | K14: =IF(OR($D14="",$E14=""),"",IF(AND(K$4<=$E14,K$4+6>=$D14),IF($G14="Completed","D",IF($G14="In Progress","N","P")),"")) | L14: =IF(OR($D14="",$E14=""),"",IF(AND(L$4<=$E14,L$4+6>=$D14),IF($G14="Completed","D",IF($G14="In Progress","N","P")),"")) | M14: =IF(OR($D14="",$E14=""),"",IF(AND(M$4<=$E14,M$4+6>=$D14),IF($G14="Completed","D",IF($G14="In Progress","N","P")),"")) | N14: =IF(OR($D14="",$E14=""),"",IF(AND(N$4<=$E14,N$4+6>=$D14),IF($G14="Completed","D",IF($G14="In Progress","N","P")),"")) | O14: =IF(OR($D14="",$E14=""),"",IF(AND(O$4<=$E14,O$4+6>=$D14),IF($G14="Completed","D",IF($G14="In Progress","N","P")),"")) | P14: =IF(OR($D14="",$E14=""),"",IF(AND(P$4<=$E14,P$4+6>=$D14),IF($G14="Completed","D",IF($G14="In Progress","N","P")),"")) | Q14: =IF(OR($D14="",$E14=""),"",IF(AND(Q$4<=$E14,Q$4+6>=$D14),IF($G14="Completed","D",IF($G14="In Progress","N","P")),"")) | R14: =IF(OR($D14="",$E14=""),"",IF(AND(R$4<=$E14,R$4+6>=$D14),IF($G14="Completed","D",IF($G14="In Progress","N","P")),"")) | ... AX14: =IF(OR($D14="",$E14=""),"",IF(AND(AX$4<=$E14,AX$4+6>=$D14),IF($G14="Completed","D",IF($G14="In Progress","N","P")),""))
A15: PH-11 | B15: PRJ-001 | C15: Painting | D15: 46275 | E15: 46293 | F15: =IF($A15="","",$E15-$D15+1) | G15: Scheduled | H15: PH-07 | I15: =IF($A15="","",MAX(0,MIN(1,(AsOfDate-$D15+1)/MAX(1,$E15-$D15+1)))) | K15: =IF(OR($D15="",$E15=""),"",IF(AND(K$4<=$E15,K$4+6>=$D15),IF($G15="Completed","D",IF($G15="In Progress","N","P")),"")) | L15: =IF(OR($D15="",$E15=""),"",IF(AND(L$4<=$E15,L$4+6>=$D15),IF($G15="Completed","D",IF($G15="In Progress","N","P")),"")) | M15: =IF(OR($D15="",$E15=""),"",IF(AND(M$4<=$E15,M$4+6>=$D15),IF($G15="Completed","D",IF($G15="In Progress","N","P")),"")) | N15: =IF(OR($D15="",$E15=""),"",IF(AND(N$4<=$E15,N$4+6>=$D15),IF($G15="Completed","D",IF($G15="In Progress","N","P")),"")) | O15: =IF(OR($D15="",$E15=""),"",IF(AND(O$4<=$E15,O$4+6>=$D15),IF($G15="Completed","D",IF($G15="In Progress","N","P")),"")) | P15: =IF(OR($D15="",$E15=""),"",IF(AND(P$4<=$E15,P$4+6>=$D15),IF($G15="Completed","D",IF($G15="In Progress","N","P")),"")) | Q15: =IF(OR($D15="",$E15=""),"",IF(AND(Q$4<=$E15,Q$4+6>=$D15),IF($G15="Completed","D",IF($G15="In Progress","N","P")),"")) | R15: =IF(OR($D15="",$E15=""),"",IF(AND(R$4<=$E15,R$4+6>=$D15),IF($G15="Completed","D",IF($G15="In Progress","N","P")),"")) | ... AX15: =IF(OR($D15="",$E15=""),"",IF(AND(AX$4<=$E15,AX$4+6>=$D15),IF($G15="Completed","D",IF($G15="In Progress","N","P")),""))
A16: PH-12 | B16: PRJ-001 | C16: Furniture | D16: 46290 | E16: 46315 | F16: =IF($A16="","",$E16-$D16+1) | G16: To Do | H16: PH-11 | I16: =IF($A16="","",MAX(0,MIN(1,(AsOfDate-$D16+1)/MAX(1,$E16-$D16+1)))) | K16: =IF(OR($D16="",$E16=""),"",IF(AND(K$4<=$E16,K$4+6>=$D16),IF($G16="Completed","D",IF($G16="In Progress","N","P")),"")) | L16: =IF(OR($D16="",$E16=""),"",IF(AND(L$4<=$E16,L$4+6>=$D16),IF($G16="Completed","D",IF($G16="In Progress","N","P")),"")) | M16: =IF(OR($D16="",$E16=""),"",IF(AND(M$4<=$E16,M$4+6>=$D16),IF($G16="Completed","D",IF($G16="In Progress","N","P")),"")) | N16: =IF(OR($D16="",$E16=""),"",IF(AND(N$4<=$E16,N$4+6>=$D16),IF($G16="Completed","D",IF($G16="In Progress","N","P")),"")) | O16: =IF(OR($D16="",$E16=""),"",IF(AND(O$4<=$E16,O$4+6>=$D16),IF($G16="Completed","D",IF($G16="In Progress","N","P")),"")) | P16: =IF(OR($D16="",$E16=""),"",IF(AND(P$4<=$E16,P$4+6>=$D16),IF($G16="Completed","D",IF($G16="In Progress","N","P")),"")) | Q16: =IF(OR($D16="",$E16=""),"",IF(AND(Q$4<=$E16,Q$4+6>=$D16),IF($G16="Completed","D",IF($G16="In Progress","N","P")),"")) | R16: =IF(OR($D16="",$E16=""),"",IF(AND(R$4<=$E16,R$4+6>=$D16),IF($G16="Completed","D",IF($G16="In Progress","N","P")),"")) | ... AX16: =IF(OR($D16="",$E16=""),"",IF(AND(AX$4<=$E16,AX$4+6>=$D16),IF($G16="Completed","D",IF($G16="In Progress","N","P")),""))
A17: PH-13 | B17: PRJ-001 | C17: Exterior / garden | D17: 46301 | E17: 46319 | F17: =IF($A17="","",$E17-$D17+1) | G17: To Do | H17: PH-11 | I17: =IF($A17="","",MAX(0,MIN(1,(AsOfDate-$D17+1)/MAX(1,$E17-$D17+1)))) | K17: =IF(OR($D17="",$E17=""),"",IF(AND(K$4<=$E17,K$4+6>=$D17),IF($G17="Completed","D",IF($G17="In Progress","N","P")),"")) | L17: =IF(OR($D17="",$E17=""),"",IF(AND(L$4<=$E17,L$4+6>=$D17),IF($G17="Completed","D",IF($G17="In Progress","N","P")),"")) | M17: =IF(OR($D17="",$E17=""),"",IF(AND(M$4<=$E17,M$4+6>=$D17),IF($G17="Completed","D",IF($G17="In Progress","N","P")),"")) | N17: =IF(OR($D17="",$E17=""),"",IF(AND(N$4<=$E17,N$4+6>=$D17),IF($G17="Completed","D",IF($G17="In Progress","N","P")),"")) | O17: =IF(OR($D17="",$E17=""),"",IF(AND(O$4<=$E17,O$4+6>=$D17),IF($G17="Completed","D",IF($G17="In Progress","N","P")),"")) | P17: =IF(OR($D17="",$E17=""),"",IF(AND(P$4<=$E17,P$4+6>=$D17),IF($G17="Completed","D",IF($G17="In Progress","N","P")),"")) | Q17: =IF(OR($D17="",$E17=""),"",IF(AND(Q$4<=$E17,Q$4+6>=$D17),IF($G17="Completed","D",IF($G17="In Progress","N","P")),"")) | R17: =IF(OR($D17="",$E17=""),"",IF(AND(R$4<=$E17,R$4+6>=$D17),IF($G17="Completed","D",IF($G17="In Progress","N","P")),"")) | ... AX17: =IF(OR($D17="",$E17=""),"",IF(AND(AX$4<=$E17,AX$4+6>=$D17),IF($G17="Completed","D",IF($G17="In Progress","N","P")),""))
... A19: PH-15 | B19: PRJ-001 | C19: Handover | D19: 46336 | E19: 46341 | F19: =IF($A19="","",$E19-$D19+1) | G19: To Do | H19: PH-14 | I19: =IF($A19="","",MAX(0,MIN(1,(AsOfDate-$D19+1)/MAX(1,$E19-$D19+1)))) | K19: =IF(OR($D19="",$E19=""),"",IF(AND(K$4<=$E19,K$4+6>=$D19),IF($G19="Completed","D",IF($G19="In Progress","N","P")),"")) | L19: =IF(OR($D19="",$E19=""),"",IF(AND(L$4<=$E19,L$4+6>=$D19),IF($G19="Completed","D",IF($G19="In Progress","N","P")),"")) | M19: =IF(OR($D19="",$E19=""),"",IF(AND(M$4<=$E19,M$4+6>=$D19),IF($G19="Completed","D",IF($G19="In Progress","N","P")),"")) | N19: =IF(OR($D19="",$E19=""),"",IF(AND(N$4<=$E19,N$4+6>=$D19),IF($G19="Completed","D",IF($G19="In Progress","N","P")),"")) | O19: =IF(OR($D19="",$E19=""),"",IF(AND(O$4<=$E19,O$4+6>=$D19),IF($G19="Completed","D",IF($G19="In Progress","N","P")),"")) | P19: =IF(OR($D19="",$E19=""),"",IF(AND(P$4<=$E19,P$4+6>=$D19),IF($G19="Completed","D",IF($G19="In Progress","N","P")),"")) | Q19: =IF(OR($D19="",$E19=""),"",IF(AND(Q$4<=$E19,Q$4+6>=$D19),IF($G19="Completed","D",IF($G19="In Progress","N","P")),"")) | R19: =IF(OR($D19="",$E19=""),"",IF(AND(R$4<=$E19,R$4+6>=$D19),IF($G19="Completed","D",IF($G19="In Progress","N","P")),"")) | ... AX19: =IF(OR($D19="",$E19=""),"",IF(AND(AX$4<=$E19,AX$4+6>=$D19),IF($G19="Completed","D",IF($G19="In Progress","N","P")),""))
A20: PH-16 | B20: PRJ-002 | C20: Cabin design | D20: 46235 | E20: 46295 | F20: =IF($A20="","",$E20-$D20+1) | G20: In Progress | I20: =IF($A20="","",MAX(0,MIN(1,(AsOfDate-$D20+1)/MAX(1,$E20-$D20+1)))) | K20: =IF(OR($D20="",$E20=""),"",IF(AND(K$4<=$E20,K$4+6>=$D20),IF($G20="Completed","D",IF($G20="In Progress","N","P")),"")) | L20: =IF(OR($D20="",$E20=""),"",IF(AND(L$4<=$E20,L$4+6>=$D20),IF($G20="Completed","D",IF($G20="In Progress","N","P")),"")) | M20: =IF(OR($D20="",$E20=""),"",IF(AND(M$4<=$E20,M$4+6>=$D20),IF($G20="Completed","D",IF($G20="In Progress","N","P")),"")) | N20: =IF(OR($D20="",$E20=""),"",IF(AND(N$4<=$E20,N$4+6>=$D20),IF($G20="Completed","D",IF($G20="In Progress","N","P")),"")) | O20: =IF(OR($D20="",$E20=""),"",IF(AND(O$4<=$E20,O$4+6>=$D20),IF($G20="Completed","D",IF($G20="In Progress","N","P")),"")) | P20: =IF(OR($D20="",$E20=""),"",IF(AND(P$4<=$E20,P$4+6>=$D20),IF($G20="Completed","D",IF($G20="In Progress","N","P")),"")) | Q20: =IF(OR($D20="",$E20=""),"",IF(AND(Q$4<=$E20,Q$4+6>=$D20),IF($G20="Completed","D",IF($G20="In Progress","N","P")),"")) | R20: =IF(OR($D20="",$E20=""),"",IF(AND(R$4<=$E20,R$4+6>=$D20),IF($G20="Completed","D",IF($G20="In Progress","N","P")),"")) | ... AX20: =IF(OR($D20="",$E20=""),"",IF(AND(AX$4<=$E20,AX$4+6>=$D20),IF($G20="Completed","D",IF($G20="In Progress","N","P")),""))
A21: PH-17 | B21: PRJ-002 | C21: Cabin construction | D21: 46310 | E21: 46366 | F21: =IF($A21="","",$E21-$D21+1) | G21: To Do | H21: PH-16 | I21: =IF($A21="","",MAX(0,MIN(1,(AsOfDate-$D21+1)/MAX(1,$E21-$D21+1)))) | K21: =IF(OR($D21="",$E21=""),"",IF(AND(K$4<=$E21,K$4+6>=$D21),IF($G21="Completed","D",IF($G21="In Progress","N","P")),"")) | L21: =IF(OR($D21="",$E21=""),"",IF(AND(L$4<=$E21,L$4+6>=$D21),IF($G21="Completed","D",IF($G21="In Progress","N","P")),"")) | M21: =IF(OR($D21="",$E21=""),"",IF(AND(M$4<=$E21,M$4+6>=$D21),IF($G21="Completed","D",IF($G21="In Progress","N","P")),"")) | N21: =IF(OR($D21="",$E21=""),"",IF(AND(N$4<=$E21,N$4+6>=$D21),IF($G21="Completed","D",IF($G21="In Progress","N","P")),"")) | O21: =IF(OR($D21="",$E21=""),"",IF(AND(O$4<=$E21,O$4+6>=$D21),IF($G21="Completed","D",IF($G21="In Progress","N","P")),"")) | P21: =IF(OR($D21="",$E21=""),"",IF(AND(P$4<=$E21,P$4+6>=$D21),IF($G21="Completed","D",IF($G21="In Progress","N","P")),"")) | Q21: =IF(OR($D21="",$E21=""),"",IF(AND(Q$4<=$E21,Q$4+6>=$D21),IF($G21="Completed","D",IF($G21="In Progress","N","P")),"")) | R21: =IF(OR($D21="",$E21=""),"",IF(AND(R$4<=$E21,R$4+6>=$D21),IF($G21="Completed","D",IF($G21="In Progress","N","P")),"")) | ... AX21: =IF(OR($D21="",$E21=""),"",IF(AND(AX$4<=$E21,AX$4+6>=$D21),IF($G21="Completed","D",IF($G21="In Progress","N","P")),""))

Sheet Materials
A1: MATERIALS
A2: Procurement · Required → Quoted → Approved → Ordered → Shipped → Delivered → Installed
A4: Material ID | B4: Project ID | C4: Room ID | D4: Product | E4: Brand | F4: SKU | G4: Category | H4: Qty Required | I4: Unit | J4: Unit Price | K4: Line Total | L4: Supplier | M4: Qty Ordered | N4: Qty Delivered | O4: Qty Installed | P4: Status | Q4: Warranty (mo) | R4: Receipt | S4: Order Date | T4: Delivery Date | U4: QR / Barcode | V4: Open Qty
A5: MAT-001 | B5: PRJ-001 | C5: RM-01 | D5: Shaker cabinet box set | E5: Cascade | F5: CC-SH-Sage | G5: Cabinetry | H5: 1 | I5: set | J5: 14800 | K5: =IF($A5="","",$H5*$J5) | L5: Cascade Cabinets | M5: 1 | N5: 1 | O5: 0.6 | P5: Delivered | Q5: 60 | R5: INV-CC-501 | S5: 46174 | T5: 46254 | U5: QR-CC-001 | V5: =IF($A5="","",$H5-$N5)
A6: MAT-002 | B6: PRJ-001 | C6: RM-01 | D6: Aged brass bar pulls | E6: Rejuvenation | F6: RJ-BP-128 | G6: Hardware | H6: 28 | I6: ea | J6: 18 | K6: =IF($A6="","",$H6*$J6) | L6: Rejuvenation | M6: 28 | N6: 0 | O6: 0 | P6: Shipped | Q6: 12 | S6: 46244 | U6: QR-RJ-128 | V6: =IF($A6="","",$H6-$N6)
A7: MAT-003 | B7: PRJ-001 | C7: RM-01 | D7: White oak 7in engineered | E7: Timberline | F7: TL-WO-7 | G7: Flooring | H7: 780 | I7: sf | J7: 8.2 | K7: =IF($A7="","",$H7*$J7) | L7: Timberline Floors | M7: 780 | N7: 780 | O7: 620 | P7: Installed | Q7: 25 | R7: PO-140 | S7: 46204 | T7: 46231 | U7: QR-TL-WO7 | V7: =IF($A7="","",$H7-$N7)
A8: MAT-004 | B8: PRJ-001 | C8: RM-01 | D8: Perimeter quartz — Frost | E8: Caesarstone | F8: CS-5110 | G8: Counters | H8: 42 | I8: sf | J8: 59 | K8: =IF($A8="","",$H8*$J8) | L8: Caesarstone | M8: 42 | N8: 42 | O8: 0 | P8: Delivered | Q8: 15 | R8: CS-882 | S8: 46235 | T8: 46250 | U8: QR-CS-5110 | V8: =IF($A8="","",$H8-$N8)
A9: MAT-005 | B9: PRJ-001 | C9: RM-01 | D9: Island porcelain slab | E9: Heritage | F9: HT-8841 | G9: Counters | H9: 28 | I9: sf | J9: 66.4 | K9: =IF($A9="","",$H9*$J9) | L9: Heritage Tile & Stone | M9: 0 | N9: 0 | O9: 0 | P9: Approved | Q9: 25 | U9: QR-HT-8841 | V9: =IF($A9="","",$H9-$N9)
A10: MAT-006 | B10: PRJ-001 | C10: RM-01 | D10: Zellige backsplash — sand | E10: Cle | F10: CLE-Z-14 | G10: Tile | H10: 48 | I10: sf | J10: 28 | K10: =IF($A10="","",$H10*$J10) | L10: Tile & Timber Co. | M10: 0 | N10: 0 | O10: 0 | P10: Quoted | Q10: 0 | U10: QR-CLE-14 | V10: =IF($A10="","",$H10-$N10)
A11: MAT-007 | B11: PRJ-001 | C11: RM-01 | D11: Island pendants x3 | E11: BrightPath | F11: BP-ISL-AB | G11: Lighting | H11: 3 | I11: ea | J11: 296.67 | K11: =IF($A11="","",$H11*$J11) | L11: BrightPath Lighting | M11: 3 | N11: 0 | O11: 0 | P11: Ordered | Q11: 24 | R11: BP-220 | S11: 46252 | U11: QR-BP-ISL | V11: =IF($A11="","",$H11-$N11)
A12: MAT-008 | B12: PRJ-001 | C12: RM-01 | D12: Range 36in dual fuel | E12: Wolf | F12: DF364C | G12: Appliances | H12: 1 | I12: ea | J12: 0 | K12: =IF($A12="","",$H12*$J12) | L12: Sub-Zero / Wolf | M12: 1 | N12: 0 | O12: 0 | P12: Ordered | Q12: 24 | R12: APPL-01 | S12: 46248 | U12: QR-WF-DF | V12: =IF($A12="","",$H12-$N12)
A13: MAT-009 | B13: PRJ-001 | C13: RM-01 | D13: Counter-depth fridge | E13: Sub-Zero | F13: DEC3650 | G13: Appliances | H13: 1 | I13: ea | J13: 0 | K13: =IF($A13="","",$H13*$J13) | L13: Sub-Zero / Wolf | M13: 1 | N13: 0 | O13: 0 | P13: Ordered | Q13: 24 | R13: APPL-01 | S13: 46248 | U13: QR-SZ-3650 | V13: =IF($A13="","",$H13-$N13)
A14: MAT-010 | B14: PRJ-001 | C14: RM-03 | D14: Porcelain floor 12x24 | E14: Heritage | F14: HT-8841F | G14: Tile | H14: 90 | I14: sf | J14: 14.2 | K14: =IF($A14="","",$H14*$J14) | L14: Tile & Timber Co. | M14: 95 | N14: 95 | O14: 90 | P14: Installed | Q14: 25 | R14: PO-114 | S14: 46183 | T14: 46193 | U14: QR-HT-F | V14: =IF($A14="","",$H14-$N14)
A15: MAT-011 | B15: PRJ-001 | C15: RM-03 | D15: Shower wall porcelain | E15: Heritage | F15: HT-8841W | G15: Tile | H15: 110 | I15: sf | J15: 16.8 | K15: =IF($A15="","",$H15*$J15) | L15: Tile & Timber Co. | M15: 115 | N15: 115 | O15: 110 | P15: Installed | Q15: 25 | R15: PO-114 | S15: 46183 | T15: 46193 | U15: QR-HT-W | V15: =IF($A15="","",$H15-$N15)
A16: MAT-012 | B16: PRJ-001 | C16: RM-03 | D16: Thermostatic shower set | E16: Brizo | F16: BZ-T600 | G16: Fixtures | H16: 1 | I16: set | J16: 890 | K16: =IF($A16="","",$H16*$J16) | L16: Ferguson | M16: 1 | N16: 1 | O16: 1 | P16: Installed | Q16: 60 | R16: FERG-9921 | S16: 46188 | T16: 46201 | U16: QR-BZ-T600 | V16: =IF($A16="","",$H16-$N16)
A17: MAT-013 | B17: PRJ-001 | C17: RM-03 | D17: Vanity 48in white oak | E17: Cascade | F17: CC-VAN-48 | G17: Cabinetry | H17: 1 | I17: ea | J17: 1680 | K17: =IF($A17="","",$H17*$J17) | L17: Cascade Cabinets | M17: 1 | N17: 1 | O17: 1 | P17: Installed | Q17: 24 | R17: INV-CC-440 | S17: 46204 | T17: 46223 | U17: QR-CC-VAN | V17: =IF($A17="","",$H17-$N17)
A18: MAT-014 | B18: PRJ-001 | C18: RM-03 | D18: Heated floor kit | E18: WarmFloor | F18: WF-240-40 | G18: Electrical | H18: 1 | I18: kit | J18: 1680 | K18: =IF($A18="","",$H18*$J18) | L18: WarmFloor Co. | M18: 1 | N18: 1 | O18: 1 | P18: Installed | Q18: 36 | R18: WF-441 | S18: 46193 | T18: 46205 | U18: QR-WF-240 | V18: =IF($A18="","",$H18-$N18)
A19: MAT-015 | B19: PRJ-001 | C19: RM-02 | D19: Modular sofa | E19: Article | F19: ART-SVEN | G19: Furniture | H19: 1 | I19: ea | J19: 2400 | K19: =IF($A19="","",$H19*$J19) | L19: Article | M19: 0 | N19: 0 | O19: 0 | P19: Quoted | Q19: 12 | U19: QR-ART-SV | V19: =IF($A19="","",$H19-$N19)
A20: MAT-016 | B20: PRJ-001 | C20: RM-02 | D20: Oak coffee table | E20: Article | F20: ART-OAK-CT | G20: Furniture | H20: 1 | I20: ea | J20: 1000 | K20: =IF($A20="","",$H20*$J20) | L20: Article | M20: 0 | N20: 0 | O20: 0 | P20: Quoted | Q20: 12 | U20: QR-ART-CT | V20: =IF($A20="","",$H20-$N20)
A21: MAT-017 | B21: PRJ-001 | C21: RM-05 | D21: Dining sconces | E21: BrightPath | F21: BP-SCN-02 | G21: Lighting | H21: 2 | I21: ea | J21: 190 | K21: =IF($A21="","",$H21*$J21) | L21: BrightPath Lighting | M21: 2 | N21: 2 | O21: 0 | P21: Delivered | Q21: 24 | R21: BP-204 | S21: 46235 | T21: 46256 | U21: QR-BP-SCN | V21: =IF($A21="","",$H21-$N21)
A22: MAT-018 | B22: PRJ-001 | C22: RM-08 | D22: Hook rail 48in | E22: Rejuvenation | F22: RJ-HR-48 | G22: Hardware | H22: 1 | I22: ea | J22: 186 | K22: =IF($A22="","",$H22*$J22) | L22: Rejuvenation | M22: 1 | N22: 1 | O22: 0 | P22: Delivered | Q22: 12 | R22: REJ-33 | S22: 46246 | T22: 46253 | U22: QR-RJ-HR | V22: =IF($A22="","",$H22-$N22)
A23: MAT-019 | B23: PRJ-001 | C23: RM-04 | D23: Interior paint — Clay | E23: Benjamin Moore | F23: BM-HC-50 | G23: Paint | H23: 4 | I23: gal | J23: 62 | K23: =IF($A23="","",$H23*$J23) | L23: Sherwin-Williams | M23: 0 | N23: 0 | O23: 0 | P23: Required | Q23: 0 | U23: QR-BM-CLAY | V23: =IF($A23="","",$H23-$N23)
A24: MAT-020 | B24: PRJ-001 | C24: RM-06 | D24: Bluestone path pavers | E24: Garden & Gate | F24: GG-BLU-12 | G24: Hardscape | H24: 220 | I24: sf | J24: 9.5 | K24: =IF($A24="","",$H24*$J24) | L24: Garden & Gate | M24: 0 | N24: 0 | O24: 0 | P24: Quoted | Q24: 0 | U24: QR-GG-BLU | V24: =IF($A24="","",$H24-$N24)
A25: MAT-021 | B25: PRJ-001 | C25: RM-01 | D25: Undermount sink | E25: Kohler | F25: K-5285 | G25: Fixtures | H25: 1 | I25: ea | J25: 420 | K25: =IF($A25="","",$H25*$J25) | L25: Ferguson | M25: 1 | N25: 1 | O25: 0 | P25: Delivered | Q25: 36 | R25: FERG-1002 | S25: 46235 | T25: 46246 | U25: QR-K-5285 | V25: =IF($A25="","",$H25-$N25)
A26: MAT-022 | B26: PRJ-001 | C26: RM-01 | D26: Bridge faucet — brass | E26: Brizo | F26: BZ-K610 | G26: Fixtures | H26: 1 | I26: ea | J26: 640 | K26: =IF($A26="","",$H26*$J26) | L26: Ferguson | M26: 1 | N26: 0 | O26: 0 | P26: Shipped | Q26: 60 | R26: FERG-1002 | S26: 46242 | U26: QR-BZ-K610 | V26: =IF($A26="","",$H26-$N26)
A27: MAT-023 | B27: PRJ-001 | C27: RM-02 | D27: Stair nosing — white oak | E27: Timberline | F27: TL-NOS-WO | G27: Flooring | H27: 14 | I27: lf | J27: 22 | K27: =IF($A27="","",$H27*$J27) | L27: Timberline Floors | M27: 14 | N27: 0 | O27: 0 | P27: Backordered | Q27: 25 | S27: 46240 | U27: QR-TL-NOS | V27: =IF($A27="","",$H27-$N27)
A28: MAT-024 | B28: PRJ-002 | C28: RM-09 | D28: Cedar vanity | E28: Cascade | F28: CC-CED-36 | G28: Cabinetry | H28: 1 | I28: ea | J28: 2100 | K28: =IF($A28="","",$H28*$J28) | L28: Cascade Cabinets | M28: 0 | N28: 0 | O28: 0 | P28: Required | Q28: 24 | U28: QR-CC-CED | V28: =IF($A28="","",$H28-$N28)
A29: MAT-025 | B29: PRJ-001 | C29: RM-04 | D29: Wardrobe kit | E29: IKEA / custom face | F29: PAX-WO | G29: Cabinetry | H29: 1 | I29: set | J29: 890 | K29: =IF($A29="","",$H29*$J29) | L29: IKEA | M29: 0 | N29: 0 | O29: 0 | P29: Required | Q29: 12 | U29: QR-PAX | V29: =IF($A29="","",$H29-$N29)

Sheet Shopping List
A1: SHOPPING LIST
A2: Auto-built from Materials still Required / Quoted / Approved · refresh by editing Materials
A4: SKU / QR | B4: Product | C4: Room | D4: Qty | E4: Unit | F4: Est. Unit $ | G4: Est. Total | H4: Supplier | I4: Status | J4: Project
A5: =IFERROR(FILTER(Materials!F5:F200,(Materials!P5:P200="Required")+(Materials!P5:P200="Quoted")+(Materials!P5:P200="Approved")),"") | B5: =IFERROR(FILTER(Materials!D5:D200,(Materials!P5:P200="Required")+(Materials!P5:P200="Quoted")+(Materials!P5:P200="Approved")),"") | C5: =IFERROR(FILTER(Materials!C5:C200,(Materials!P5:P200="Required")+(Materials!P5:P200="Quoted")+(Materials!P5:P200="Approved")),"") | D5: =IFERROR(FILTER(Materials!H5:H200,(Materials!P5:P200="Required")+(Materials!P5:P200="Quoted")+(Materials!P5:P200="Approved")),"") | E5: =IFERROR(FILTER(Materials!I5:I200,(Materials!P5:P200="Required")+(Materials!P5:P200="Quoted")+(Materials!P5:P200="Approved")),"") | F5: =IFERROR(FILTER(Materials!J5:J200,(Materials!P5:P200="Required")+(Materials!P5:P200="Quoted")+(Materials!P5:P200="Approved")),"") | G5: =IFERROR(FILTER(Materials!K5:K200,(Materials!P5:P200="Required")+(Materials!P5:P200="Quoted")+(Materials!P5:P200="Approved")),"") | H5: =IFERROR(FILTER(Materials!L5:L200,(Materials!P5:P200="Required")+(Materials!P5:P200="Quoted")+(Materials!P5:P200="Approved")),"") | I5: =IFERROR(FILTER(Materials!P5:P200,(Materials!P5:P200="Required")+(Materials!P5:P200="Quoted")+(Materials!P5:P200="Approved")),"") | J5: =IFERROR(FILTER(Materials!B5:B200,(Materials!P5:P200="Required")+(Materials!P5:P200="Quoted")+(Materials!P5:P200="Approved")),"")
A32: Excel 365 and Google Sheets will spill the shopping list from row 5. If you are on Excel 2019 or earlier, filter the Materials sheet for Status = Required / Quoted / Approved and copy those rows here.

Sheet Suppliers
A1: SUPPLIERS
A2: Vendor book · lead times drive the prediction engine
A4: Supplier ID | B4: Name | C4: Category | D4: Contact | E4: Phone | F4: Email | G4: Website | H4: Rating | I4: Payment Terms | J4: Lead Time (days) | K4: Notes
A5: SUP-001 | B5: Tile & Timber Co. | C5: Tile / flooring | D5: Harper Quinn | E5: +1-503-555-0160 | F5: orders@tileandtimber.example | G5: tileandtimber.example | H5: 4.7 | I5: Net 15 | J5: 7 | K5: Preferred tile house
A6: SUP-002 | B6: Ferguson | C6: Plumbing fixtures | D6: Counter desk | E6: +1-503-555-2000 | F6: pdx@ferguson.example | G6: ferguson.com | H6: 4.5 | I6: Net 30 | J6: 10 | K6: Will-call available
A7: SUP-003 | B7: Caesarstone | C7: Counters | D7: West desk | E7: +1-800-555-0199 | F7: west@caesarstone.example | G7: caesarstoneus.com | H7: 4.6 | I7: Prepaid | J7: 14 | K7: Frost 5110 in stock
A8: SUP-004 | B8: Sub-Zero / Wolf dealer | C8: Appliances | D8: Aiden Brooks | E8: +1-503-555-2111 | F8: aiden@swdealer.example | G8: subzero-wolf.com | H8: 4.8 | I8: 50% deposit | J8: 28 | K8: Delivery window Sep 12
A9: SUP-005 | B9: Rejuvenation | C9: Hardware / lighting | D9: Online + Pearl | E9: +1-888-401-1900 | F9: hello@rejuvenation.example | G9: rejuvenation.com | H9: 4.6 | I9: Card | J9: 12 | K9: Hardware in transit
A10: SUP-006 | B10: Sherwin-Williams | C10: Paint | D10: Hawthorne store | E10: +1-503-555-2220 | F10: store@sw.example | G10: sherwin-williams.com | H10: 4.4 | I10: Card | J10: 1 | K10: Color match BM
A11: SUP-007 | B11: Article | C11: Furniture | D11: Wholesale desk | E11: +1-888-746-3455 | F11: trade@article.example | G11: article.com | H11: 4.3 | I11: Prepaid | J11: 42 | K11: Order by Sep 1
A12: SUP-008 | B12: WarmFloor Co. | C12: Radiant | D12: Support | E12: +1-800-555-0182 | F12: support@warmfloor.example | G12: warmfloor.example | H12: 4.5 | I12: Card | J12: 5 | K12: 10yr warranty
A13: SUP-009 | B13: BrightPath Lighting | C13: Lighting | D13: Nina Cho | E13: +1-503-555-0180 | F13: nina@brightpath.example | G13: brightpath.example | H13: 4.6 | I13: Net 15 | J13: 21 | K13: Also a contractor
A14: SUP-010 | B14: Garden & Gate Yard | C14: Hardscape | D14: Theo Brooks | E14: +1-503-555-0199 | F14: yard@gardengate.example | G14: gardengate.example | H14: 4.4 | I14: 50% deposit | J14: 14 | K14: Bluestone seasonal

Sheet Documents
A1: DOCUMENTS
A2: Project vault · contracts, permits, warranties, photos, signed agreements
A4: Doc ID | B4: Project ID | C4: Room ID | D4: Category | E4: Title | F4: Version | G4: File Link | H4: Upload Date | I4: Expiration | J4: Signed | K4: Owner | L4: Notes | M4: Days to Expiry | N4: Expiry Alert
A5: DOC-001 | B5: PRJ-001 | D5: Contract | E5: Ironwood GC agreement | F5: 1.2 | G5: drive/docs/iw-contract.pdf | H5: 46085 | J5: Yes | K5: Alex Rivera | L5: Signed via DocuSign | M5: =IF(OR($A5="",$I5=""),"",$I5-AsOfDate) | N5: =IF(OR($A5="",$I5=""),"",IF($I5<AsOfDate,"Expired",IF($I5<=AsOfDate+30,"Expiring","OK")))
A6: DOC-002 | B6: PRJ-001 | D6: Contract | E6: Luna Interiors design services | F6: 1.0 | G6: drive/docs/luna-contract.pdf | H6: 46087 | J6: Yes | K6: Alex Rivera | M6: =IF(OR($A6="",$I6=""),"",$I6-AsOfDate) | N6: =IF(OR($A6="",$I6=""),"",IF($I6<AsOfDate,"Expired",IF($I6<=AsOfDate+30,"Expiring","OK")))
A7: DOC-003 | B7: PRJ-001 | C7: RM-01 | D7: Contract | E7: Cascade Cabinets millwork | F7: 1.1 | G7: drive/docs/cascade-contract.pdf | H7: 46170 | J7: Yes | K7: Alex Rivera | L7: Includes install | M7: =IF(OR($A7="",$I7=""),"",$I7-AsOfDate) | N7: =IF(OR($A7="",$I7=""),"",IF($I7<AsOfDate,"Expired",IF($I7<=AsOfDate+30,"Expiring","OK")))
A8: DOC-004 | B8: PRJ-001 | D8: Building Permit | E8: Residential remodel permit | F8: 1.0 | G8: drive/docs/permit-441.pdf | H8: 46124 | I8: 46489 | J8: Yes | K8: Marcus Webb | L8: Expires 12 months | M8: =IF(OR($A8="",$I8=""),"",$I8-AsOfDate) | N8: =IF(OR($A8="",$I8=""),"",IF($I8<AsOfDate,"Expired",IF($I8<=AsOfDate+30,"Expiring","OK")))
A9: DOC-005 | B9: PRJ-001 | D9: License | E9: Ironwood CCB + insurance cert | F9: 2026 | G9: drive/docs/iw-insurance.pdf | H9: 46085 | I9: 46507 | J9: No | K9: Marcus Webb | L9: Remind 30 days prior | M9: =IF(OR($A9="",$I9=""),"",$I9-AsOfDate) | N9: =IF(OR($A9="",$I9=""),"",IF($I9<AsOfDate,"Expired",IF($I9<=AsOfDate+30,"Expiring","OK")))
A10: DOC-006 | B10: PRJ-001 | C10: RM-01 | D10: Floor Plan | E10: Kitchen layout v4 | F10: 4.0 | G10: drive/plans/kitchen-v4.pdf | H10: 46152 | J10: Yes | K10: Sofia Alvarez | L10: Supersedes v3 | M10: =IF(OR($A10="",$I10=""),"",$I10-AsOfDate) | N10: =IF(OR($A10="",$I10=""),"",IF($I10<AsOfDate,"Expired",IF($I10<=AsOfDate+30,"Expiring","OK")))
A11: DOC-007 | B11: PRJ-001 | C11: RM-03 | D11: Floor Plan | E11: Primary bath plan | F11: 2.0 | G11: drive/plans/bath-v2.pdf | H11: 46154 | J11: Yes | K11: Sofia Alvarez | M11: =IF(OR($A11="",$I11=""),"",$I11-AsOfDate) | N11: =IF(OR($A11="",$I11=""),"",IF($I11<AsOfDate,"Expired",IF($I11<=AsOfDate+30,"Expiring","OK")))
A12: DOC-008 | B12: PRJ-001 | D12: Inspection Report | E12: Plumbing rough inspection | F12: 1.0 | G12: drive/insp/plumb-rough.pdf | H12: 46203 | J12: No | K12: Riley Grant | L12: Pass | M12: =IF(OR($A12="",$I12=""),"",$I12-AsOfDate) | N12: =IF(OR($A12="",$I12=""),"",IF($I12<AsOfDate,"Expired",IF($I12<=AsOfDate+30,"Expiring","OK")))
A13: DOC-009 | B13: PRJ-001 | D13: Inspection Report | E13: Electrical rough inspection | F13: 1.0 | G13: drive/insp/elec-rough.pdf | H13: 46205 | J13: No | K13: Riley Grant | L13: Pass | M13: =IF(OR($A13="",$I13=""),"",$I13-AsOfDate) | N13: =IF(OR($A13="",$I13=""),"",IF($I13<AsOfDate,"Expired",IF($I13<=AsOfDate+30,"Expiring","OK")))
A14: DOC-010 | B14: PRJ-001 | C14: RM-03 | D14: Warranty | E14: Heritage tile labor + material | F14: 1.0 | G14: drive/warr/heritage.pdf | H14: 46246 | I14: 46977 | J14: No | K14: Priya Shah | L14: 2 year labor | M14: =IF(OR($A14="",$I14=""),"",$I14-AsOfDate) | N14: =IF(OR($A14="",$I14=""),"",IF($I14<AsOfDate,"Expired",IF($I14<=AsOfDate+30,"Expiring","OK")))
A15: DOC-011 | B15: PRJ-001 | C15: RM-03 | D15: Product Manual | E15: WarmFloor thermostat | F15: 1.0 | G15: drive/manuals/wf.pdf | H15: 46209 | J15: No | K15: Sam Ortiz | M15: =IF(OR($A15="",$I15=""),"",$I15-AsOfDate) | N15: =IF(OR($A15="",$I15=""),"",IF($I15<AsOfDate,"Expired",IF($I15<=AsOfDate+30,"Expiring","OK")))
A16: DOC-012 | B16: PRJ-001 | C16: RM-01 | D16: Invoice | E16: Cascade deposit INV-CC-501 | F16: 1.0 | G16: drive/inv/cc-501.pdf | H16: 46236 | J16: No | K16: Jamie Cole | L16: Paid | M16: =IF(OR($A16="",$I16=""),"",$I16-AsOfDate) | N16: =IF(OR($A16="",$I16=""),"",IF($I16<AsOfDate,"Expired",IF($I16<=AsOfDate+30,"Expiring","OK")))
A17: DOC-013 | B17: PRJ-001 | C17: RM-01 | D17: Photo | E17: Kitchen before set | F17: 1.0 | G17: drive/photos/kitchen-before | H17: 46093 | J17: No | K17: Alex Rivera | L17: 20 images | M17: =IF(OR($A17="",$I17=""),"",$I17-AsOfDate) | N17: =IF(OR($A17="",$I17=""),"",IF($I17<AsOfDate,"Expired",IF($I17<=AsOfDate+30,"Expiring","OK")))
A18: DOC-014 | B18: PRJ-001 | D18: Insurance | E18: Homeowner policy declarations | F18: 2026 | G18: drive/docs/ho-policy.pdf | H18: 46027 | I18: 46392 | J18: No | K18: Alex Rivera | L18: Notify carrier of remodel | M18: =IF(OR($A18="",$I18=""),"",$I18-AsOfDate) | N18: =IF(OR($A18="",$I18=""),"",IF($I18<AsOfDate,"Expired",IF($I18<=AsOfDate+30,"Expiring","OK")))
A19: DOC-015 | B19: PRJ-001 | D19: Change Order | E19: CO-002 island porcelain | F19: 1.0 | G19: drive/co/co-002.pdf | H19: 46255 | J19: No | K19: Alex Rivera | L19: Awaiting signature | M19: =IF(OR($A19="",$I19=""),"",$I19-AsOfDate) | N19: =IF(OR($A19="",$I19=""),"",IF($I19<AsOfDate,"Expired",IF($I19<=AsOfDate+30,"Expiring","OK")))
A20: DOC-016 | B20: PRJ-002 | C20: RM-09 | D20: Photo | E20: Cabin bath before | F20: 1.0 | G20: drive/photos/cabin-before | H20: 46233 | J20: No | K20: Alex Rivera | M20: =IF(OR($A20="",$I20=""),"",$I20-AsOfDate) | N20: =IF(OR($A20="",$I20=""),"",IF($I20<AsOfDate,"Expired",IF($I20<=AsOfDate+30,"Expiring","OK")))

Sheet Messages
A1: MESSAGES
A2: Homeowner ↔ contractor ↔ designer ↔ supplier · keep threads on a room or task
A4: Msg ID | B4: Date / Time | C4: Project ID | D4: Room / Task | E4: From | F4: To | G4: Channel | H4: Message | I4: Attachments | J4: Mentions | K4: Read
A5: MSG-001 | B5: 46254.383 | C5: PRJ-001 | D5: RM-01 / TSK-013 | E5: Maya Chen | F5: Alex Rivera | G5: App | H5: Boxes land tomorrow 7:30. Please keep driveway clear. | J5: @Alex | K5: Yes
A6: MSG-002 | B6: 46254.403 | C6: PRJ-001 | D6: RM-01 / TSK-013 | E6: Alex Rivera | F6: Maya Chen | G6: App | H6: Confirmed. I'll move the car tonight. | J6: @Maya | K6: Yes
A7: MSG-003 | B7: 46255.587 | C7: PRJ-001 | D7: RM-01 | E7: Sofia Alvarez | F7: Project group | G7: Group Chat | H7: AI recommends porcelain on the island only. Mood board updated. | I7: drive/mood/kitchen-01 | J7: @Alex @Marcus | K7: Yes
A8: MSG-004 | B8: 46255.682 | C8: PRJ-001 | D8: RM-01 | E8: Alex Rivera | F8: Sofia Alvarez | G8: App | H8: Approved — keep quartz on the run, porcelain on the island. | J8: @Sofia | K8: Yes
A9: MSG-005 | B9: 46256.334 | C9: PRJ-001 | D9: MAT-002 | E9: Maya Chen | F9: Marcus Webb | G9: SMS | H9: Pulls still in transit. ETA Friday. Plan hardware day next week. | J9: @Marcus | K9: Yes
A10: MSG-006 | B10: 46256.471 | C10: PRJ-001 | D10: RM-03 / TSK-010 | E10: Priya Shah | F10: Alex Rivera | G10: Photo Comment | H10: Haze on the niche shelf — will reclean Thursday. | I10: drive/photos/bath-niche | J10: @Alex | K10: Yes
A11: MSG-007 | B11: 46257.739 | C11: PRJ-001 | D11: JOB-006 | E11: Elena Voss | F11: Project group | G11: Group Chat | H11: Finish coat Tuesday. No traffic 48 hours. | J11: @all | K11: Yes
A12: MSG-008 | B12: 46258.33 | C12: PRJ-001 | D12: TSK-027 | E12: Marcus Webb | F12: Project group | G12: App | H12: Weekly meeting tomorrow 9:00 on site. Agenda in documents. | I12: drive/docs/agenda-0825.pdf | J12: @Alex @Sofia @Maya | K12: No
A13: MSG-009 | B13: 46258.34 | C13: PRJ-001 | D13: AI-005 | E13: Morgan Ellis | F13: Alex Rivera | G13: Email | H13: Contingency dropped below 10%. Recommend pausing water feature. | J13: @Alex @Jamie | K13: No
A14: MSG-010 | B14: 46246.626 | C14: PRJ-001 | D14: DOC-009 | E14: Riley Grant | F14: Marcus Webb | G14: App | H14: Electrical rough passed. Final after device install. | I14: drive/insp/elec-rough.pdf | J14: @Marcus | K14: Yes
A15: MSG-011 | B15: 46252.812 | C15: PRJ-002 | D15: RM-09 | E15: Sofia Alvarez | F15: Alex Rivera | G15: App | H15: Cabin Japandi board is in Design Studio. Two fixture directions. | I15: drive/mood/cabin | J15: @Alex | K15: Yes
A16: MSG-012 | B16: 46253.42 | C16: PRJ-001 | D16: SUP-004 | E16: Harper Quinn | F16: Sofia Alvarez | G16: Email | H16: Wolf range crate confirmed for Sep 12 window. | J16: @Sofia | K16: Yes

Sheet Inventory
A1: INVENTORY
A2: Everything in the house · insurance + future maintenance
A4: Item ID | B4: Item | C4: Brand | D4: Room / Location | E4: Category | F4: Purchase Date | G4: Cost | H4: Warranty (yrs) | I4: Warranty End | J4: Serial | K4: Model | L4: Receipt | M4: Condition | N4: Replacement Value | O4: Notes
A5: INV-001 | B5: Samsung Refrigerator (existing, to donate) | C5: Samsung | D5: RM-01 | E5: Appliance | F5: 43556 | G5: 1200 | H5: 1 | I5: =IF(OR($A5="",$F5="",$H5=""),"",EDATE($F5,$H5*12)) | J5: RF28R7351SG | K5: RF28 | L5: drive/rcpt/old-fridge | M5: Fair | N5: 400 | O5: Pickup scheduled after new fridge arrives
A6: INV-002 | B6: Sub-Zero fridge (on order) | C6: Sub-Zero | D6: RM-01 | E6: Appliance | F6: 46277 | G6: 0 | H6: 2 | I6: =IF(OR($A6="",$F6="",$H6=""),"",EDATE($F6,$H6*12)) | J6: TBD | K6: DEC3650 | L6: APPL-01 | M6: On order | N6: 8900 | O6: Serial on delivery
A7: INV-003 | B7: Wolf 36 dual-fuel range (on order) | C7: Wolf | D7: RM-01 | E7: Appliance | F7: 46277 | G7: 0 | H7: 2 | I7: =IF(OR($A7="",$F7="",$H7=""),"",EDATE($F7,$H7*12)) | J7: TBD | K7: DF364C | L7: APPL-01 | M7: On order | N7: 7900
A8: INV-004 | B8: Bosch dishwasher | C8: Bosch | D8: RM-01 | E8: Appliance | F8: 45078 | G8: 980 | H8: 1 | I8: =IF(OR($A8="",$F8="",$H8=""),"",EDATE($F8,$H8*12)) | J8: FD-2291 | K8: SHPM88Z75N | L8: drive/rcpt/dw | M8: Good | N8: 900 | O8: Reuse
A9: INV-005 | B9: WarmFloor thermostat | C9: WarmFloor | D9: RM-03 | E9: System | F9: 46209 | G9: 1680 | H9: 3 | I9: =IF(OR($A9="",$F9="",$H9=""),"",EDATE($F9,$H9*12)) | J9: WF-T-44190 | K9: WF-STAT-2 | L9: WF-441 | M9: New | N9: 1680 | O9: Program 82F mornings
A10: INV-006 | B10: Brizo shower set | C10: Brizo | D10: RM-03 | E10: Fixture | F10: 46248 | G10: 890 | H10: 5 | I10: =IF(OR($A10="",$F10="",$H10=""),"",EDATE($F10,$H10*12)) | J10: BZ-100221 | K10: BZ-T600 | L10: FERG-9921 | M10: New | N10: 890
A11: INV-007 | B11: Primary bath vanity | C11: Cascade | D11: RM-03 | E11: Cabinetry | F11: 46223 | G11: 1680 | H11: 2 | I11: =IF(OR($A11="",$F11="",$H11=""),"",EDATE($F11,$H11*12)) | J11: CC-VAN-48-09 | K11: CC-VAN-48 | L11: INV-CC-440 | M11: New | N11: 1680
A12: INV-008 | B12: HVAC furnace | C12: Trane | D12: Laundry / mech | E12: HVAC | F12: 44440 | G12: 4200 | H12: 1 | I12: =IF(OR($A12="",$F12="",$H12=""),"",EDATE($F12,$H12*12)) | J12: TR-88120 | K12: S9V2 | L12: drive/rcpt/hvac | M12: Good | N12: 3800 | O12: Filter every 90 days
A13: INV-009 | B13: Water heater (heat pump) | C13: Rheem | D13: Laundry / mech | E13: Plumbing | F13: 45332 | G13: 2100 | H13: 2 | I13: =IF(OR($A13="",$F13="",$H13=""),"",EDATE($F13,$H13*12)) | J13: RH-44019 | K13: PROPH80 | L13: drive/rcpt/wh | M13: Good | N13: 2000 | O13: Anode 2027
A14: INV-010 | B14: Roof — architectural shingle | C14: Owens Corning | D14: Exterior | E14: Envelope | F14: 43282 | G14: 9800 | H14: 2 | I14: =IF(OR($A14="",$F14="",$H14=""),"",EDATE($F14,$H14*12)) | K14: Duration | L14: drive/rcpt/roof | M14: Fair | N14: 12000 | O14: Inspect after storms
A15: INV-011 | B15: Washer / dryer pair | C15: LG | D15: RM-07 | E15: Appliance | F15: 44866 | G15: 1600 | H15: 1 | I15: =IF(OR($A15="",$F15="",$H15=""),"",EDATE($F15,$H15*12)) | J15: LG-W8821 / LG-D8821 | K15: WM4000 / DLEX4000 | L15: drive/rcpt/ld | M15: Good | N15: 1400
A16: INV-012 | B16: Living room rug (existing) | C16: West Elm | D16: RM-02 | E16: Furniture | F16: 43845 | G16: 640 | H16: 0 | I16: =IF(OR($A16="",$F16="",$H16=""),"",EDATE($F16,$H16*12)) | K16: Kelim 9x12 | M16: Keep | N16: 400 | O16: Clean after flooring
A17: INV-013 | B17: Entry hook rail | C17: Rejuvenation | D17: RM-08 | E17: Hardware | F17: 46253 | G17: 186 | H17: 1 | I17: =IF(OR($A17="",$F17="",$H17=""),"",EDATE($F17,$H17*12)) | K17: RJ-HR-48 | L17: REJ-33 | M17: New | N17: 186 | O17: Install this week
A18: INV-014 | B18: Smoke / CO detectors x6 | C18: First Alert | D18: Whole home | E18: Safety | F18: 45665 | G18: 180 | H18: 10 | I18: =IF(OR($A18="",$F18="",$H18=""),"",EDATE($F18,$H18*12)) | K18: SMCO410 | M18: Good | N18: 180 | O18: Hush test monthly
A19: INV-015 | B19: Cabin water filter | C19: Berkey | D19: PROP-002 | E19: Plumbing | F19: 45047 | G19: 320 | H19: 2 | I19: =IF(OR($A19="",$F19="",$H19=""),"",EDATE($F19,$H19*12)) | K19: Royal | M19: Good | N19: 280 | O19: Replace elements 2026-11

Sheet Maintenance
A1: MAINTENANCE
A2: The system does not end at handover · HVAC, roof, warranties, pest, water, solar
A4: Maint ID | B4: Item / System | C4: Room / Location | D4: Type | E4: Frequency | F4: Last Service | G4: Next Due | H4: Vendor | I4: Est. Cost | J4: Status | K4: Remind (days) | L4: Notes | M4: Days Until Due | N4: Reminder
A5: MNT-001 | B5: HVAC furnace service | C5: Laundry / mech | D5: HVAC | E5: Annual | F5: 45942 | G5: 46307 | H5: Allied Heating | I5: 180 | J5: Upcoming | K5: 14 | L5: Replace filter at service | M5: =IF(OR($A5="",$G5=""),"",$G5-AsOfDate) | N5: =IF($A5="","",IF($J5="Complete","—",IF($G5<AsOfDate,"🔔 OVERDUE",IF($G5<=AsOfDate+$K5,"🔔 Due soon","OK"))))
A6: MNT-002 | B6: Heat-pump water heater flush | C6: Laundry / mech | D6: Plumbing | E6: Annual | F6: 45698 | G6: 46275 | H6: Pacific Plumbing | I6: 140 | J6: Due Soon | K6: 14 | L6: Check anode | M6: =IF(OR($A6="",$G6=""),"",$G6-AsOfDate) | N6: =IF($A6="","",IF($J6="Complete","—",IF($G6<AsOfDate,"🔔 OVERDUE",IF($G6<=AsOfDate+$K6,"🔔 Due soon","OK"))))
A7: MNT-003 | B7: Gutter clean + roof walk | C7: Exterior | D7: Envelope | E7: Biannual | F7: 46114 | G7: 46310 | H7: Ironwood / roofer | I7: 220 | J7: Upcoming | K7: 14 | L7: After leaf drop | M7: =IF(OR($A7="",$G7=""),"",$G7-AsOfDate) | N7: =IF($A7="","",IF($J7="Complete","—",IF($G7<AsOfDate,"🔔 OVERDUE",IF($G7<=AsOfDate+$K7,"🔔 Due soon","OK"))))
A8: MNT-004 | B8: Paint touch-up interior | C8: Whole home | D8: Finishes | E8: As needed | G8: 46346 | H8: Greenfield Painting | I8: 0 | J8: Upcoming | K8: 7 | L8: Leave labeled quarts | M8: =IF(OR($A8="",$G8=""),"",$G8-AsOfDate) | N8: =IF($A8="","",IF($J8="Complete","—",IF($G8<AsOfDate,"🔔 OVERDUE",IF($G8<=AsOfDate+$K8,"🔔 Due soon","OK"))))
A9: MNT-005 | B9: Pest control | C9: Exterior | D9: Pest | E9: Quarterly | F9: 46174 | G9: 46266 | H9: Oregon Pest | I9: 95 | J9: Due Soon | K9: 7 | M9: =IF(OR($A9="",$G9=""),"",$G9-AsOfDate) | N9: =IF($A9="","",IF($J9="Complete","—",IF($G9<AsOfDate,"🔔 OVERDUE",IF($G9<=AsOfDate+$K9,"🔔 Due soon","OK"))))
A10: MNT-006 | B10: Radiant floor test | C10: RM-03 | D10: Electrical | E10: Annual | F10: 46209 | G10: 46574 | H10: WarmFloor / NWE | I10: 0 | J10: Upcoming | K10: 30 | L10: First winter check | M10: =IF(OR($A10="",$G10=""),"",$G10-AsOfDate) | N10: =IF($A10="","",IF($J10="Complete","—",IF($G10<AsOfDate,"🔔 OVERDUE",IF($G10<=AsOfDate+$K10,"🔔 Due soon","OK"))))
A11: MNT-007 | B11: Appliance warranty photo set | C11: RM-01 | D11: Appliance | E11: Once | G11: 46285 | H11: Alex Rivera | I11: 0 | J11: Upcoming | K11: 3 | L11: After delivery | M11: =IF(OR($A11="",$G11=""),"",$G11-AsOfDate) | N11: =IF($A11="","",IF($J11="Complete","—",IF($G11<AsOfDate,"🔔 OVERDUE",IF($G11<=AsOfDate+$K11,"🔔 Due soon","OK"))))
A12: MNT-008 | B12: Smoke / CO test | C12: Whole home | D12: Safety | E12: Monthly | F12: 46235 | G12: 46266 | H12: Alex Rivera | I12: 0 | J12: Upcoming | K12: 3 | M12: =IF(OR($A12="",$G12=""),"",$G12-AsOfDate) | N12: =IF($A12="","",IF($J12="Complete","—",IF($G12<AsOfDate,"🔔 OVERDUE",IF($G12<=AsOfDate+$K12,"🔔 Due soon","OK"))))
A13: MNT-009 | B13: Cabin water filter elements | C13: PROP-002 | D13: Plumbing | E13: Annual | F13: 45962 | G13: 46327 | H13: Alex Rivera | I13: 60 | J13: Upcoming | K13: 14 | M13: =IF(OR($A13="",$G13=""),"",$G13-AsOfDate) | N13: =IF($A13="","",IF($J13="Complete","—",IF($G13<AsOfDate,"🔔 OVERDUE",IF($G13<=AsOfDate+$K13,"🔔 Due soon","OK"))))
A14: MNT-010 | B14: Window weatherstrip | C14: Whole home | D14: Envelope | E14: Annual | F14: 45976 | G14: 46336 | H14: Ironwood | I14: 160 | J14: Upcoming | K14: 14 | L14: Before handover winter | M14: =IF(OR($A14="",$G14=""),"",$G14-AsOfDate) | N14: =IF($A14="","",IF($J14="Complete","—",IF($G14<AsOfDate,"🔔 OVERDUE",IF($G14<=AsOfDate+$K14,"🔔 Due soon","OK"))))
A15: MNT-011 | B15: Irrigation blowout | C15: RM-06 | D15: Landscape | E15: Annual | F15: 45950 | G15: 46315 | H15: Garden & Gate | I15: 120 | J15: Upcoming | K15: 14 | L15: After path work | M15: =IF(OR($A15="",$G15=""),"",$G15-AsOfDate) | N15: =IF($A15="","",IF($J15="Complete","—",IF($G15<AsOfDate,"🔔 OVERDUE",IF($G15<=AsOfDate+$K15,"🔔 Due soon","OK"))))
A16: MNT-012 | B16: Grout seal — primary bath | C16: RM-03 | D16: Tile | E16: Annual | F16: 46246 | G16: 46611 | H16: Heritage Tile | I16: 0 | J16: Complete | K16: 30 | L16: Sealed at install | M16: =IF(OR($A16="",$G16=""),"",$G16-AsOfDate) | N16: =IF($A16="","",IF($J16="Complete","—",IF($G16<AsOfDate,"🔔 OVERDUE",IF($G16<=AsOfDate+$K16,"🔔 Due soon","OK"))))

Sheet Inspections
A1: INSPECTIONS
A2: City + independent · attach reports in the vault
A4: Insp ID | B4: Project ID | C4: Room ID | D4: Type | E4: Inspector | F4: Date | G4: Result | H4: Issues Found | I4: Follow-up | J4: Status | K4: Report Link
A5: INS-001 | B5: PRJ-001 | D5: Building permit review | E5: Riley Grant | F5: 46124 | G5: Pass | H5: None | J5: Complete | K5: drive/insp/permit.pdf
A6: INS-002 | B6: PRJ-001 | C6: RM-01 | D6: Electrical rough | E6: Riley Grant | F6: 46205 | G6: Pass | H6: Add AFCI in pantry — done same day | J6: Complete | K6: drive/insp/elec-rough.pdf
A7: INS-003 | B7: PRJ-001 | C7: RM-03 | D7: Plumbing rough | E7: Riley Grant | F7: 46203 | G7: Pass | H7: None | J7: Complete | K7: drive/insp/plumb-rough.pdf
A8: INS-004 | B8: PRJ-001 | C8: RM-03 | D8: Waterproofing / shower pan | E8: Marcus Webb | F8: 46213 | G8: Pass | H8: None | J8: Complete | K8: drive/insp/pan.pdf
A9: INS-005 | B9: PRJ-001 | C9: RM-03 | D9: Primary bath punch | E9: Priya Shah | F9: 46260 | G9: Scheduled | H9: Haze on niche | I9: Reclean + photo | J9: Scheduled
A10: INS-006 | B10: PRJ-001 | D10: Electrical final | E10: Riley Grant | F10: 46323 | G10: Scheduled | I10: After devices | J10: Scheduled
A11: INS-007 | B11: PRJ-001 | D11: Plumbing final | E11: Riley Grant | F11: 46323 | G11: Scheduled | J11: Scheduled
A12: INS-008 | B12: PRJ-001 | D12: Building final | E12: Riley Grant | F12: 46330 | G12: Scheduled | I12: After electrical/plumbing finals | J12: Scheduled
A13: INS-009 | B13: PRJ-001 | D13: Independent punch | E13: Alder Inspection Group | F13: 46334 | G13: Scheduled | I13: Pre-handover | J13: Scheduled

Sheet Payments
A1: PAYMENTS
A2: Draws, deposits, scheduled wires · aging for unpaid
A4: Pay ID | B4: Date | C4: Payee Type | D4: Payee | E4: Project ID | F4: Invoice # | G4: Amount | H4: Method | I4: Status | J4: Due Date | K4: Paid Date | L4: Aging (days)
A5: PAY-001 | B5: 46089 | C5: Designer | D5: Luna Interiors | E5: PRJ-001 | F5: INV-LUNA-110 | G5: 2400 | H5: ACH | I5: Paid | J5: 46096 | K5: 46089 | L5: =IF($A5="","",IF($I5="Paid",0,IF($J5="","" ,AsOfDate-$J5)))
A6: PAY-002 | B6: 46114 | C6: Authority | D6: City of Portland | E6: PRJ-001 | F6: PMT-2026-441 | G6: 840 | H6: Credit Card | I6: Paid | J6: 46114 | K6: 46114 | L6: =IF($A6="","",IF($I6="Paid",0,IF($J6="","" ,AsOfDate-$J6)))
A7: PAY-003 | B7: 46146 | C7: Designer | D7: Luna Interiors | E7: PRJ-001 | F7: INV-LUNA-126 | G7: 1800 | H7: ACH | I7: Paid | J7: 46160 | K7: 46146 | L7: =IF($A7="","",IF($I7="Paid",0,IF($J7="","" ,AsOfDate-$J7)))
A8: PAY-004 | B8: 46164 | C8: Contractor | D8: Ironwood Construction | E8: PRJ-001 | F8: INV-IW-204 | G8: 2800 | H8: Check | I8: Paid | J8: 46178 | K8: 46164 | L8: =IF($A8="","",IF($I8="Paid",0,IF($J8="","" ,AsOfDate-$J8)))
A9: PAY-005 | B9: 46236 | C9: Contractor | D9: Cascade Cabinets | E9: PRJ-001 | F9: INV-CC-501 | G9: 7400 | H9: Wire | I9: Paid | J9: 46243 | K9: 46236 | L9: =IF($A9="","",IF($I9="Paid",0,IF($J9="","" ,AsOfDate-$J9)))
A10: PAY-006 | B10: 46259 | C10: Contractor | D10: Cascade Cabinets | E10: PRJ-001 | F10: INV-CC-502 | G10: 7400 | H10: Wire | I10: Scheduled | J10: 46273 | L10: =IF($A10="","",IF($I10="Paid",0,IF($J10="","" ,AsOfDate-$J10)))
A11: PAY-007 | B11: 46262 | C11: Contractor | D11: Cascade Cabinets | E11: PRJ-001 | F11: INV-CC-510 | G11: 3600 | H11: ACH | I11: Scheduled | J11: 46276 | L11: =IF($A11="","",IF($I11="Paid",0,IF($J11="","" ,AsOfDate-$J11)))
A12: PAY-008 | B12: 46252 | C12: Contractor | D12: Ironwood Construction | E12: PRJ-001 | F12: INV-IW-228 | G12: 1550 | H12: ACH | I12: Paid | J12: 46266 | K12: 46252 | L12: =IF($A12="","",IF($I12="Paid",0,IF($J12="","" ,AsOfDate-$J12)))
A13: PAY-009 | B13: 46242 | C13: Contractor | D13: Heritage Tile & Stone | E13: PRJ-001 | F13: INV-HT-81 | G13: 2100 | H13: ACH | I13: Paid | J13: 46256 | K13: 46242 | L13: =IF($A13="","",IF($I13="Paid",0,IF($J13="","" ,AsOfDate-$J13)))
A14: PAY-010 | B14: 46235 | C14: Designer | D14: Luna Interiors | E14: PRJ-002 | F14: INV-LUNA-140 | G14: 600 | H14: ACH | I14: Paid | J14: 46249 | K14: 46235 | L14: =IF($A14="","",IF($I14="Paid",0,IF($J14="","" ,AsOfDate-$J14)))
A15: PAY-011 | B15: 46277 | C15: Supplier | D15: Article | E15: PRJ-001 | F15: ART-SOFA | G15: 3400 | H15: Credit Card | I15: Draft | J15: 46277 | L15: =IF($A15="","",IF($I15="Paid",0,IF($J15="","" ,AsOfDate-$J15)))

Sheet Change Orders
A1: CHANGE ORDERS
A2: Scope, cost, and schedule impacts · negative cost = savings
A4: CO ID | B4: Project ID | C4: Room ID | D4: Description | E4: Requested By | F4: Date | G4: Cost Impact | H4: Schedule Impact (days) | I4: Status | J4: Approved By
A5: CO-001 | B5: PRJ-001 | C5: RM-03 | D5: Swap marble floor for porcelain HT-8841 | E5: Sofia Alvarez / AI | F5: 46160 | G5: -1640 | H5: 0 | I5: Implemented | J5: Alex Rivera
A6: CO-002 | B6: PRJ-001 | C6: RM-01 | D6: Island surface: porcelain slab instead of marble | E6: Sofia Alvarez / AI | F6: 46255 | G6: -460 | H6: 2 | I6: Submitted
A7: CO-003 | B7: PRJ-001 | C7: RM-01 | D7: Add pot-filler at range | E7: Alex Rivera | F7: 46183 | G7: 480 | H7: 1 | I7: Approved | J7: Alex Rivera
A8: CO-004 | B8: PRJ-001 | C8: RM-02 | D8: Site-cut oak nosing in lieu of factory (backorder) | E8: Elena Voss | F8: 46255 | G8: 0 | H8: 0 | I8: Approved | J8: Marcus Webb
A9: CO-005 | B9: PRJ-001 | C9: RM-06 | D9: Hold water feature until contingency recovers | E9: Morgan Ellis / AI | F9: 46258 | G9: -1800 | H9: 0 | I9: Draft

Sheet Permits
A1: PERMITS
A2: Authority, fees, expiration reminders
A4: Permit ID | B4: Project ID | C4: Type | D4: Authority | E4: Applied | F4: Approved | G4: Number | H4: Fee | I4: Expiration | J4: Status | K4: Document Link | L4: Days to Expiry
A5: PMT-001 | B5: PRJ-001 | C5: Building — residential remodel | D5: City of Portland | E5: 46114 | F5: 46124 | G5: 2026-REM-44182 | H5: 840 | I5: 46489 | J5: Approved | K5: drive/docs/permit-441.pdf | L5: =IF(OR($A5="",$I5=""),"",$I5-AsOfDate)
A6: PMT-002 | B6: PRJ-001 | C6: Electrical | D6: City of Portland | E6: 46130 | F6: 46134 | G6: 2026-EL-11904 | H6: 310 | I6: 46499 | J6: Approved | K6: drive/docs/permit-el.pdf | L6: =IF(OR($A6="",$I6=""),"",$I6-AsOfDate)
A7: PMT-003 | B7: PRJ-001 | C7: Plumbing | D7: City of Portland | E7: 46130 | F7: 46134 | G7: 2026-PL-7731 | H7: 300 | I7: 46499 | J7: Approved | K7: drive/docs/permit-pl.pdf | L7: =IF(OR($A7="",$I7=""),"",$I7-AsOfDate)
A8: PMT-004 | B8: PRJ-001 | C8: Right-of-way dumpster | D8: PBOT | E8: 46152 | F8: 46156 | G8: ROW-5521 | H8: 75 | I8: 46187 | J8: Closed | K8: drive/docs/row.pdf | L8: =IF(OR($A8="",$I8=""),"",$I8-AsOfDate)
A9: PMT-005 | B9: PRJ-002 | C9: Building — bath remodel | D9: Hood River County | H9: 0 | J9: Not Started | L9: =IF(OR($A9="",$I9=""),"",$I9-AsOfDate)

Sheet Warranties
A1: WARRANTIES
A2: Labor and product coverage after handover
A4: Warranty ID | B4: Project ID | C4: Item / Work | D4: Provider | E4: Start | F4: End | G4: Term (months) | H4: Coverage | I4: Claim Process | J4: Doc Link | K4: Days Remaining
A5: WAR-001 | B5: PRJ-001 | C5: Heritage tile labor + material | D5: Heritage Tile & Stone | E5: 46246 | F5: 46977 | G5: 24 | H5: Labor + setting materials | I5: Photo + email Priya | J5: drive/warr/heritage.pdf | K5: =IF(OR($A5="",$F5=""),"",$F5-AsOfDate)
A6: WAR-002 | B6: PRJ-001 | C6: WarmFloor system | D6: WarmFloor Co. | E6: 46209 | F6: 47305 | G6: 36 | H6: Mat + thermostat | I6: Serial + install photos | J6: drive/warr/wf.pdf | K6: =IF(OR($A6="",$F6=""),"",$F6-AsOfDate)
A7: WAR-003 | B7: PRJ-001 | C7: White oak flooring finish | D7: Timberline Floors | E7: 46262 | F7: 46627 | G7: 12 | H7: Site finish wear | I7: No steam mops year 1 | K7: =IF(OR($A7="",$F7=""),"",$F7-AsOfDate)
A8: WAR-004 | B8: PRJ-001 | C8: Cascade cabinetry | D8: Cascade Cabinets | E8: 46280 | F8: 47011 | G8: 24 | H8: Boxes, doors, finish | I8: Maya Chen | K8: =IF(OR($A8="",$F8=""),"",$F8-AsOfDate)
A9: WAR-005 | B9: PRJ-001 | C9: Wolf range (pending delivery) | D9: Sub-Zero Group | E9: 46277 | F9: 47008 | G9: 24 | H9: Parts + labor | I9: Register online 30 days | K9: =IF(OR($A9="",$F9=""),"",$F9-AsOfDate)
A10: WAR-006 | B10: PRJ-001 | C10: Sub-Zero fridge (pending) | D10: Sub-Zero Group | E10: 46277 | F10: 47008 | G10: 24 | H10: Sealed system 5yr | I10: Register online 30 days | K10: =IF(OR($A10="",$F10=""),"",$F10-AsOfDate)
A11: WAR-007 | B11: PRJ-001 | C11: Brizo fixtures | D11: Brizo / Ferguson | E11: 46248 | F11: 48074 | G11: 60 | H11: Finish + function | I11: Proof of purchase | J11: FERG-9921 | K11: =IF(OR($A11="",$F11=""),"",$F11-AsOfDate)

Sheet Calendar
A1: CALENDAR
A2: Visits, deliveries, inspections, reminders · also subscribe via the Apps Script
A4: Date | B4: Time | C4: Event | D4: Project / Property | E4: Detail | F4: Owner | G4: Status
A5: 46259 | B5: 09:00 | C5: Site meeting | D5: PRJ-001 | E5: Weekly GC / designer / homeowner | F5: Marcus Webb | G5: Scheduled
A6: 46259 | B6: 07:30 | C6: Cabinet install | D6: PRJ-001 | E6: Cascade — box set continues | F6: Maya Chen | G6: Scheduled
A7: 46260 | B7: 10:00 | C7: Bath punch | D7: PRJ-001 | E7: Heritage reclean + walk | F7: Priya Shah | G7: Scheduled
A8: 46261 | B8: All day | C8: Hardware ETA | D8: PRJ-001 | E8: Pulls expected — do not hang if late | F8: Maya Chen | G8: Watch
A9: 46262 | B9: All day | C9: Floor finish cure | D9: PRJ-001 | E9: No traffic 48 hours after Tuesday coat | F9: Elena Voss | G9: Scheduled
A10: 46266 | B10: 17:00 | C10: Order sofa | D10: PRJ-001 | E10: 6-week lead — last day to hit Oct move-in | F10: Sofia Alvarez | G10: To Do
A11: 46266 | B11: All day | C11: Pest control due | D11: PROP-001 | E11: Oregon Pest quarterly | F11: Alex Rivera | G11: Due Soon
A12: 46269 | B12: 08:00 | C12: Counter template | D12: PRJ-001 | E12: After doors hung | F12: Heritage Tile | G12: Scheduled
A13: 46275 | B13: 07:00 | C13: Painting starts | D13: PRJ-001 | E13: Guest, dining, entry | F13: Leo Park | G13: Scheduled
A14: 46275 | B14: All day | C14: Water heater flush due | D14: PROP-001 | E14: Pacific Plumbing | F14: Sam Ortiz | G14: Due Soon
A15: 46277 | B15: Window | C15: Appliance delivery | D15: PRJ-001 | E15: Wolf + Sub-Zero | F15: Aiden Brooks | G15: Scheduled
A16: 46301 | B16: 07:00 | C16: Exterior path start | D16: PRJ-001 | E16: Release only if contingency healthy | F16: Theo Brooks | G16: Hold
... A19: 46336 | B19: 10:00 | C19: Handover walkthrough | D19: PRJ-001 | E19: Punch + vault packet | F19: Marcus Webb | G19: To Do

Sheet Notifications
A1: NOTIFICATIONS
A2: In-app / email / SMS queue · mark Status = Read when handled
A4: ID | B4: Date | C4: Severity | D4: Module | E4: Message | F4: Status | G4: Audience
A5: NTF-001 | B5: 46258 | C5: Warning | D5: Budget | E5: Kitchen budget is 12% over original target. Island swap pending. | F5: Open | G5: HO-001
A6: NTF-002 | B6: 46258 | C6: Critical | D6: Finance | E6: Project contingency has fallen below 10%. | F6: Open | G6: HO-001
A7: NTF-003 | B7: 46258 | C7: Success | D7: Rooms | E7: Primary bathroom is under budget after porcelain swap. | F7: Open | G7: HO-001
A8: NTF-004 | B8: 46257 | C8: Warning | D8: Procurement | E8: White oak stair nosing backordered 11 days. | F8: Open | G8: PM-001
A9: NTF-005 | B9: 46256 | C9: Info | D9: Schedule | E9: Cabinet hardware still in transit — hardware day next week. | F9: Open | G9: CT-001
A10: NTF-006 | B10: 46254 | C10: Info | D10: Visit | E10: Cascade Cabinets on site Aug 25–27 for box set. | F10: Open | G10: HO-001
A11: NTF-007 | B11: 46252 | C11: Warning | D11: Approval | E11: CO-002 island porcelain awaiting signature. | F11: Open | G11: HO-001
A12: NTF-008 | B12: 46266 | C12: Info | D12: Maintenance | E12: Pest control due in 8 days. | F12: Scheduled | G12: HO-001
A13: NTF-009 | B13: 46258 | C13: Info | D13: Message | E13: Marcus posted tomorrow's site meeting agenda. | F13: Open | G13: HO-001
A14: NTF-010 | B14: 46246 | C14: Success | D14: Inspection | E14: Electrical rough passed. | F14: Read | G14: PM-001

Sheet Users
A1: USERS
A2: Nine roles · each role sees a different dashboard in the product
A4: User ID | B4: Name | C4: Email | D4: Phone | E4: Role | F4: Company | G4: Status | H4: Last Login | I4: Permissions
A5: HO-001 | B5: Alex Rivera | C5: alex.rivera@email.example | D5: +1-503-555-0148 | E5: Homeowner | F5: Rivera Household | G5: Active | H5: 46258 | I5: Full project visibility, approvals, payments
A6: AD-001 | B6: Morgan Ellis | C6: morgan@novalitystore.example | D6: +1-503-555-0100 | E6: Admin | F6: Novality Store | G6: Active | H6: 46258 | I6: System admin, all properties
A7: PM-001 | B7: Marcus Webb | C7: marcus@ironwood.build | D7: +1-503-555-0172 | E7: Project Manager | F7: Ironwood Construction | G7: Active | H7: 46257 | I7: Schedule, contractors, inspections
A8: DS-001 | B8: Sofia Alvarez | C8: sofia@lunainteriors.example | D8: +1-503-555-0194 | E8: Interior Designer | F8: Luna Interiors | G8: Active | H8: 46256 | I8: Design studio, materials, mood boards
A9: CT-001 | B9: Maya Chen | C9: maya@cascadecabinets.example | D9: +1-503-555-0111 | E9: Contractor | F9: Cascade Cabinets | G9: Active | H9: 46255 | I9: Kitchen millwork
A10: SC-001 | B10: Devon Ruiz | C10: devon@nw-electric.example | D10: +1-503-555-0133 | E10: Subcontractor | F10: Northwest Electric | G10: Active | H10: 46254 | I10: Electrical rough and finish
A11: SU-001 | B11: Harper Quinn | C11: orders@tileandtimber.example | D11: +1-503-555-0160 | E11: Supplier | F11: Tile & Timber Co. | G11: Active | H11: 46252 | I11: Materials, lead times
A12: IN-001 | B12: Riley Grant | C12: r.grant@portland.gov.example | D12: +1-503-555-0188 | E12: Inspector | F12: City of Portland | G12: Active | H12: 46246 | I12: Building, electrical, plumbing
A13: AC-001 | B13: Jamie Cole | C13: jamie@novalitystore.example | D13: +1-503-555-0108 | E13: Accountant | F13: Novality Store | G13: Active | H13: 46258 | I13: Invoices, tax, payments

Sheet Properties
A1: PROPERTIES
A2: Multi-property digital twin · one row per home
A4: Property ID | B4: Name | C4: Street | D4: City | E4: State | F4: Postal | G4: Country | H4: Type | I4: Year Built | J4: Sq Ft | K4: Stories | L4: Beds | M4: Baths | N4: Owner | O4: Owner User ID | P4: Insurance Policy | Q4: Insurance Year | R4: Notes
A5: PROP-001 | B5: Maplewood Residence | C5: 1847 Maplewood Drive | D5: Portland | E5: OR | F5: 97214 | G5: USA | H5: Single Family | I5: 1928 | J5: 2480 | K5: 2 | L5: 4 | M5: 2.5 | N5: Alex Rivera | O5: HO-001 | P5: State Farm HO-34821 | Q5: 2027 | R5: Craftsman with later additions. Knob-and-tube mostly retired.
A6: PROP-002 | B6: Columbia Gorge Cabin | C6: 88 Ridge Trail | D6: Hood River | E6: OR | F6: 97031 | G6: USA | H6: Cabin | I6: 1998 | J6: 980 | K6: 1 | L6: 2 | M6: 1 | N6: Alex Rivera | O6: HO-001 | P6: State Farm HO-34822 | Q6: 2027 | R6: Weekend cabin. Bath refresh only.

Sheet Roles & Permissions
A1: ROLES & PERMISSIONS
A2: Who can see and change what · enforce in the live product; this matrix is the source of truth
A4: Module \ Role | B4: Homeowner | C4: Admin | D4: Project Manager | E4: Interior Designer | F4: Contractor | G4: Subcontractor | H4: Supplier | I4: Inspector | J4: Accountant
A5: Dashboard | B5: F | C5: F | D5: F | E5: V | F5: V | G5: V | H5: — | I5: V | J5: V
A6: Projects | B6: F | C6: F | D6: F | E6: V | F6: V | G6: V | H6: — | I6: V | J6: V
A7: Rooms | B7: F | C7: F | D7: F | E7: F | F7: V | G7: V | H7: — | I7: V | J7: —
A8: Design Studio | B8: F | C8: F | D8: V | E8: F | F8: V | G8: — | H8: — | I8: — | J8: —
A9: AI Insights | B9: V | C9: F | D9: V | E9: F | F9: — | G9: — | H9: — | I9: — | J9: —
A10: Budget | B10: V | C10: F | D10: F | E10: V | F10: — | G10: — | H10: — | I10: — | J10: F
A11: Expenses | B11: E | C11: F | D11: F | E11: V | F11: E | G11: — | H11: — | I11: — | J11: F
A12: Finance | B12: V | C12: F | D12: F | E12: V | F12: — | G12: — | H12: — | I12: — | J12: F
A13: Contractors | B13: V | C13: F | D13: F | E13: V | F13: V | G13: — | H13: — | I13: V | J13: V
A14: Quotes | B14: V | C14: F | D14: F | E14: V | F14: V | G14: — | H14: V | I14: — | J14: V
A15: Jobs | B15: V | C15: F | D15: F | E15: V | F15: F | G15: F | H15: — | I15: V | J15: V
... A28: Users | B28: — | C28: F | D28: V | E28: — | F28: — | G28: — | H28: — | I28: — | J28: V
A30: F = full · E = edit own records · V = view · A = approve · — = no access

Sheet Admin
A1: ADMIN
A2: System administrator · portfolio of all homeowners and projects
A5: HOMEOWNERS | D5: ACTIVE PROJECTS | G5: COMPLETED | J5: CONTRACTORS
A6: =COUNTIF(Users!E:E,"Homeowner") | D6: =COUNTIF(Projects!E:E,"Active") | G6: =COUNTIF(Projects!E:E,"Completed") | J6: =COUNTA(Contractors!A5:A200)
A7: Active household accounts | D7: In construction or design | G7: Renovations handed over | J7: In the bench
A9: PORTFOLIO VALUE | D9: REVENUE (PAID) | G9: DELAYED TASKS | J9: OPEN DISPUTES
A10: =SUM(Projects!J:J) | D10: =SUMIF(Expenses!J:J,"Paid",Expenses!H:H) | G10: =COUNTIF(Tasks!Q:Q,"Overdue") | J10: =COUNTIF(Jobs!J:J,"Disputed")+COUNTIF(Payments!I:I,"Disputed")
A11: Sum of project budgets | D11: Cash out recorded | G11: Across all projects | J11: Jobs + payments
A13: PENDING APPROVALS | D13: OPEN MESSAGES | G13: PERMITS OPEN | J13: MAINT DUE
A14: =COUNTIF('Change Orders'!I:I,"Submitted")+COUNTIF(Quotes!J:J,"Received") | D14: =COUNTIF(Messages!K:K,"No") | G14: =COUNTIFS(Permits!J:J,"<>Closed",Permits!J:J,"<>")-1 | J14: =COUNTIF(Maintenance!N:N,"🔔 OVERDUE")+COUNTIF(Maintenance!N:N,"🔔 Due soon")
A15: COs + quotes | D15: Unread | G15: Not closed | J15: Aftercare load
A17: PROJECT PORTFOLIO
A18: Project | B18: Property | C18: Status | D18: Phase | E18: Budget | F18: Spent | G18: Health | H18: Progress
A19: =IFERROR(INDEX(Projects!C:C,MATCH("PRJ-001",Projects!A:A,0)),"") | B19: PRJ-001 | C19: =IFERROR(INDEX(Projects!E:E,MATCH("PRJ-001",Projects!A:A,0)),"") | D19: =IFERROR(INDEX(Projects!F:F,MATCH("PRJ-001",Projects!A:A,0)),"") | E19: =IFERROR(INDEX(Projects!J:J,MATCH("PRJ-001",Projects!A:A,0)),0) | F19: =IFERROR(INDEX(Projects!R:R,MATCH("PRJ-001",Projects!A:A,0)),0) | G19: =IFERROR(INDEX(Projects!U:U,MATCH("PRJ-001",Projects!A:A,0)),"") | H19: =IFERROR(INDEX(Projects!P:P,MATCH("PRJ-001",Projects!A:A,0)),0)
A20: =IFERROR(INDEX(Projects!C:C,MATCH("PRJ-002",Projects!A:A,0)),"") | B20: PRJ-002 | C20: =IFERROR(INDEX(Projects!E:E,MATCH("PRJ-002",Projects!A:A,0)),"") | D20: =IFERROR(INDEX(Projects!F:F,MATCH("PRJ-002",Projects!A:A,0)),"") | E20: =IFERROR(INDEX(Projects!J:J,MATCH("PRJ-002",Projects!A:A,0)),0) | F20: =IFERROR(INDEX(Projects!R:R,MATCH("PRJ-002",Projects!A:A,0)),0) | G20: =IFERROR(INDEX(Projects!U:U,MATCH("PRJ-002",Projects!A:A,0)),"") | H20: =IFERROR(INDEX(Projects!P:P,MATCH("PRJ-002",Projects!A:A,0)),0)
A23: SUPPLIER PERFORMANCE (lead time vs rating)
A24: Supplier | B24: Category | C24: Rating | D24: Lead days
A25: =Suppliers!B5:B20 | B25: =Suppliers!C5:C20 | C25: =Suppliers!H5:H20 | D25: =Suppliers!J5:J20

Sheet Settings
A1: SETTINGS
A2: Company, currency, thresholds · change values in column B
A4: Setting | B4: Value | C4: Notes
A5: Company Name | B5: Novality Store
A6: Product Name | B6: Home Renovation Management System
A7: Version | B7: 1.0.0
A8: Homeowner | B8: Alex Rivera
A9: Active Project ID | B9: PRJ-001 | C9: Default filter for dashboard KPIs.
A10: Active Property ID | B10: PROP-001
A11: Currency | B11: USD | C11: USD formulas use $ format; change display only.
A12: Currency Symbol | B12: $
A13: Language | B13: English
A14: Contingency % | B14: 0.1 | C14: Used by Finance + alerts. Default 10%.
A15: Fiscal Year Start | B15: 46023
A16: Today (system) | B16: 46258 | C16: Dashboard 'today'. Update if you archive this file later.
A17: Timezone | B17: America/Los_Angeles
A18: Tax Rate | B18: 0 | C18: Optional. Applied on Finance tax line if > 0.
A19: Default Payment Terms (days) | B19: 14
A20: Maintenance Reminder (days) | B20: 14
A21: Document Expiry Reminder (days) | B21: 30
A22: Low Contingency Threshold | B22: 0.1 | C22: Alert when remaining contingency / budget < this.
A23: Budget Overrun Alert % | B23: 0.1 | C23: Room/category alert when spent+committed exceeds planned by this.
A24: Support Email | B24: studio@novalitystore.example
A25: Primary Color | B25: #16352F
A26: Secondary Color | B26: #E8DDCB
A27: Accent Color | B27: #C86B4A
A28: Background Color | B28: #F8F6F1
A29: Success Color | B29: #719B7A
A30: Warning Color | B30: #D99A3D
A31: Danger Color | B31: #C75C5C

Sheet Lookups
A1: LOOKUPS
A2: Dropdown sources · do not delete · add values downward
A3: These lists power every dropdown in the workbook. Add new items in the first empty cell of a column.
A4: Project Status | B4: Project Phase | C4: Room Type | D4: Room Status | E4: Design Style | F4: Design Item | G4: Budget Category | H4: Expense Status | I4: Payment Method | J4: Trade | K4: Task Status | L4: Priority | M4: Material Status | N4: Doc Category | O4: Role | P4: Quote Status | Q4: Job Status | R4: Insp Result | S4: Payment Status | T4: CO Status | U4: Permit Status | V4: Maint Status | W4: Insight Severity | X4: Insight Status | Y4: Channel | Z4: Currency | AA4: Language | AB4: Property Type
A5: Planning | B5: Planning | C5: Kitchen | D5: Not Started | E5: Modern | F5: Mood Board | G5: Labor | H5: Planned | I5: ACH | J5: General Contractor | K5: To Do | L5: Critical | M5: Required | N5: Contract | O5: Homeowner | P5: Requested | Q5: Assigned | R5: Pass | S5: Draft | T5: Draft | U5: Not Started | V5: Upcoming | W5: Info | X5: New | Y5: App | Z5: USD | AA5: English | AB5: Single Family
A6: Active | B6: Design | C6: Living Room | D6: Design | E6: Minimal | F6: Color Palette | G6: Materials | H6: Committed | I6: Check | J6: Interior Designer | K6: Scheduled | L6: High | M6: Quoted | N6: Invoice | O6: Admin | P6: Received | Q6: Scheduled | R6: Conditional | S6: Scheduled | T6: Submitted | U6: Applied | V6: Due Soon | W6: Opportunity | X6: Accepted | Y6: Email | Z6: EUR | AA6: Spanish | AB6: Townhouse
A7: On Hold | B7: Permits | C7: Bedroom | D7: In Progress | E7: Scandinavian | F7: Material Board | G7: Design | H7: Paid | I7: Credit Card | J7: Architect | K7: In Progress | L7: Medium | M7: Approved | N7: Receipt | O7: Project Manager | P7: Compared | Q7: In Progress | R7: Fail | S7: Paid | T7: Approved | U7: In Review | V7: Overdue | W7: Warning | X7: In Progress | Y7: SMS | Z7: GBP | AA7: French | AB7: Condo
A8: Completed | B8: Demolition | C8: Primary Bedroom | D8: Punch List | E8: Luxury | F8: Furniture | G8: Permits | H8: Void | I8: Wire | J8: Cabinetry | K8: Inspection | L8: Low | M8: Ordered | N8: Floor Plan | O8: Interior Designer | P8: Accepted | Q8: Milestone Review | R8: Scheduled | S8: Overdue | T8: Rejected | U8: Approved | V8: Scheduled | W8: Critical | X8: Dismissed | Y8: Group Chat | Z8: CAD | AA8: German | AB8: Multi-Family
A9: Cancelled | B9: Rough-In | C9: Bathroom | D9: Complete | E9: Industrial | F9: Flooring | G9: Delivery | I9: Cash | J9: Electrical | K9: Completed | M9: Shipped | N9: Building Permit | O9: Contractor | P9: Rejected | Q9: Complete | S9: Disputed | T9: Implemented | U9: Expired | V9: Complete | X9: Resolved | Y9: Task Comment | Z9: AUD | AA9: Portuguese | AB9: Cabin
B10: Construction | C10: Primary Bathroom | E10: Traditional | F10: Wall | G10: Contingency | I10: Financing | J10: Plumbing | K10: Blocked | M10: Delivered | N10: License | O10: Subcontractor | P10: Expired | Q10: Disputed | U10: Closed | Y10: Photo Comment | Z10: INR | AA10: Arabic | AB10: Commercial
B11: Finishes | C11: Powder Room | E11: Transitional | F11: Ceiling | G11: Appliances | J11: Tile & Stone | M11: Installed | N11: Insurance | O11: Supplier | Y11: Voice | Z11: AED | AA11: Hindi
B12: Furnishing | C12: Dining Room | E12: Japandi | F12: Lighting | G12: Furniture | J12: Painting | M12: Returned | N12: Warranty | O12: Inspector
B13: Inspection | C13: Office | E13: Mediterranean | F13: Cabinetry | G13: Inspections | J13: Flooring | M13: Backordered | N13: Inspection Report | O13: Accountant
B14: Handover | C14: Garage | E14: Coastal | F14: Hardware | G14: Other | J14: Lighting | N14: Product Manual
B15: Maintenance | C15: Exterior | F15: 2D Floor Plan | J15: HVAC | N15: Photo
C16: Garden | F16: 3D Visualization | J16: Carpentry | N16: Agreement
C17: Laundry | F17: AI Concept | J17: Roofing | N17: Change Order
C18: Entry / Foyer | J18: Landscaping | N18: Quote
C19: Hallway | J19: Windows & Doors
C20: Basement | J20: Appliance
C21: Attic | J21: Inspection
C22: Custom

Sheet Audit Log
A1: AUDIT LOG
A2: Who changed what · append-only in the live product
A4: Audit ID | B4: Timestamp | C4: User ID | D4: User Name | E4: Module | F4: Record ID | G4: Action
A5: AUD-001 | B5: 46258.34 | C5: AD-001 | D5: Morgan Ellis | E5: AI Insights | F5: AI-005 | G5: Created contingency alert
A6: AUD-002 | B6: 46255.682 | C6: HO-001 | D6: Alex Rivera | E6: Change Orders | F6: CO-002 | G6: Approved design direction (pending formal sign)
A7: AUD-003 | B7: 46255.587 | C7: DS-001 | D7: Sofia Alvarez | E7: Design Studio | F7: DSN-006 | G7: Published porcelain material board
A8: AUD-004 | B8: 46254.319 | C8: CT-001 | D8: Maya Chen | E8: Materials | F8: MAT-001 | G8: Marked cabinets Delivered
A9: AUD-005 | B9: 46252.71 | C9: AC-001 | D9: Jamie Cole | E9: Payments | F9: PAY-008 | G9: Recorded Ironwood August draw
A10: AUD-006 | B10: 46248.458 | C10: PM-001 | D10: Marcus Webb | E10: Inspections | F10: INS-002 | G10: Attached electrical rough report
A11: AUD-007 | B11: 46246.626 | C11: IN-001 | D11: Riley Grant | E11: Inspections | F11: INS-002 | G11: Result = Pass
A12: AUD-008 | B12: 46236.385 | C12: HO-001 | D12: Alex Rivera | E12: Payments | F12: PAY-005 | G12: Wired Cascade deposit
A13: AUD-009 | B13: 46160.417 | C13: DS-001 | D13: Sofia Alvarez | E13: Change Orders | F13: CO-001 | G13: Implemented marble→porcelain
A14: AUD-010 | B14: 46085.698 | C14: HO-001 | D14: Alex Rivera | E14: Documents | F14: DOC-001 | G14: Signed GC agreement
